Workbook

Sheet LerXml
A1: 11222333000181 | B1: NFE | C1: DT EMISSÃO | D1: UF | E1: Regime Tributário | F1: DESCRIÇÃO DO PRODUTO | G1: NCM | H1: CEST | I1: CFOP | J1: QTD | K1: VLR UNIT | L1: FRETE | M1: SEGURO | N1: DESCONTO | O1: OUTRAS DESPESAS | P1: VALOR TOTAL | Q1: VLR IPI | R1: ORIGEM | S1: CST | T1: ALQ ICMS NFE | U1: VLR ICMS NFE | V1: B.C ICMS ST DESTACADO | W1: ICMS ST DESTACADO | X1: MVA ICMS ST DESTACADO | Y1: Finalidade | Z1: MVA CEST | AA1: MVA NCM | AB1: MVA Escolhido | AC1: É ST? | AD1: NCM BIT? | AE1: NCM ANEXO I? | AF1: NCM ANEXO II? | AG1: Beneficio utilizado | AH1: Red B.C Antes do MVA | AI1: Total do Produto | AJ1: B.C ST Ajustado com o MVA | AK1: ICMS Interno Calculado a 17% | AL1: Crédito de ICMS Nfe | AM1: ICMS ST Calculado A Recolher | AN1: B.C Reduzida BIT (41,17%) | AO1: Déb. de ICMS Interno 17% B.C Reduzida | AP1: Credito ICMS Nfe (BIT) | AQ1: ICMS ST Calculado A Recolher BIT | AR1: MVA % Convenio 52/91 | AS1: BC OP PROP RED 73,33% OU 58,33% | AT1: BC OP PROD + MVA | AU1: CRÉDITO ICMS Se 4% = Nfe | AV1: Déb. de ICMS Interno 17% 51,77% OU 32,95% | AW1: ICMS ST Calculado A Recolher Conv 52/91 | AX1: Diferença de ICMS ST a Recolher (Cód 2817 | AY1: Aliquota Interestadual p/ calculo de DIFAL | AZ1: B.C Difal USO/CONS Imobilizado CG | BA1: Difal USO/CONS Imobilizado CG | BB1: Difal USO/CONS Imobilizado CONVENIO | BC1: B.C Difal USO/CONS Imobilizado ST | BD1: ICMS CALCULADO A 17% - ST | BE1: Difal USO/CONS Imobilizado ST | BF1: ICMS_OUTROS | BG1: CFOP Entrada
D2: =CONCATENATE(A1, " ",TEXT(MEDIAN(C3:C84750),"mm-aaaa")," - ",TEXT(E2,"dd-mm-aaaa hh-mm")) -> #VALUE! | E2: =NOW() -> 46297.35 | F2: Não mexer nessa linha - Siga as instruções | M2: BIT | N2: ANEXO I | O2: ANEXO II | P2: Pneus | Q2: - | R2: SIM | S2: NÃO | U2: CONSUMO | V2: REVENDA | Y2: REVENDA | Z2: =IF(B2="","",(IFERROR(VLOOKUP(H2,Dados!A$3:B$15000,2,0),"Não Encontrado"))) | AA2: =IF(B2="","",(IFERROR(VLOOKUP(G2,Dados!C$3:E$15000,3,0),"Não Encontrado"))) | AB2: =IFERROR(IF(Z2<>"Não Encontrado",Z2,IF(AA2<>"Não Encontrado",AA2,"")),"") | AC2: =IF(B2="","",IF(AB2="","NÃO","SIM")) | AD2: =IFERROR(VLOOKUP(G2,Dados!$P$3:$R$500,3,0),"") | AE2: =IFERROR(VLOOKUP(G2,Dados!$K$3:$L$500,2,0),"") | AF2: =IFERROR(VLOOKUP(G2,Dados!$M$3:$N$500,2,0),"") | AG2: =IF(F2="","",IF(AND(AD2="",AE2="",AF2=""),"-",IF(AND(AD2="BIT",AE2="",AF2=""),"BIT",IF(AND(AE2="ANEXO I",AD2="",AF2=""),"ANEXO I",IF(AND(AF2="ANEXO II",AD2="",AE2=""),"ANEXO II","Escolher"))))) -> - | AH2: =IF(AG2<>"Pneus","",IFERROR(VLOOKUP(R2,Dados!$X$2:$Z$5,3,0)*(AI2-Q2),VLOOKUP(D2,Dados!$X$7:$Z$33,3,0)*(AI2-Q2))) | AI2: =IF(B2="","",P2+Q2+O2+M2+L2-N2) | AJ2: =IFERROR(IF(AND(AC2="SIM",AG2="-",Y2="REVENDA"),(AB2/1+1)*AI2,IF(AND(AC2="SIM",AG2="Pneus",Y2="REVENDA"),(AB2/1+1)*(AI2-AH2),"")),"") | AK2: =IF(AJ2="","",AJ2*17%) | AL2: =IFERROR(IF(AC2="NÃO","",IF(AK2="","",IF(E2="Simples Nacional",BF2,IF(T2=0.12,U2*0.5833337002,IF(T2=0,AI2*0.07,U2))))),"") | AM2: =IFERROR(IF(AC2="NÃO","",IF(OR(AG2="-",AG2="Pneus"),AK2-AL2,"")),"") | AN2: =IF(AND(Y2="REVENDA",AC2="SIM",AG2="BIT"),((AB2/1+1)*AI2)*0.4117,"") | AO2: =IF(AN2="","",AN2*17%) | AP2: =IF(AN2="","",IF(T2=0.12,(U2*0.4117)*0.4117,IF(T2=0,(AI2*0.07)*0.4117,U2*0.4117))) | AQ2: =IF(AN2="","",AO2-AP2) | AR2: =IFERROR(IF(AND(AC2="SIM",Y2="REVENDA",LEFT(AG2,5)="ANEXO")*OR(AE2="ANEXO I",AF2="ANEXO II"),VLOOKUP(H2,Dados!G:I,2,0),""),"INSERIR MVA") | AS2: =IF(LEFT(AG2,5)="ANEXO",VLOOKUP(AG2,Dados!$X$111:$Z$112,2,0)*(AI2-Q2),"") | AT2: =IFERROR(IF(AR2="","",(AI2*AR2)+AI2),"INSERIR MVA") | AU2: =IF(AT2="","",IF(AY2=0.04,U2,AS2*AY2)) | AV2: =IFERROR(IF(AU2="","",(VLOOKUP(AG2,Dados!$X$111:$Z$112,3,0)*AT2*0.17)),"INSERIR MVA") | AW2: =IFERROR(IF(AR2="","",AV2-AU2),"") | AX2: =IFERROR(IF(AC2="NÃO","",IF(AM2<>"",AM2-W2,IF(AQ2<>"",AQ2-W2,IF(AW2<>"",AW2-W2,"")))),"") | AY2: =IFERROR(IF(ISNA(VLOOKUP(R2,Dados!$X$2:$Y$5,2,0)),VLOOKUP(D2,Dados!$X$7:$Y$33,2,0),VLOOKUP(R2,Dados!$X$2:$Y$5,2,0)),"") | AZ2: =IF(C2="","",IF(AND(Y2="CONSUMO",AC2="NÃO")*OR(AG2="-",AG2="BIT"),IF(E2<>"",(AI2-(P2+L2-N2+Q2)*AY2)/0.83),"")) | BA2: =IF(AZ2="","",AZ2*0.17-((P2+L2-N2+Q2)*AY2)) | BB2: =IF(AND(Y2="CONSUMO",AG2="ANEXO I",AY2>4%),(AI2-(P2+L2-N2+Q2)*0.0514)/0.83*(0.5177)*(0.17)-AI2*0.0514,IF(AND(Y2="CONSUMO",AG2="ANEXO II",AY2>4%),(AI2-(P2+L2-N2+Q2)*0.041)/0.83*(0.3295)*(0.17)-AI2*0.041,IF(AND(Y2="CONSUMO",AG2="ANEXO I",AY2=4%),(AI2-(P2+L2-N2+Q2)*0.04)/0.83*(0.5177)*(0.17)-AI2*0.04,IF(AND(Y2="CONSUMO",AG2="ANEXO II",AY2=4%),(AI2-(P2+L2-N2+Q2)*0.04)/0.83*(0.3295)*(0.17)-AI2*0.04,"")))) | BC2: =IF(C2="","",IF(AND(Y2="CONSUMO",AC2="SIM")*OR(AG2="-",AG2="BIT"),IF(E2<>"",(AI2-(P2+L2-N2+Q2)*AY2)/0.83),"")) | BD2: =IF(BC2="","",BC2*0.17) | BE2: =IF(I2=6908,0,IF(BC2="","",BD2-((P2+L2-N2+Q2)*AY2))) | BF2: =IF(B2="","",IF(OR(B2="",E2="Regime Normal"),0,(AI2-Q2)*VLOOKUP(R2,Dados!$X$98:$Y$108,2,0))) | BG2: =IFERROR(VLOOKUP(I2,Dados!$AC$27:$AD$43,2,0),IF(B2="","",IF(D2<>"MT",IF(AND(AC2="SIM",Y2="Revenda"),"2403",IF(AND(AC2="SIM",Y2="Consumo"),"2407",IF(AND(AC2="NÃO",Y2="Revenda"),"2102",IF(AND(AC2="NÃO",Y2="Consumo"),"2556",)))),REPLACE(I2,1,1,1))))
Z3: =IF(B3="","",(IFERROR(VLOOKUP(H3,Dados!A$3:B$15000,2,0),"Não Encontrado"))) | AA3: =IF(B3="","",(IFERROR(VLOOKUP(G3,Dados!C$3:E$15000,3,0),"Não Encontrado"))) | AB3: =IFERROR(IF(Z3<>"Não Encontrado",Z3,IF(AA3<>"Não Encontrado",AA3,"")),"") | AC3: =IF(B3="","",IF(AB3="","NÃO","SIM")) | AD3: =IFERROR(VLOOKUP(G3,Dados!$P$3:$R$500,3,0),"") | AE3: =IFERROR(VLOOKUP(G3,Dados!$K$3:$L$500,2,0),"") | AF3: =IFERROR(VLOOKUP(G3,Dados!$M$3:$N$500,2,0),"") | AG3: =IF(F3="","",IF(AND(AD3="",AE3="",AF3=""),"-",IF(AND(AD3="BIT",AE3="",AF3=""),"BIT",IF(AND(AE3="ANEXO I",AD3="",AF3=""),"ANEXO I",IF(AND(AF3="ANEXO II",AD3="",AE3=""),"ANEXO II","Escolher"))))) | AH3: =IF(AG3<>"Pneus","",IFERROR(VLOOKUP(R3,Dados!$X$2:$Z$5,3,0)*(AI3-Q3),VLOOKUP(D3,Dados!$X$7:$Z$33,3,0)*(AI3-Q3))) | AI3: =IF(B3="","",P3+Q3+O3+M3+L3-N3) | AJ3: =IFERROR(IF(AND(AC3="SIM",AG3="-",Y3="REVENDA"),(AB3/1+1)*AI3,IF(AND(AC3="SIM",AG3="Pneus",Y3="REVENDA"),(AB3/1+1)*(AI3-AH3),"")),"") | AK3: =IF(AJ3="","",AJ3*17%) | AL3: =IFERROR(IF(AC3="NÃO","",IF(AK3="","",IF(E3="Simples Nacional",BF3,IF(T3=0.12,U3*0.5833337002,IF(T3=0,AI3*0.07,U3))))),"") | AM3: =IFERROR(IF(AC3="NÃO","",IF(OR(AG3="-",AG3="Pneus"),AK3-AL3,"")),"") | AN3: =IF(AND(Y3="REVENDA",AC3="SIM",AG3="BIT"),((AB3/1+1)*AI3)*0.4117,"") | AO3: =IF(AN3="","",AN3*17%) | AP3: =IF(AN3="","",IF(T3=0.12,(U3*0.4117)*0.4117,IF(T3=0,(AI3*0.07)*0.4117,U3*0.4117))) | AQ3: =IF(AN3="","",AO3-AP3) | AR3: =IFERROR(IF(AND(AC3="SIM",Y3="REVENDA",LEFT(AG3,5)="ANEXO")*OR(AE3="ANEXO I",AF3="ANEXO II"),VLOOKUP(H3,Dados!G:I,2,0),""),"INSERIR MVA") | AS3: =IF(LEFT(AG3,5)="ANEXO",VLOOKUP(AG3,Dados!$X$111:$Z$112,2,0)*(AI3-Q3),"") | AT3: =IFERROR(IF(AR3="","",(AI3*AR3)+AI3),"INSERIR MVA") | AU3: =IF(AT3="","",IF(AY3=0.04,U3,AS3*AY3)) | AV3: =IFERROR(IF(AU3="","",(VLOOKUP(AG3,Dados!$X$111:$Z$112,3,0)*AT3*0.17)),"INSERIR MVA") | AW3: =IFERROR(IF(AR3="","",AV3-AU3),"") | AX3: =IFERROR(IF(AC3="NÃO","",IF(AM3<>"",AM3-W3,IF(AQ3<>"",AQ3-W3,IF(AW3<>"",AW3-W3,"")))),"") | AY3: =IFERROR(IF(ISNA(VLOOKUP(R3,Dados!$X$2:$Y$5,2,0)),VLOOKUP(D3,Dados!$X$7:$Y$33,2,0),VLOOKUP(R3,Dados!$X$2:$Y$5,2,0)),"") | AZ3: =IF(C3="","",IF(AND(Y3="CONSUMO",AC3="NÃO")*OR(AG3="-",AG3="BIT"),IF(E3<>"",(AI3-(P3+L3-N3+Q3)*AY3)/0.83),"")) | BA3: =IF(AZ3="","",AZ3*0.17-((P3+L3-N3+Q3)*AY3)) | BB3: =IF(AND(Y3="CONSUMO",AG3="ANEXO I",AY3>4%),(AI3-(P3+L3-N3+Q3)*0.0514)/0.83*(0.5177)*(0.17)-AI3*0.0514,IF(AND(Y3="CONSUMO",AG3="ANEXO II",AY3>4%),(AI3-(P3+L3-N3+Q3)*0.041)/0.83*(0.3295)*(0.17)-AI3*0.041,IF(AND(Y3="CONSUMO",AG3="ANEXO I",AY3=4%),(AI3-(P3+L3-N3+Q3)*0.04)/0.83*(0.5177)*(0.17)-AI3*0.04,IF(AND(Y3="CONSUMO",AG3="ANEXO II",AY3=4%),(AI3-(P3+L3-N3+Q3)*0.04)/0.83*(0.3295)*(0.17)-AI3*0.04,"")))) | BC3: =IF(C3="","",IF(AND(Y3="CONSUMO",AC3="SIM")*OR(AG3="-",AG3="BIT"),IF(E3<>"",(AI3-(P3+L3-N3+Q3)*AY3)/0.83),"")) | BD3: =IF(BC3="","",BC3*0.17) | BE3: =IF(I3=6908,0,IF(BC3="","",BD3-((P3+L3-N3+Q3)*AY3))) | BF3: =IF(B3="","",IF(OR(B3="",E3="Regime Normal"),0,(AI3-Q3)*VLOOKUP(R3,Dados!$X$98:$Y$108,2,0))) | BG3: =IFERROR(VLOOKUP(I3,Dados!$AC$27:$AD$43,2,0),IF(B3="","",IF(D3<>"MT",IF(AND(AC3="SIM",Y3="Revenda"),"2403",IF(AND(AC3="SIM",Y3="Consumo"),"2407",IF(AND(AC3="NÃO",Y3="Revenda"),"2102",IF(AND(AC3="NÃO",Y3="Consumo"),"2556",)))),REPLACE(I3,1,1,1))))
Z4: =IF(B4="","",(IFERROR(VLOOKUP(H4,Dados!A$3:B$15000,2,0),"Não Encontrado"))) | AA4: =IF(B4="","",(IFERROR(VLOOKUP(G4,Dados!C$3:E$15000,3,0),"Não Encontrado"))) | AB4: =IFERROR(IF(Z4<>"Não Encontrado",Z4,IF(AA4<>"Não Encontrado",AA4,"")),"") | AC4: =IF(B4="","",IF(AB4="","NÃO","SIM")) | AD4: =IFERROR(VLOOKUP(G4,Dados!$P$3:$R$500,3,0),"") | AE4: =IFERROR(VLOOKUP(G4,Dados!$K$3:$L$500,2,0),"") | AF4: =IFERROR(VLOOKUP(G4,Dados!$M$3:$N$500,2,0),"") | AG4: =IF(F4="","",IF(AND(AD4="",AE4="",AF4=""),"-",IF(AND(AD4="BIT",AE4="",AF4=""),"BIT",IF(AND(AE4="ANEXO I",AD4="",AF4=""),"ANEXO I",IF(AND(AF4="ANEXO II",AD4="",AE4=""),"ANEXO II","Escolher"))))) | AH4: =IF(AG4<>"Pneus","",IFERROR(VLOOKUP(R4,Dados!$X$2:$Z$5,3,0)*(AI4-Q4),VLOOKUP(D4,Dados!$X$7:$Z$33,3,0)*(AI4-Q4))) | AI4: =IF(B4="","",P4+Q4+O4+M4+L4-N4) | AJ4: =IFERROR(IF(AND(AC4="SIM",AG4="-",Y4="REVENDA"),(AB4/1+1)*AI4,IF(AND(AC4="SIM",AG4="Pneus",Y4="REVENDA"),(AB4/1+1)*(AI4-AH4),"")),"") | AK4: =IF(AJ4="","",AJ4*17%) | AL4: =IFERROR(IF(AC4="NÃO","",IF(AK4="","",IF(E4="Simples Nacional",BF4,IF(T4=0.12,U4*0.5833337002,IF(T4=0,AI4*0.07,U4))))),"") | AM4: =IFERROR(IF(AC4="NÃO","",IF(OR(AG4="-",AG4="Pneus"),AK4-AL4,"")),"") | AN4: =IF(AND(Y4="REVENDA",AC4="SIM",AG4="BIT"),((AB4/1+1)*AI4)*0.4117,"") | AO4: =IF(AN4="","",AN4*17%) | AP4: =IF(AN4="","",IF(T4=0.12,(U4*0.4117)*0.4117,IF(T4=0,(AI4*0.07)*0.4117,U4*0.4117))) | AQ4: =IF(AN4="","",AO4-AP4) | AR4: =IFERROR(IF(AND(AC4="SIM",Y4="REVENDA",LEFT(AG4,5)="ANEXO")*OR(AE4="ANEXO I",AF4="ANEXO II"),VLOOKUP(H4,Dados!G:I,2,0),""),"INSERIR MVA") | AS4: =IF(LEFT(AG4,5)="ANEXO",VLOOKUP(AG4,Dados!$X$111:$Z$112,2,0)*(AI4-Q4),"") | AT4: =IFERROR(IF(AR4="","",(AI4*AR4)+AI4),"INSERIR MVA") | AU4: =IF(AT4="","",IF(AY4=0.04,U4,AS4*AY4)) | AV4: =IFERROR(IF(AU4="","",(VLOOKUP(AG4,Dados!$X$111:$Z$112,3,0)*AT4*0.17)),"INSERIR MVA") | AW4: =IFERROR(IF(AR4="","",AV4-AU4),"") | AX4: =IFERROR(IF(AC4="NÃO","",IF(AM4<>"",AM4-W4,IF(AQ4<>"",AQ4-W4,IF(AW4<>"",AW4-W4,"")))),"") | AY4: =IFERROR(IF(ISNA(VLOOKUP(R4,Dados!$X$2:$Y$5,2,0)),VLOOKUP(D4,Dados!$X$7:$Y$33,2,0),VLOOKUP(R4,Dados!$X$2:$Y$5,2,0)),"") | AZ4: =IF(C4="","",IF(AND(Y4="CONSUMO",AC4="NÃO")*OR(AG4="-",AG4="BIT"),IF(E4<>"",(AI4-(P4+L4-N4+Q4)*AY4)/0.83),"")) | BA4: =IF(AZ4="","",AZ4*0.17-((P4+L4-N4+Q4)*AY4)) | BB4: =IF(AND(Y4="CONSUMO",AG4="ANEXO I",AY4>4%),(AI4-(P4+L4-N4+Q4)*0.0514)/0.83*(0.5177)*(0.17)-AI4*0.0514,IF(AND(Y4="CONSUMO",AG4="ANEXO II",AY4>4%),(AI4-(P4+L4-N4+Q4)*0.041)/0.83*(0.3295)*(0.17)-AI4*0.041,IF(AND(Y4="CONSUMO",AG4="ANEXO I",AY4=4%),(AI4-(P4+L4-N4+Q4)*0.04)/0.83*(0.5177)*(0.17)-AI4*0.04,IF(AND(Y4="CONSUMO",AG4="ANEXO II",AY4=4%),(AI4-(P4+L4-N4+Q4)*0.04)/0.83*(0.3295)*(0.17)-AI4*0.04,"")))) | BC4: =IF(C4="","",IF(AND(Y4="CONSUMO",AC4="SIM")*OR(AG4="-",AG4="BIT"),IF(E4<>"",(AI4-(P4+L4-N4+Q4)*AY4)/0.83),"")) | BD4: =IF(BC4="","",BC4*0.17) | BE4: =IF(I4=6908,0,IF(BC4="","",BD4-((P4+L4-N4+Q4)*AY4))) | BF4: =IF(B4="","",IF(OR(B4="",E4="Regime Normal"),0,(AI4-Q4)*VLOOKUP(R4,Dados!$X$98:$Y$108,2,0))) | BG4: =IFERROR(VLOOKUP(I4,Dados!$AC$27:$AD$43,2,0),IF(B4="","",IF(D4<>"MT",IF(AND(AC4="SIM",Y4="Revenda"),"2403",IF(AND(AC4="SIM",Y4="Consumo"),"2407",IF(AND(AC4="NÃO",Y4="Revenda"),"2102",IF(AND(AC4="NÃO",Y4="Consumo"),"2556",)))),REPLACE(I4,1,1,1))))
Z5: =IF(B5="","",(IFERROR(VLOOKUP(H5,Dados!A$3:B$15000,2,0),"Não Encontrado"))) | AA5: =IF(B5="","",(IFERROR(VLOOKUP(G5,Dados!C$3:E$15000,3,0),"Não Encontrado"))) | AB5: =IFERROR(IF(Z5<>"Não Encontrado",Z5,IF(AA5<>"Não Encontrado",AA5,"")),"") | AC5: =IF(B5="","",IF(AB5="","NÃO","SIM")) | AD5: =IFERROR(VLOOKUP(G5,Dados!$P$3:$R$500,3,0),"") | AE5: =IFERROR(VLOOKUP(G5,Dados!$K$3:$L$500,2,0),"") | AF5: =IFERROR(VLOOKUP(G5,Dados!$M$3:$N$500,2,0),"") | AG5: =IF(F5="","",IF(AND(AD5="",AE5="",AF5=""),"-",IF(AND(AD5="BIT",AE5="",AF5=""),"BIT",IF(AND(AE5="ANEXO I",AD5="",AF5=""),"ANEXO I",IF(AND(AF5="ANEXO II",AD5="",AE5=""),"ANEXO II","Escolher"))))) | AH5: =IF(AG5<>"Pneus","",IFERROR(VLOOKUP(R5,Dados!$X$2:$Z$5,3,0)*(AI5-Q5),VLOOKUP(D5,Dados!$X$7:$Z$33,3,0)*(AI5-Q5))) | AI5: =IF(B5="","",P5+Q5+O5+M5+L5-N5) | AJ5: =IFERROR(IF(AND(AC5="SIM",AG5="-",Y5="REVENDA"),(AB5/1+1)*AI5,IF(AND(AC5="SIM",AG5="Pneus",Y5="REVENDA"),(AB5/1+1)*(AI5-AH5),"")),"") | AK5: =IF(AJ5="","",AJ5*17%) | AL5: =IFERROR(IF(AC5="NÃO","",IF(AK5="","",IF(E5="Simples Nacional",BF5,IF(T5=0.12,U5*0.5833337002,IF(T5=0,AI5*0.07,U5))))),"") | AM5: =IFERROR(IF(AC5="NÃO","",IF(OR(AG5="-",AG5="Pneus"),AK5-AL5,"")),"") | AN5: =IF(AND(Y5="REVENDA",AC5="SIM",AG5="BIT"),((AB5/1+1)*AI5)*0.4117,"") | AO5: =IF(AN5="","",AN5*17%) | AP5: =IF(AN5="","",IF(T5=0.12,(U5*0.4117)*0.4117,IF(T5=0,(AI5*0.07)*0.4117,U5*0.4117))) | AQ5: =IF(AN5="","",AO5-AP5) | AR5: =IFERROR(IF(AND(AC5="SIM",Y5="REVENDA",LEFT(AG5,5)="ANEXO")*OR(AE5="ANEXO I",AF5="ANEXO II"),VLOOKUP(H5,Dados!G:I,2,0),""),"INSERIR MVA") | AS5: =IF(LEFT(AG5,5)="ANEXO",VLOOKUP(AG5,Dados!$X$111:$Z$112,2,0)*(AI5-Q5),"") | AT5: =IFERROR(IF(AR5="","",(AI5*AR5)+AI5),"INSERIR MVA") | AU5: =IF(AT5="","",IF(AY5=0.04,U5,AS5*AY5)) | AV5: =IFERROR(IF(AU5="","",(VLOOKUP(AG5,Dados!$X$111:$Z$112,3,0)*AT5*0.17)),"INSERIR MVA") | AW5: =IFERROR(IF(AR5="","",AV5-AU5),"") | AX5: =IFERROR(IF(AC5="NÃO","",IF(AM5<>"",AM5-W5,IF(AQ5<>"",AQ5-W5,IF(AW5<>"",AW5-W5,"")))),"") | AY5: =IFERROR(IF(ISNA(VLOOKUP(R5,Dados!$X$2:$Y$5,2,0)),VLOOKUP(D5,Dados!$X$7:$Y$33,2,0),VLOOKUP(R5,Dados!$X$2:$Y$5,2,0)),"") | AZ5: =IF(C5="","",IF(AND(Y5="CONSUMO",AC5="NÃO")*OR(AG5="-",AG5="BIT"),IF(E5<>"",(AI5-(P5+L5-N5+Q5)*AY5)/0.83),"")) | BA5: =IF(AZ5="","",AZ5*0.17-((P5+L5-N5+Q5)*AY5)) | BB5: =IF(AND(Y5="CONSUMO",AG5="ANEXO I",AY5>4%),(AI5-(P5+L5-N5+Q5)*0.0514)/0.83*(0.5177)*(0.17)-AI5*0.0514,IF(AND(Y5="CONSUMO",AG5="ANEXO II",AY5>4%),(AI5-(P5+L5-N5+Q5)*0.041)/0.83*(0.3295)*(0.17)-AI5*0.041,IF(AND(Y5="CONSUMO",AG5="ANEXO I",AY5=4%),(AI5-(P5+L5-N5+Q5)*0.04)/0.83*(0.5177)*(0.17)-AI5*0.04,IF(AND(Y5="CONSUMO",AG5="ANEXO II",AY5=4%),(AI5-(P5+L5-N5+Q5)*0.04)/0.83*(0.3295)*(0.17)-AI5*0.04,"")))) | BC5: =IF(C5="","",IF(AND(Y5="CONSUMO",AC5="SIM")*OR(AG5="-",AG5="BIT"),IF(E5<>"",(AI5-(P5+L5-N5+Q5)*AY5)/0.83),"")) | BD5: =IF(BC5="","",BC5*0.17) | BE5: =IF(I5=6908,0,IF(BC5="","",BD5-((P5+L5-N5+Q5)*AY5))) | BF5: =IF(B5="","",IF(OR(B5="",E5="Regime Normal"),0,(AI5-Q5)*VLOOKUP(R5,Dados!$X$98:$Y$108,2,0))) | BG5: =IFERROR(VLOOKUP(I5,Dados!$AC$27:$AD$43,2,0),IF(B5="","",IF(D5<>"MT",IF(AND(AC5="SIM",Y5="Revenda"),"2403",IF(AND(AC5="SIM",Y5="Consumo"),"2407",IF(AND(AC5="NÃO",Y5="Revenda"),"2102",IF(AND(AC5="NÃO",Y5="Consumo"),"2556",)))),REPLACE(I5,1,1,1))))
Z6: =IF(B6="","",(IFERROR(VLOOKUP(H6,Dados!A$3:B$15000,2,0),"Não Encontrado"))) | AA6: =IF(B6="","",(IFERROR(VLOOKUP(G6,Dados!C$3:E$15000,3,0),"Não Encontrado"))) | AB6: =IFERROR(IF(Z6<>"Não Encontrado",Z6,IF(AA6<>"Não Encontrado",AA6,"")),"") | AC6: =IF(B6="","",IF(AB6="","NÃO","SIM")) | AD6: =IFERROR(VLOOKUP(G6,Dados!$P$3:$R$500,3,0),"") | AE6: =IFERROR(VLOOKUP(G6,Dados!$K$3:$L$500,2,0),"") | AF6: =IFERROR(VLOOKUP(G6,Dados!$M$3:$N$500,2,0),"") | AG6: =IF(F6="","",IF(AND(AD6="",AE6="",AF6=""),"-",IF(AND(AD6="BIT",AE6="",AF6=""),"BIT",IF(AND(AE6="ANEXO I",AD6="",AF6=""),"ANEXO I",IF(AND(AF6="ANEXO II",AD6="",AE6=""),"ANEXO II","Escolher"))))) | AH6: =IF(AG6<>"Pneus","",IFERROR(VLOOKUP(R6,Dados!$X$2:$Z$5,3,0)*(AI6-Q6),VLOOKUP(D6,Dados!$X$7:$Z$33,3,0)*(AI6-Q6))) | AI6: =IF(B6="","",P6+Q6+O6+M6+L6-N6) | AJ6: =IFERROR(IF(AND(AC6="SIM",AG6="-",Y6="REVENDA"),(AB6/1+1)*AI6,IF(AND(AC6="SIM",AG6="Pneus",Y6="REVENDA"),(AB6/1+1)*(AI6-AH6),"")),"") | AK6: =IF(AJ6="","",AJ6*17%) | AL6: =IFERROR(IF(AC6="NÃO","",IF(AK6="","",IF(E6="Simples Nacional",BF6,IF(T6=0.12,U6*0.5833337002,IF(T6=0,AI6*0.07,U6))))),"") | AM6: =IFERROR(IF(AC6="NÃO","",IF(OR(AG6="-",AG6="Pneus"),AK6-AL6,"")),"") | AN6: =IF(AND(Y6="REVENDA",AC6="SIM",AG6="BIT"),((AB6/1+1)*AI6)*0.4117,"") | AO6: =IF(AN6="","",AN6*17%) | AP6: =IF(AN6="","",IF(T6=0.12,(U6*0.4117)*0.4117,IF(T6=0,(AI6*0.07)*0.4117,U6*0.4117))) | AQ6: =IF(AN6="","",AO6-AP6) | AR6: =IFERROR(IF(AND(AC6="SIM",Y6="REVENDA",LEFT(AG6,5)="ANEXO")*OR(AE6="ANEXO I",AF6="ANEXO II"),VLOOKUP(H6,Dados!G:I,2,0),""),"INSERIR MVA") | AS6: =IF(LEFT(AG6,5)="ANEXO",VLOOKUP(AG6,Dados!$X$111:$Z$112,2,0)*(AI6-Q6),"") | AT6: =IFERROR(IF(AR6="","",(AI6*AR6)+AI6),"INSERIR MVA") | AU6: =IF(AT6="","",IF(AY6=0.04,U6,AS6*AY6)) | AV6: =IFERROR(IF(AU6="","",(VLOOKUP(AG6,Dados!$X$111:$Z$112,3,0)*AT6*0.17)),"INSERIR MVA") | AW6: =IFERROR(IF(AR6="","",AV6-AU6),"") | AX6: =IFERROR(IF(AC6="NÃO","",IF(AM6<>"",AM6-W6,IF(AQ6<>"",AQ6-W6,IF(AW6<>"",AW6-W6,"")))),"") | AY6: =IFERROR(IF(ISNA(VLOOKUP(R6,Dados!$X$2:$Y$5,2,0)),VLOOKUP(D6,Dados!$X$7:$Y$33,2,0),VLOOKUP(R6,Dados!$X$2:$Y$5,2,0)),"") | AZ6: =IF(C6="","",IF(AND(Y6="CONSUMO",AC6="NÃO")*OR(AG6="-",AG6="BIT"),IF(E6<>"",(AI6-(P6+L6-N6+Q6)*AY6)/0.83),"")) | BA6: =IF(AZ6="","",AZ6*0.17-((P6+L6-N6+Q6)*AY6)) | BB6: =IF(AND(Y6="CONSUMO",AG6="ANEXO I",AY6>4%),(AI6-(P6+L6-N6+Q6)*0.0514)/0.83*(0.5177)*(0.17)-AI6*0.0514,IF(AND(Y6="CONSUMO",AG6="ANEXO II",AY6>4%),(AI6-(P6+L6-N6+Q6)*0.041)/0.83*(0.3295)*(0.17)-AI6*0.041,IF(AND(Y6="CONSUMO",AG6="ANEXO I",AY6=4%),(AI6-(P6+L6-N6+Q6)*0.04)/0.83*(0.5177)*(0.17)-AI6*0.04,IF(AND(Y6="CONSUMO",AG6="ANEXO II",AY6=4%),(AI6-(P6+L6-N6+Q6)*0.04)/0.83*(0.3295)*(0.17)-AI6*0.04,"")))) | BC6: =IF(C6="","",IF(AND(Y6="CONSUMO",AC6="SIM")*OR(AG6="-",AG6="BIT"),IF(E6<>"",(AI6-(P6+L6-N6+Q6)*AY6)/0.83),"")) | BD6: =IF(BC6="","",BC6*0.17) | BE6: =IF(I6=6908,0,IF(BC6="","",BD6-((P6+L6-N6+Q6)*AY6))) | BF6: =IF(B6="","",IF(OR(B6="",E6="Regime Normal"),0,(AI6-Q6)*VLOOKUP(R6,Dados!$X$98:$Y$108,2,0))) | BG6: =IFERROR(VLOOKUP(I6,Dados!$AC$27:$AD$43,2,0),IF(B6="","",IF(D6<>"MT",IF(AND(AC6="SIM",Y6="Revenda"),"2403",IF(AND(AC6="SIM",Y6="Consumo"),"2407",IF(AND(AC6="NÃO",Y6="Revenda"),"2102",IF(AND(AC6="NÃO",Y6="Consumo"),"2556",)))),REPLACE(I6,1,1,1))))
Z7: =IF(B7="","",(IFERROR(VLOOKUP(H7,Dados!A$3:B$15000,2,0),"Não Encontrado"))) | AA7: =IF(B7="","",(IFERROR(VLOOKUP(G7,Dados!C$3:E$15000,3,0),"Não Encontrado"))) | AB7: =IFERROR(IF(Z7<>"Não Encontrado",Z7,IF(AA7<>"Não Encontrado",AA7,"")),"") | AC7: =IF(B7="","",IF(AB7="","NÃO","SIM")) | AD7: =IFERROR(VLOOKUP(G7,Dados!$P$3:$R$500,3,0),"") | AE7: =IFERROR(VLOOKUP(G7,Dados!$K$3:$L$500,2,0),"") | AF7: =IFERROR(VLOOKUP(G7,Dados!$M$3:$N$500,2,0),"") | AG7: =IF(F7="","",IF(AND(AD7="",AE7="",AF7=""),"-",IF(AND(AD7="BIT",AE7="",AF7=""),"BIT",IF(AND(AE7="ANEXO I",AD7="",AF7=""),"ANEXO I",IF(AND(AF7="ANEXO II",AD7="",AE7=""),"ANEXO II","Escolher"))))) | AH7: =IF(AG7<>"Pneus","",IFERROR(VLOOKUP(R7,Dados!$X$2:$Z$5,3,0)*(AI7-Q7),VLOOKUP(D7,Dados!$X$7:$Z$33,3,0)*(AI7-Q7))) | AI7: =IF(B7="","",P7+Q7+O7+M7+L7-N7) | AJ7: =IFERROR(IF(AND(AC7="SIM",AG7="-",Y7="REVENDA"),(AB7/1+1)*AI7,IF(AND(AC7="SIM",AG7="Pneus",Y7="REVENDA"),(AB7/1+1)*(AI7-AH7),"")),"") | AK7: =IF(AJ7="","",AJ7*17%) | AL7: =IFERROR(IF(AC7="NÃO","",IF(AK7="","",IF(E7="Simples Nacional",BF7,IF(T7=0.12,U7*0.5833337002,IF(T7=0,AI7*0.07,U7))))),"") | AM7: =IFERROR(IF(AC7="NÃO","",IF(OR(AG7="-",AG7="Pneus"),AK7-AL7,"")),"") | AN7: =IF(AND(Y7="REVENDA",AC7="SIM",AG7="BIT"),((AB7/1+1)*AI7)*0.4117,"") | AO7: =IF(AN7="","",AN7*17%) | AP7: =IF(AN7="","",IF(T7=0.12,(U7*0.4117)*0.4117,IF(T7=0,(AI7*0.07)*0.4117,U7*0.4117))) | AQ7: =IF(AN7="","",AO7-AP7) | AR7: =IFERROR(IF(AND(AC7="SIM",Y7="REVENDA",LEFT(AG7,5)="ANEXO")*OR(AE7="ANEXO I",AF7="ANEXO II"),VLOOKUP(H7,Dados!G:I,2,0),""),"INSERIR MVA") | AS7: =IF(LEFT(AG7,5)="ANEXO",VLOOKUP(AG7,Dados!$X$111:$Z$112,2,0)*(AI7-Q7),"") | AT7: =IFERROR(IF(AR7="","",(AI7*AR7)+AI7),"INSERIR MVA") | AU7: =IF(AT7="","",IF(AY7=0.04,U7,AS7*AY7)) | AV7: =IFERROR(IF(AU7="","",(VLOOKUP(AG7,Dados!$X$111:$Z$112,3,0)*AT7*0.17)),"INSERIR MVA") | AW7: =IFERROR(IF(AR7="","",AV7-AU7),"") | AX7: =IFERROR(IF(AC7="NÃO","",IF(AM7<>"",AM7-W7,IF(AQ7<>"",AQ7-W7,IF(AW7<>"",AW7-W7,"")))),"") | AY7: =IFERROR(IF(ISNA(VLOOKUP(R7,Dados!$X$2:$Y$5,2,0)),VLOOKUP(D7,Dados!$X$7:$Y$33,2,0),VLOOKUP(R7,Dados!$X$2:$Y$5,2,0)),"") | AZ7: =IF(C7="","",IF(AND(Y7="CONSUMO",AC7="NÃO")*OR(AG7="-",AG7="BIT"),IF(E7<>"",(AI7-(P7+L7-N7+Q7)*AY7)/0.83),"")) | BA7: =IF(AZ7="","",AZ7*0.17-((P7+L7-N7+Q7)*AY7)) | BB7: =IF(AND(Y7="CONSUMO",AG7="ANEXO I",AY7>4%),(AI7-(P7+L7-N7+Q7)*0.0514)/0.83*(0.5177)*(0.17)-AI7*0.0514,IF(AND(Y7="CONSUMO",AG7="ANEXO II",AY7>4%),(AI7-(P7+L7-N7+Q7)*0.041)/0.83*(0.3295)*(0.17)-AI7*0.041,IF(AND(Y7="CONSUMO",AG7="ANEXO I",AY7=4%),(AI7-(P7+L7-N7+Q7)*0.04)/0.83*(0.5177)*(0.17)-AI7*0.04,IF(AND(Y7="CONSUMO",AG7="ANEXO II",AY7=4%),(AI7-(P7+L7-N7+Q7)*0.04)/0.83*(0.3295)*(0.17)-AI7*0.04,"")))) | BC7: =IF(C7="","",IF(AND(Y7="CONSUMO",AC7="SIM")*OR(AG7="-",AG7="BIT"),IF(E7<>"",(AI7-(P7+L7-N7+Q7)*AY7)/0.83),"")) | BD7: =IF(BC7="","",BC7*0.17) | BE7: =IF(I7=6908,0,IF(BC7="","",BD7-((P7+L7-N7+Q7)*AY7))) | BF7: =IF(B7="","",IF(OR(B7="",E7="Regime Normal"),0,(AI7-Q7)*VLOOKUP(R7,Dados!$X$98:$Y$108,2,0))) | BG7: =IFERROR(VLOOKUP(I7,Dados!$AC$27:$AD$43,2,0),IF(B7="","",IF(D7<>"MT",IF(AND(AC7="SIM",Y7="Revenda"),"2403",IF(AND(AC7="SIM",Y7="Consumo"),"2407",IF(AND(AC7="NÃO",Y7="Revenda"),"2102",IF(AND(AC7="NÃO",Y7="Consumo"),"2556",)))),REPLACE(I7,1,1,1))))
Z8: =IF(B8="","",(IFERROR(VLOOKUP(H8,Dados!A$3:B$15000,2,0),"Não Encontrado"))) | AA8: =IF(B8="","",(IFERROR(VLOOKUP(G8,Dados!C$3:E$15000,3,0),"Não Encontrado"))) | AB8: =IFERROR(IF(Z8<>"Não Encontrado",Z8,IF(AA8<>"Não Encontrado",AA8,"")),"") | AC8: =IF(B8="","",IF(AB8="","NÃO","SIM")) | AD8: =IFERROR(VLOOKUP(G8,Dados!$P$3:$R$500,3,0),"") | AE8: =IFERROR(VLOOKUP(G8,Dados!$K$3:$L$500,2,0),"") | AF8: =IFERROR(VLOOKUP(G8,Dados!$M$3:$N$500,2,0),"") | AG8: =IF(F8="","",IF(AND(AD8="",AE8="",AF8=""),"-",IF(AND(AD8="BIT",AE8="",AF8=""),"BIT",IF(AND(AE8="ANEXO I",AD8="",AF8=""),"ANEXO I",IF(AND(AF8="ANEXO II",AD8="",AE8=""),"ANEXO II","Escolher"))))) | AH8: =IF(AG8<>"Pneus","",IFERROR(VLOOKUP(R8,Dados!$X$2:$Z$5,3,0)*(AI8-Q8),VLOOKUP(D8,Dados!$X$7:$Z$33,3,0)*(AI8-Q8))) | AI8: =IF(B8="","",P8+Q8+O8+M8+L8-N8) | AJ8: =IFERROR(IF(AND(AC8="SIM",AG8="-",Y8="REVENDA"),(AB8/1+1)*AI8,IF(AND(AC8="SIM",AG8="Pneus",Y8="REVENDA"),(AB8/1+1)*(AI8-AH8),"")),"") | AK8: =IF(AJ8="","",AJ8*17%) | AL8: =IFERROR(IF(AC8="NÃO","",IF(AK8="","",IF(E8="Simples Nacional",BF8,IF(T8=0.12,U8*0.5833337002,IF(T8=0,AI8*0.07,U8))))),"") | AM8: =IFERROR(IF(AC8="NÃO","",IF(OR(AG8="-",AG8="Pneus"),AK8-AL8,"")),"") | AN8: =IF(AND(Y8="REVENDA",AC8="SIM",AG8="BIT"),((AB8/1+1)*AI8)*0.4117,"") | AO8: =IF(AN8="","",AN8*17%) | AP8: =IF(AN8="","",IF(T8=0.12,(U8*0.4117)*0.4117,IF(T8=0,(AI8*0.07)*0.4117,U8*0.4117))) | AQ8: =IF(AN8="","",AO8-AP8) | AR8: =IFERROR(IF(AND(AC8="SIM",Y8="REVENDA",LEFT(AG8,5)="ANEXO")*OR(AE8="ANEXO I",AF8="ANEXO II"),VLOOKUP(H8,Dados!G:I,2,0),""),"INSERIR MVA") | AS8: =IF(LEFT(AG8,5)="ANEXO",VLOOKUP(AG8,Dados!$X$111:$Z$112,2,0)*(AI8-Q8),"") | AT8: =IFERROR(IF(AR8="","",(AI8*AR8)+AI8),"INSERIR MVA") | AU8: =IF(AT8="","",IF(AY8=0.04,U8,AS8*AY8)) | AV8: =IFERROR(IF(AU8="","",(VLOOKUP(AG8,Dados!$X$111:$Z$112,3,0)*AT8*0.17)),"INSERIR MVA") | AW8: =IFERROR(IF(AR8="","",AV8-AU8),"") | AX8: =IFERROR(IF(AC8="NÃO","",IF(AM8<>"",AM8-W8,IF(AQ8<>"",AQ8-W8,IF(AW8<>"",AW8-W8,"")))),"") | AY8: =IFERROR(IF(ISNA(VLOOKUP(R8,Dados!$X$2:$Y$5,2,0)),VLOOKUP(D8,Dados!$X$7:$Y$33,2,0),VLOOKUP(R8,Dados!$X$2:$Y$5,2,0)),"") | AZ8: =IF(C8="","",IF(AND(Y8="CONSUMO",AC8="NÃO")*OR(AG8="-",AG8="BIT"),IF(E8<>"",(AI8-(P8+L8-N8+Q8)*AY8)/0.83),"")) | BA8: =IF(AZ8="","",AZ8*0.17-((P8+L8-N8+Q8)*AY8)) | BB8: =IF(AND(Y8="CONSUMO",AG8="ANEXO I",AY8>4%),(AI8-(P8+L8-N8+Q8)*0.0514)/0.83*(0.5177)*(0.17)-AI8*0.0514,IF(AND(Y8="CONSUMO",AG8="ANEXO II",AY8>4%),(AI8-(P8+L8-N8+Q8)*0.041)/0.83*(0.3295)*(0.17)-AI8*0.041,IF(AND(Y8="CONSUMO",AG8="ANEXO I",AY8=4%),(AI8-(P8+L8-N8+Q8)*0.04)/0.83*(0.5177)*(0.17)-AI8*0.04,IF(AND(Y8="CONSUMO",AG8="ANEXO II",AY8=4%),(AI8-(P8+L8-N8+Q8)*0.04)/0.83*(0.3295)*(0.17)-AI8*0.04,"")))) | BC8: =IF(C8="","",IF(AND(Y8="CONSUMO",AC8="SIM")*OR(AG8="-",AG8="BIT"),IF(E8<>"",(AI8-(P8+L8-N8+Q8)*AY8)/0.83),"")) | BD8: =IF(BC8="","",BC8*0.17) | BE8: =IF(I8=6908,0,IF(BC8="","",BD8-((P8+L8-N8+Q8)*AY8))) | BF8: =IF(B8="","",IF(OR(B8="",E8="Regime Normal"),0,(AI8-Q8)*VLOOKUP(R8,Dados!$X$98:$Y$108,2,0))) | BG8: =IFERROR(VLOOKUP(I8,Dados!$AC$27:$AD$43,2,0),IF(B8="","",IF(D8<>"MT",IF(AND(AC8="SIM",Y8="Revenda"),"2403",IF(AND(AC8="SIM",Y8="Consumo"),"2407",IF(AND(AC8="NÃO",Y8="Revenda"),"2102",IF(AND(AC8="NÃO",Y8="Consumo"),"2556",)))),REPLACE(I8,1,1,1))))
Z9: =IF(B9="","",(IFERROR(VLOOKUP(H9,Dados!A$3:B$15000,2,0),"Não Encontrado"))) | AA9: =IF(B9="","",(IFERROR(VLOOKUP(G9,Dados!C$3:E$15000,3,0),"Não Encontrado"))) | AB9: =IFERROR(IF(Z9<>"Não Encontrado",Z9,IF(AA9<>"Não Encontrado",AA9,"")),"") | AC9: =IF(B9="","",IF(AB9="","NÃO","SIM")) | AD9: =IFERROR(VLOOKUP(G9,Dados!$P$3:$R$500,3,0),"") | AE9: =IFERROR(VLOOKUP(G9,Dados!$K$3:$L$500,2,0),"") | AF9: =IFERROR(VLOOKUP(G9,Dados!$M$3:$N$500,2,0),"") | AG9: =IF(F9="","",IF(AND(AD9="",AE9="",AF9=""),"-",IF(AND(AD9="BIT",AE9="",AF9=""),"BIT",IF(AND(AE9="ANEXO I",AD9="",AF9=""),"ANEXO I",IF(AND(AF9="ANEXO II",AD9="",AE9=""),"ANEXO II","Escolher"))))) | AH9: =IF(AG9<>"Pneus","",IFERROR(VLOOKUP(R9,Dados!$X$2:$Z$5,3,0)*(AI9-Q9),VLOOKUP(D9,Dados!$X$7:$Z$33,3,0)*(AI9-Q9))) | AI9: =IF(B9="","",P9+Q9+O9+M9+L9-N9) | AJ9: =IFERROR(IF(AND(AC9="SIM",AG9="-",Y9="REVENDA"),(AB9/1+1)*AI9,IF(AND(AC9="SIM",AG9="Pneus",Y9="REVENDA"),(AB9/1+1)*(AI9-AH9),"")),"") | AK9: =IF(AJ9="","",AJ9*17%) | AL9: =IFERROR(IF(AC9="NÃO","",IF(AK9="","",IF(E9="Simples Nacional",BF9,IF(T9=0.12,U9*0.5833337002,IF(T9=0,AI9*0.07,U9))))),"") | AM9: =IFERROR(IF(AC9="NÃO","",IF(OR(AG9="-",AG9="Pneus"),AK9-AL9,"")),"") | AN9: =IF(AND(Y9="REVENDA",AC9="SIM",AG9="BIT"),((AB9/1+1)*AI9)*0.4117,"") | AO9: =IF(AN9="","",AN9*17%) | AP9: =IF(AN9="","",IF(T9=0.12,(U9*0.4117)*0.4117,IF(T9=0,(AI9*0.07)*0.4117,U9*0.4117))) | AQ9: =IF(AN9="","",AO9-AP9) | AR9: =IFERROR(IF(AND(AC9="SIM",Y9="REVENDA",LEFT(AG9,5)="ANEXO")*OR(AE9="ANEXO I",AF9="ANEXO II"),VLOOKUP(H9,Dados!G:I,2,0),""),"INSERIR MVA") | AS9: =IF(LEFT(AG9,5)="ANEXO",VLOOKUP(AG9,Dados!$X$111:$Z$112,2,0)*(AI9-Q9),"") | AT9: =IFERROR(IF(AR9="","",(AI9*AR9)+AI9),"INSERIR MVA") | AU9: =IF(AT9="","",IF(AY9=0.04,U9,AS9*AY9)) | AV9: =IFERROR(IF(AU9="","",(VLOOKUP(AG9,Dados!$X$111:$Z$112,3,0)*AT9*0.17)),"INSERIR MVA") | AW9: =IFERROR(IF(AR9="","",AV9-AU9),"") | AX9: =IFERROR(IF(AC9="NÃO","",IF(AM9<>"",AM9-W9,IF(AQ9<>"",AQ9-W9,IF(AW9<>"",AW9-W9,"")))),"") | AY9: =IFERROR(IF(ISNA(VLOOKUP(R9,Dados!$X$2:$Y$5,2,0)),VLOOKUP(D9,Dados!$X$7:$Y$33,2,0),VLOOKUP(R9,Dados!$X$2:$Y$5,2,0)),"") | AZ9: =IF(C9="","",IF(AND(Y9="CONSUMO",AC9="NÃO")*OR(AG9="-",AG9="BIT"),IF(E9<>"",(AI9-(P9+L9-N9+Q9)*AY9)/0.83),"")) | BA9: =IF(AZ9="","",AZ9*0.17-((P9+L9-N9+Q9)*AY9)) | BB9: =IF(AND(Y9="CONSUMO",AG9="ANEXO I",AY9>4%),(AI9-(P9+L9-N9+Q9)*0.0514)/0.83*(0.5177)*(0.17)-AI9*0.0514,IF(AND(Y9="CONSUMO",AG9="ANEXO II",AY9>4%),(AI9-(P9+L9-N9+Q9)*0.041)/0.83*(0.3295)*(0.17)-AI9*0.041,IF(AND(Y9="CONSUMO",AG9="ANEXO I",AY9=4%),(AI9-(P9+L9-N9+Q9)*0.04)/0.83*(0.5177)*(0.17)-AI9*0.04,IF(AND(Y9="CONSUMO",AG9="ANEXO II",AY9=4%),(AI9-(P9+L9-N9+Q9)*0.04)/0.83*(0.3295)*(0.17)-AI9*0.04,"")))) | BC9: =IF(C9="","",IF(AND(Y9="CONSUMO",AC9="SIM")*OR(AG9="-",AG9="BIT"),IF(E9<>"",(AI9-(P9+L9-N9+Q9)*AY9)/0.83),"")) | BD9: =IF(BC9="","",BC9*0.17) | BE9: =IF(I9=6908,0,IF(BC9="","",BD9-((P9+L9-N9+Q9)*AY9))) | BF9: =IF(B9="","",IF(OR(B9="",E9="Regime Normal"),0,(AI9-Q9)*VLOOKUP(R9,Dados!$X$98:$Y$108,2,0))) | BG9: =IFERROR(VLOOKUP(I9,Dados!$AC$27:$AD$43,2,0),IF(B9="","",IF(D9<>"MT",IF(AND(AC9="SIM",Y9="Revenda"),"2403",IF(AND(AC9="SIM",Y9="Consumo"),"2407",IF(AND(AC9="NÃO",Y9="Revenda"),"2102",IF(AND(AC9="NÃO",Y9="Consumo"),"2556",)))),REPLACE(I9,1,1,1))))
Z10: =IF(B10="","",(IFERROR(VLOOKUP(H10,Dados!A$3:B$15000,2,0),"Não Encontrado"))) | AA10: =IF(B10="","",(IFERROR(VLOOKUP(G10,Dados!C$3:E$15000,3,0),"Não Encontrado"))) | AB10: =IFERROR(IF(Z10<>"Não Encontrado",Z10,IF(AA10<>"Não Encontrado",AA10,"")),"") | AC10: =IF(B10="","",IF(AB10="","NÃO","SIM")) | AD10: =IFERROR(VLOOKUP(G10,Dados!$P$3:$R$500,3,0),"") | AE10: =IFERROR(VLOOKUP(G10,Dados!$K$3:$L$500,2,0),"") | AF10: =IFERROR(VLOOKUP(G10,Dados!$M$3:$N$500,2,0),"") | AG10: =IF(F10="","",IF(AND(AD10="",AE10="",AF10=""),"-",IF(AND(AD10="BIT",AE10="",AF10=""),"BIT",IF(AND(AE10="ANEXO I",AD10="",AF10=""),"ANEXO I",IF(AND(AF10="ANEXO II",AD10="",AE10=""),"ANEXO II","Escolher"))))) | AH10: =IF(AG10<>"Pneus","",IFERROR(VLOOKUP(R10,Dados!$X$2:$Z$5,3,0)*(AI10-Q10),VLOOKUP(D10,Dados!$X$7:$Z$33,3,0)*(AI10-Q10))) | AI10: =IF(B10="","",P10+Q10+O10+M10+L10-N10) | AJ10: =IFERROR(IF(AND(AC10="SIM",AG10="-",Y10="REVENDA"),(AB10/1+1)*AI10,IF(AND(AC10="SIM",AG10="Pneus",Y10="REVENDA"),(AB10/1+1)*(AI10-AH10),"")),"") | AK10: =IF(AJ10="","",AJ10*17%) | AL10: =IFERROR(IF(AC10="NÃO","",IF(AK10="","",IF(E10="Simples Nacional",BF10,IF(T10=0.12,U10*0.5833337002,IF(T10=0,AI10*0.07,U10))))),"") | AM10: =IFERROR(IF(AC10="NÃO","",IF(OR(AG10="-",AG10="Pneus"),AK10-AL10,"")),"") | AN10: =IF(AND(Y10="REVENDA",AC10="SIM",AG10="BIT"),((AB10/1+1)*AI10)*0.4117,"") | AO10: =IF(AN10="","",AN10*17%) | AP10: =IF(AN10="","",IF(T10=0.12,(U10*0.4117)*0.4117,IF(T10=0,(AI10*0.07)*0.4117,U10*0.4117))) | AQ10: =IF(AN10="","",AO10-AP10) | AR10: =IFERROR(IF(AND(AC10="SIM",Y10="REVENDA",LEFT(AG10,5)="ANEXO")*OR(AE10="ANEXO I",AF10="ANEXO II"),VLOOKUP(H10,Dados!G:I,2,0),""),"INSERIR MVA") | AS10: =IF(LEFT(AG10,5)="ANEXO",VLOOKUP(AG10,Dados!$X$111:$Z$112,2,0)*(AI10-Q10),"") | AT10: =IFERROR(IF(AR10="","",(AI10*AR10)+AI10),"INSERIR MVA") | AU10: =IF(AT10="","",IF(AY10=0.04,U10,AS10*AY10)) | AV10: =IFERROR(IF(AU10="","",(VLOOKUP(AG10,Dados!$X$111:$Z$112,3,0)*AT10*0.17)),"INSERIR MVA") | AW10: =IFERROR(IF(AR10="","",AV10-AU10),"") | AX10: =IFERROR(IF(AC10="NÃO","",IF(AM10<>"",AM10-W10,IF(AQ10<>"",AQ10-W10,IF(AW10<>"",AW10-W10,"")))),"") | AY10: =IFERROR(IF(ISNA(VLOOKUP(R10,Dados!$X$2:$Y$5,2,0)),VLOOKUP(D10,Dados!$X$7:$Y$33,2,0),VLOOKUP(R10,Dados!$X$2:$Y$5,2,0)),"") | AZ10: =IF(C10="","",IF(AND(Y10="CONSUMO",AC10="NÃO")*OR(AG10="-",AG10="BIT"),IF(E10<>"",(AI10-(P10+L10-N10+Q10)*AY10)/0.83),"")) | BA10: =IF(AZ10="","",AZ10*0.17-((P10+L10-N10+Q10)*AY10)) | BB10: =IF(AND(Y10="CONSUMO",AG10="ANEXO I",AY10>4%),(AI10-(P10+L10-N10+Q10)*0.0514)/0.83*(0.5177)*(0.17)-AI10*0.0514,IF(AND(Y10="CONSUMO",AG10="ANEXO II",AY10>4%),(AI10-(P10+L10-N10+Q10)*0.041)/0.83*(0.3295)*(0.17)-AI10*0.041,IF(AND(Y10="CONSUMO",AG10="ANEXO I",AY10=4%),(AI10-(P10+L10-N10+Q10)*0.04)/0.83*(0.5177)*(0.17)-AI10*0.04,IF(AND(Y10="CONSUMO",AG10="ANEXO II",AY10=4%),(AI10-(P10+L10-N10+Q10)*0.04)/0.83*(0.3295)*(0.17)-AI10*0.04,"")))) | BC10: =IF(C10="","",IF(AND(Y10="CONSUMO",AC10="SIM")*OR(AG10="-",AG10="BIT"),IF(E10<>"",(AI10-(P10+L10-N10+Q10)*AY10)/0.83),"")) | BD10: =IF(BC10="","",BC10*0.17) | BE10: =IF(I10=6908,0,IF(BC10="","",BD10-((P10+L10-N10+Q10)*AY10))) | BF10: =IF(B10="","",IF(OR(B10="",E10="Regime Normal"),0,(AI10-Q10)*VLOOKUP(R10,Dados!$X$98:$Y$108,2,0))) | BG10: =IFERROR(VLOOKUP(I10,Dados!$AC$27:$AD$43,2,0),IF(B10="","",IF(D10<>"MT",IF(AND(AC10="SIM",Y10="Revenda"),"2403",IF(AND(AC10="SIM",Y10="Consumo"),"2407",IF(AND(AC10="NÃO",Y10="Revenda"),"2102",IF(AND(AC10="NÃO",Y10="Consumo"),"2556",)))),REPLACE(I10,1,1,1))))
Z11: =IF(B11="","",(IFERROR(VLOOKUP(H11,Dados!A$3:B$15000,2,0),"Não Encontrado"))) | AA11: =IF(B11="","",(IFERROR(VLOOKUP(G11,Dados!C$3:E$15000,3,0),"Não Encontrado"))) | AB11: =IFERROR(IF(Z11<>"Não Encontrado",Z11,IF(AA11<>"Não Encontrado",AA11,"")),"") | AC11: =IF(B11="","",IF(AB11="","NÃO","SIM")) | AD11: =IFERROR(VLOOKUP(G11,Dados!$P$3:$R$500,3,0),"") | AE11: =IFERROR(VLOOKUP(G11,Dados!$K$3:$L$500,2,0),"") | AF11: =IFERROR(VLOOKUP(G11,Dados!$M$3:$N$500,2,0),"") | AG11: =IF(F11="","",IF(AND(AD11="",AE11="",AF11=""),"-",IF(AND(AD11="BIT",AE11="",AF11=""),"BIT",IF(AND(AE11="ANEXO I",AD11="",AF11=""),"ANEXO I",IF(AND(AF11="ANEXO II",AD11="",AE11=""),"ANEXO II","Escolher"))))) | AH11: =IF(AG11<>"Pneus","",IFERROR(VLOOKUP(R11,Dados!$X$2:$Z$5,3,0)*(AI11-Q11),VLOOKUP(D11,Dados!$X$7:$Z$33,3,0)*(AI11-Q11))) | AI11: =IF(B11="","",P11+Q11+O11+M11+L11-N11) | AJ11: =IFERROR(IF(AND(AC11="SIM",AG11="-",Y11="REVENDA"),(AB11/1+1)*AI11,IF(AND(AC11="SIM",AG11="Pneus",Y11="REVENDA"),(AB11/1+1)*(AI11-AH11),"")),"") | AK11: =IF(AJ11="","",AJ11*17%) | AL11: =IFERROR(IF(AC11="NÃO","",IF(AK11="","",IF(E11="Simples Nacional",BF11,IF(T11=0.12,U11*0.5833337002,IF(T11=0,AI11*0.07,U11))))),"") | AM11: =IFERROR(IF(AC11="NÃO","",IF(OR(AG11="-",AG11="Pneus"),AK11-AL11,"")),"") | AN11: =IF(AND(Y11="REVENDA",AC11="SIM",AG11="BIT"),((AB11/1+1)*AI11)*0.4117,"") | AO11: =IF(AN11="","",AN11*17%) | AP11: =IF(AN11="","",IF(T11=0.12,(U11*0.4117)*0.4117,IF(T11=0,(AI11*0.07)*0.4117,U11*0.4117))) | AQ11: =IF(AN11="","",AO11-AP11) | AR11: =IFERROR(IF(AND(AC11="SIM",Y11="REVENDA",LEFT(AG11,5)="ANEXO")*OR(AE11="ANEXO I",AF11="ANEXO II"),VLOOKUP(H11,Dados!G:I,2,0),""),"INSERIR MVA") | AS11: =IF(LEFT(AG11,5)="ANEXO",VLOOKUP(AG11,Dados!$X$111:$Z$112,2,0)*(AI11-Q11),"") | AT11: =IFERROR(IF(AR11="","",(AI11*AR11)+AI11),"INSERIR MVA") | AU11: =IF(AT11="","",IF(AY11=0.04,U11,AS11*AY11)) | AV11: =IFERROR(IF(AU11="","",(VLOOKUP(AG11,Dados!$X$111:$Z$112,3,0)*AT11*0.17)),"INSERIR MVA") | AW11: =IFERROR(IF(AR11="","",AV11-AU11),"") | AX11: =IFERROR(IF(AC11="NÃO","",IF(AM11<>"",AM11-W11,IF(AQ11<>"",AQ11-W11,IF(AW11<>"",AW11-W11,"")))),"") | AY11: =IFERROR(IF(ISNA(VLOOKUP(R11,Dados!$X$2:$Y$5,2,0)),VLOOKUP(D11,Dados!$X$7:$Y$33,2,0),VLOOKUP(R11,Dados!$X$2:$Y$5,2,0)),"") | AZ11: =IF(C11="","",IF(AND(Y11="CONSUMO",AC11="NÃO")*OR(AG11="-",AG11="BIT"),IF(E11<>"",(AI11-(P11+L11-N11+Q11)*AY11)/0.83),"")) | BA11: =IF(AZ11="","",AZ11*0.17-((P11+L11-N11+Q11)*AY11)) | BB11: =IF(AND(Y11="CONSUMO",AG11="ANEXO I",AY11>4%),(AI11-(P11+L11-N11+Q11)*0.0514)/0.83*(0.5177)*(0.17)-AI11*0.0514,IF(AND(Y11="CONSUMO",AG11="ANEXO II",AY11>4%),(AI11-(P11+L11-N11+Q11)*0.041)/0.83*(0.3295)*(0.17)-AI11*0.041,IF(AND(Y11="CONSUMO",AG11="ANEXO I",AY11=4%),(AI11-(P11+L11-N11+Q11)*0.04)/0.83*(0.5177)*(0.17)-AI11*0.04,IF(AND(Y11="CONSUMO",AG11="ANEXO II",AY11=4%),(AI11-(P11+L11-N11+Q11)*0.04)/0.83*(0.3295)*(0.17)-AI11*0.04,"")))) | BC11: =IF(C11="","",IF(AND(Y11="CONSUMO",AC11="SIM")*OR(AG11="-",AG11="BIT"),IF(E11<>"",(AI11-(P11+L11-N11+Q11)*AY11)/0.83),"")) | BD11: =IF(BC11="","",BC11*0.17) | BE11: =IF(I11=6908,0,IF(BC11="","",BD11-((P11+L11-N11+Q11)*AY11))) | BF11: =IF(B11="","",IF(OR(B11="",E11="Regime Normal"),0,(AI11-Q11)*VLOOKUP(R11,Dados!$X$98:$Y$108,2,0))) | BG11: =IFERROR(VLOOKUP(I11,Dados!$AC$27:$AD$43,2,0),IF(B11="","",IF(D11<>"MT",IF(AND(AC11="SIM",Y11="Revenda"),"2403",IF(AND(AC11="SIM",Y11="Consumo"),"2407",IF(AND(AC11="NÃO",Y11="Revenda"),"2102",IF(AND(AC11="NÃO",Y11="Consumo"),"2556",)))),REPLACE(I11,1,1,1))))
Z12: =IF(B12="","",(IFERROR(VLOOKUP(H12,Dados!A$3:B$15000,2,0),"Não Encontrado"))) | AA12: =IF(B12="","",(IFERROR(VLOOKUP(G12,Dados!C$3:E$15000,3,0),"Não Encontrado"))) | AB12: =IFERROR(IF(Z12<>"Não Encontrado",Z12,IF(AA12<>"Não Encontrado",AA12,"")),"") | AC12: =IF(B12="","",IF(AB12="","NÃO","SIM")) | AD12: =IFERROR(VLOOKUP(G12,Dados!$P$3:$R$500,3,0),"") | AE12: =IFERROR(VLOOKUP(G12,Dados!$K$3:$L$500,2,0),"") | AF12: =IFERROR(VLOOKUP(G12,Dados!$M$3:$N$500,2,0),"") | AG12: =IF(F12="","",IF(AND(AD12="",AE12="",AF12=""),"-",IF(AND(AD12="BIT",AE12="",AF12=""),"BIT",IF(AND(AE12="ANEXO I",AD12="",AF12=""),"ANEXO I",IF(AND(AF12="ANEXO II",AD12="",AE12=""),"ANEXO II","Escolher"))))) | AH12: =IF(AG12<>"Pneus","",IFERROR(VLOOKUP(R12,Dados!$X$2:$Z$5,3,0)*(AI12-Q12),VLOOKUP(D12,Dados!$X$7:$Z$33,3,0)*(AI12-Q12))) | AI12: =IF(B12="","",P12+Q12+O12+M12+L12-N12) | AJ12: =IFERROR(IF(AND(AC12="SIM",AG12="-",Y12="REVENDA"),(AB12/1+1)*AI12,IF(AND(AC12="SIM",AG12="Pneus",Y12="REVENDA"),(AB12/1+1)*(AI12-AH12),"")),"") | AK12: =IF(AJ12="","",AJ12*17%) | AL12: =IFERROR(IF(AC12="NÃO","",IF(AK12="","",IF(E12="Simples Nacional",BF12,IF(T12=0.12,U12*0.5833337002,IF(T12=0,AI12*0.07,U12))))),"") | AM12: =IFERROR(IF(AC12="NÃO","",IF(OR(AG12="-",AG12="Pneus"),AK12-AL12,"")),"") | AN12: =IF(AND(Y12="REVENDA",AC12="SIM",AG12="BIT"),((AB12/1+1)*AI12)*0.4117,"") | AO12: =IF(AN12="","",AN12*17%) | AP12: =IF(AN12="","",IF(T12=0.12,(U12*0.4117)*0.4117,IF(T12=0,(AI12*0.07)*0.4117,U12*0.4117))) | AQ12: =IF(AN12="","",AO12-AP12) | AR12: =IFERROR(IF(AND(AC12="SIM",Y12="REVENDA",LEFT(AG12,5)="ANEXO")*OR(AE12="ANEXO I",AF12="ANEXO II"),VLOOKUP(H12,Dados!G:I,2,0),""),"INSERIR MVA") | AS12: =IF(LEFT(AG12,5)="ANEXO",VLOOKUP(AG12,Dados!$X$111:$Z$112,2,0)*(AI12-Q12),"") | AT12: =IFERROR(IF(AR12="","",(AI12*AR12)+AI12),"INSERIR MVA") | AU12: =IF(AT12="","",IF(AY12=0.04,U12,AS12*AY12)) | AV12: =IFERROR(IF(AU12="","",(VLOOKUP(AG12,Dados!$X$111:$Z$112,3,0)*AT12*0.17)),"INSERIR MVA") | AW12: =IFERROR(IF(AR12="","",AV12-AU12),"") | AX12: =IFERROR(IF(AC12="NÃO","",IF(AM12<>"",AM12-W12,IF(AQ12<>"",AQ12-W12,IF(AW12<>"",AW12-W12,"")))),"") | AY12: =IFERROR(IF(ISNA(VLOOKUP(R12,Dados!$X$2:$Y$5,2,0)),VLOOKUP(D12,Dados!$X$7:$Y$33,2,0),VLOOKUP(R12,Dados!$X$2:$Y$5,2,0)),"") | AZ12: =IF(C12="","",IF(AND(Y12="CONSUMO",AC12="NÃO")*OR(AG12="-",AG12="BIT"),IF(E12<>"",(AI12-(P12+L12-N12+Q12)*AY12)/0.83),"")) | BA12: =IF(AZ12="","",AZ12*0.17-((P12+L12-N12+Q12)*AY12)) | BB12: =IF(AND(Y12="CONSUMO",AG12="ANEXO I",AY12>4%),(AI12-(P12+L12-N12+Q12)*0.0514)/0.83*(0.5177)*(0.17)-AI12*0.0514,IF(AND(Y12="CONSUMO",AG12="ANEXO II",AY12>4%),(AI12-(P12+L12-N12+Q12)*0.041)/0.83*(0.3295)*(0.17)-AI12*0.041,IF(AND(Y12="CONSUMO",AG12="ANEXO I",AY12=4%),(AI12-(P12+L12-N12+Q12)*0.04)/0.83*(0.5177)*(0.17)-AI12*0.04,IF(AND(Y12="CONSUMO",AG12="ANEXO II",AY12=4%),(AI12-(P12+L12-N12+Q12)*0.04)/0.83*(0.3295)*(0.17)-AI12*0.04,"")))) | BC12: =IF(C12="","",IF(AND(Y12="CONSUMO",AC12="SIM")*OR(AG12="-",AG12="BIT"),IF(E12<>"",(AI12-(P12+L12-N12+Q12)*AY12)/0.83),"")) | BD12: =IF(BC12="","",BC12*0.17) | BE12: =IF(I12=6908,0,IF(BC12="","",BD12-((P12+L12-N12+Q12)*AY12))) | BF12: =IF(B12="","",IF(OR(B12="",E12="Regime Normal"),0,(AI12-Q12)*VLOOKUP(R12,Dados!$X$98:$Y$108,2,0))) | BG12: =IFERROR(VLOOKUP(I12,Dados!$AC$27:$AD$43,2,0),IF(B12="","",IF(D12<>"MT",IF(AND(AC12="SIM",Y12="Revenda"),"2403",IF(AND(AC12="SIM",Y12="Consumo"),"2407",IF(AND(AC12="NÃO",Y12="Revenda"),"2102",IF(AND(AC12="NÃO",Y12="Consumo"),"2556",)))),REPLACE(I12,1,1,1))))
Z13: =IF(B13="","",(IFERROR(VLOOKUP(H13,Dados!A$3:B$15000,2,0),"Não Encontrado"))) | AA13: =IF(B13="","",(IFERROR(VLOOKUP(G13,Dados!C$3:E$15000,3,0),"Não Encontrado"))) | AB13: =IFERROR(IF(Z13<>"Não Encontrado",Z13,IF(AA13<>"Não Encontrado",AA13,"")),"") | AC13: =IF(B13="","",IF(AB13="","NÃO","SIM")) | AD13: =IFERROR(VLOOKUP(G13,Dados!$P$3:$R$500,3,0),"") | AE13: =IFERROR(VLOOKUP(G13,Dados!$K$3:$L$500,2,0),"") | AF13: =IFERROR(VLOOKUP(G13,Dados!$M$3:$N$500,2,0),"") | AG13: =IF(F13="","",IF(AND(AD13="",AE13="",AF13=""),"-",IF(AND(AD13="BIT",AE13="",AF13=""),"BIT",IF(AND(AE13="ANEXO I",AD13="",AF13=""),"ANEXO I",IF(AND(AF13="ANEXO II",AD13="",AE13=""),"ANEXO II","Escolher"))))) | AH13: =IF(AG13<>"Pneus","",IFERROR(VLOOKUP(R13,Dados!$X$2:$Z$5,3,0)*(AI13-Q13),VLOOKUP(D13,Dados!$X$7:$Z$33,3,0)*(AI13-Q13))) | AI13: =IF(B13="","",P13+Q13+O13+M13+L13-N13) | AJ13: =IFERROR(IF(AND(AC13="SIM",AG13="-",Y13="REVENDA"),(AB13/1+1)*AI13,IF(AND(AC13="SIM",AG13="Pneus",Y13="REVENDA"),(AB13/1+1)*(AI13-AH13),"")),"") | AK13: =IF(AJ13="","",AJ13*17%) | AL13: =IFERROR(IF(AC13="NÃO","",IF(AK13="","",IF(E13="Simples Nacional",BF13,IF(T13=0.12,U13*0.5833337002,IF(T13=0,AI13*0.07,U13))))),"") | AM13: =IFERROR(IF(AC13="NÃO","",IF(OR(AG13="-",AG13="Pneus"),AK13-AL13,"")),"") | AN13: =IF(AND(Y13="REVENDA",AC13="SIM",AG13="BIT"),((AB13/1+1)*AI13)*0.4117,"") | AO13: =IF(AN13="","",AN13*17%) | AP13: =IF(AN13="","",IF(T13=0.12,(U13*0.4117)*0.4117,IF(T13=0,(AI13*0.07)*0.4117,U13*0.4117))) | AQ13: =IF(AN13="","",AO13-AP13) | AR13: =IFERROR(IF(AND(AC13="SIM",Y13="REVENDA",LEFT(AG13,5)="ANEXO")*OR(AE13="ANEXO I",AF13="ANEXO II"),VLOOKUP(H13,Dados!G:I,2,0),""),"INSERIR MVA") | AS13: =IF(LEFT(AG13,5)="ANEXO",VLOOKUP(AG13,Dados!$X$111:$Z$112,2,0)*(AI13-Q13),"") | AT13: =IFERROR(IF(AR13="","",(AI13*AR13)+AI13),"INSERIR MVA") | AU13: =IF(AT13="","",IF(AY13=0.04,U13,AS13*AY13)) | AV13: =IFERROR(IF(AU13="","",(VLOOKUP(AG13,Dados!$X$111:$Z$112,3,0)*AT13*0.17)),"INSERIR MVA") | AW13: =IFERROR(IF(AR13="","",AV13-AU13),"") | AX13: =IFERROR(IF(AC13="NÃO","",IF(AM13<>"",AM13-W13,IF(AQ13<>"",AQ13-W13,IF(AW13<>"",AW13-W13,"")))),"") | AY13: =IFERROR(IF(ISNA(VLOOKUP(R13,Dados!$X$2:$Y$5,2,0)),VLOOKUP(D13,Dados!$X$7:$Y$33,2,0),VLOOKUP(R13,Dados!$X$2:$Y$5,2,0)),"") | AZ13: =IF(C13="","",IF(AND(Y13="CONSUMO",AC13="NÃO")*OR(AG13="-",AG13="BIT"),IF(E13<>"",(AI13-(P13+L13-N13+Q13)*AY13)/0.83),"")) | BA13: =IF(AZ13="","",AZ13*0.17-((P13+L13-N13+Q13)*AY13)) | BB13: =IF(AND(Y13="CONSUMO",AG13="ANEXO I",AY13>4%),(AI13-(P13+L13-N13+Q13)*0.0514)/0.83*(0.5177)*(0.17)-AI13*0.0514,IF(AND(Y13="CONSUMO",AG13="ANEXO II",AY13>4%),(AI13-(P13+L13-N13+Q13)*0.041)/0.83*(0.3295)*(0.17)-AI13*0.041,IF(AND(Y13="CONSUMO",AG13="ANEXO I",AY13=4%),(AI13-(P13+L13-N13+Q13)*0.04)/0.83*(0.5177)*(0.17)-AI13*0.04,IF(AND(Y13="CONSUMO",AG13="ANEXO II",AY13=4%),(AI13-(P13+L13-N13+Q13)*0.04)/0.83*(0.3295)*(0.17)-AI13*0.04,"")))) | BC13: =IF(C13="","",IF(AND(Y13="CONSUMO",AC13="SIM")*OR(AG13="-",AG13="BIT"),IF(E13<>"",(AI13-(P13+L13-N13+Q13)*AY13)/0.83),"")) | BD13: =IF(BC13="","",BC13*0.17) | BE13: =IF(I13=6908,0,IF(BC13="","",BD13-((P13+L13-N13+Q13)*AY13))) | BF13: =IF(B13="","",IF(OR(B13="",E13="Regime Normal"),0,(AI13-Q13)*VLOOKUP(R13,Dados!$X$98:$Y$108,2,0))) | BG13: =IFERROR(VLOOKUP(I13,Dados!$AC$27:$AD$43,2,0),IF(B13="","",IF(D13<>"MT",IF(AND(AC13="SIM",Y13="Revenda"),"2403",IF(AND(AC13="SIM",Y13="Consumo"),"2407",IF(AND(AC13="NÃO",Y13="Revenda"),"2102",IF(AND(AC13="NÃO",Y13="Consumo"),"2556",)))),REPLACE(I13,1,1,1))))
Z14: =IF(B14="","",(IFERROR(VLOOKUP(H14,Dados!A$3:B$15000,2,0),"Não Encontrado"))) | AA14: =IF(B14="","",(IFERROR(VLOOKUP(G14,Dados!C$3:E$15000,3,0),"Não Encontrado"))) | AB14: =IFERROR(IF(Z14<>"Não Encontrado",Z14,IF(AA14<>"Não Encontrado",AA14,"")),"") | AC14: =IF(B14="","",IF(AB14="","NÃO","SIM")) | AD14: =IFERROR(VLOOKUP(G14,Dados!$P$3:$R$500,3,0),"") | AE14: =IFERROR(VLOOKUP(G14,Dados!$K$3:$L$500,2,0),"") | AF14: =IFERROR(VLOOKUP(G14,Dados!$M$3:$N$500,2,0),"") | AG14: =IF(F14="","",IF(AND(AD14="",AE14="",AF14=""),"-",IF(AND(AD14="BIT",AE14="",AF14=""),"BIT",IF(AND(AE14="ANEXO I",AD14="",AF14=""),"ANEXO I",IF(AND(AF14="ANEXO II",AD14="",AE14=""),"ANEXO II","Escolher"))))) | AH14: =IF(AG14<>"Pneus","",IFERROR(VLOOKUP(R14,Dados!$X$2:$Z$5,3,0)*(AI14-Q14),VLOOKUP(D14,Dados!$X$7:$Z$33,3,0)*(AI14-Q14))) | AI14: =IF(B14="","",P14+Q14+O14+M14+L14-N14) | AJ14: =IFERROR(IF(AND(AC14="SIM",AG14="-",Y14="REVENDA"),(AB14/1+1)*AI14,IF(AND(AC14="SIM",AG14="Pneus",Y14="REVENDA"),(AB14/1+1)*(AI14-AH14),"")),"") | AK14: =IF(AJ14="","",AJ14*17%) | AL14: =IFERROR(IF(AC14="NÃO","",IF(AK14="","",IF(E14="Simples Nacional",BF14,IF(T14=0.12,U14*0.5833337002,IF(T14=0,AI14*0.07,U14))))),"") | AM14: =IFERROR(IF(AC14="NÃO","",IF(OR(AG14="-",AG14="Pneus"),AK14-AL14,"")),"") | AN14: =IF(AND(Y14="REVENDA",AC14="SIM",AG14="BIT"),((AB14/1+1)*AI14)*0.4117,"") | AO14: =IF(AN14="","",AN14*17%) | AP14: =IF(AN14="","",IF(T14=0.12,(U14*0.4117)*0.4117,IF(T14=0,(AI14*0.07)*0.4117,U14*0.4117))) | AQ14: =IF(AN14="","",AO14-AP14) | AR14: =IFERROR(IF(AND(AC14="SIM",Y14="REVENDA",LEFT(AG14,5)="ANEXO")*OR(AE14="ANEXO I",AF14="ANEXO II"),VLOOKUP(H14,Dados!G:I,2,0),""),"INSERIR MVA") | AS14: =IF(LEFT(AG14,5)="ANEXO",VLOOKUP(AG14,Dados!$X$111:$Z$112,2,0)*(AI14-Q14),"") | AT14: =IFERROR(IF(AR14="","",(AI14*AR14)+AI14),"INSERIR MVA") | AU14: =IF(AT14="","",IF(AY14=0.04,U14,AS14*AY14)) | AV14: =IFERROR(IF(AU14="","",(VLOOKUP(AG14,Dados!$X$111:$Z$112,3,0)*AT14*0.17)),"INSERIR MVA") | AW14: =IFERROR(IF(AR14="","",AV14-AU14),"") | AX14: =IFERROR(IF(AC14="NÃO","",IF(AM14<>"",AM14-W14,IF(AQ14<>"",AQ14-W14,IF(AW14<>"",AW14-W14,"")))),"") | AY14: =IFERROR(IF(ISNA(VLOOKUP(R14,Dados!$X$2:$Y$5,2,0)),VLOOKUP(D14,Dados!$X$7:$Y$33,2,0),VLOOKUP(R14,Dados!$X$2:$Y$5,2,0)),"") | AZ14: =IF(C14="","",IF(AND(Y14="CONSUMO",AC14="NÃO")*OR(AG14="-",AG14="BIT"),IF(E14<>"",(AI14-(P14+L14-N14+Q14)*AY14)/0.83),"")) | BA14: =IF(AZ14="","",AZ14*0.17-((P14+L14-N14+Q14)*AY14)) | BB14: =IF(AND(Y14="CONSUMO",AG14="ANEXO I",AY14>4%),(AI14-(P14+L14-N14+Q14)*0.0514)/0.83*(0.5177)*(0.17)-AI14*0.0514,IF(AND(Y14="CONSUMO",AG14="ANEXO II",AY14>4%),(AI14-(P14+L14-N14+Q14)*0.041)/0.83*(0.3295)*(0.17)-AI14*0.041,IF(AND(Y14="CONSUMO",AG14="ANEXO I",AY14=4%),(AI14-(P14+L14-N14+Q14)*0.04)/0.83*(0.5177)*(0.17)-AI14*0.04,IF(AND(Y14="CONSUMO",AG14="ANEXO II",AY14=4%),(AI14-(P14+L14-N14+Q14)*0.04)/0.83*(0.3295)*(0.17)-AI14*0.04,"")))) | BC14: =IF(C14="","",IF(AND(Y14="CONSUMO",AC14="SIM")*OR(AG14="-",AG14="BIT"),IF(E14<>"",(AI14-(P14+L14-N14+Q14)*AY14)/0.83),"")) | BD14: =IF(BC14="","",BC14*0.17) | BE14: =IF(I14=6908,0,IF(BC14="","",BD14-((P14+L14-N14+Q14)*AY14))) | BF14: =IF(B14="","",IF(OR(B14="",E14="Regime Normal"),0,(AI14-Q14)*VLOOKUP(R14,Dados!$X$98:$Y$108,2,0))) | BG14: =IFERROR(VLOOKUP(I14,Dados!$AC$27:$AD$43,2,0),IF(B14="","",IF(D14<>"MT",IF(AND(AC14="SIM",Y14="Revenda"),"2403",IF(AND(AC14="SIM",Y14="Consumo"),"2407",IF(AND(AC14="NÃO",Y14="Revenda"),"2102",IF(AND(AC14="NÃO",Y14="Consumo"),"2556",)))),REPLACE(I14,1,1,1))))
... Z2499: =IF(B2499="","",(IFERROR(VLOOKUP(H2499,Dados!A$3:B$15000,2,0),"Não Encontrado"))) | AA2499: =IF(B2499="","",(IFERROR(VLOOKUP(G2499,Dados!C$3:E$15000,3,0),"Não Encontrado"))) | AB2499: =IFERROR(IF(Z2499<>"Não Encontrado",Z2499,IF(AA2499<>"Não Encontrado",AA2499,"")),"") | AC2499: =IF(B2499="","",IF(AB2499="","NÃO","SIM")) | AD2499: =IFERROR(VLOOKUP(G2499,Dados!$P$3:$R$500,3,0),"") | AE2499: =IFERROR(VLOOKUP(G2499,Dados!$K$3:$L$500,2,0),"") | AF2499: =IFERROR(VLOOKUP(G2499,Dados!$M$3:$N$500,2,0),"") | AG2499: =IF(F2499="","",IF(AND(AD2499="",AE2499="",AF2499=""),"-",IF(AND(AD2499="BIT",AE2499="",AF2499=""),"BIT",IF(AND(AE2499="ANEXO I",AD2499="",AF2499=""),"ANEXO I",IF(AND(AF2499="ANEXO II",AD2499="",AE2499=""),"ANEXO II","Escolher"))))) | AH2499: =IF(AG2499<>"Pneus","",IFERROR(VLOOKUP(R2499,Dados!$X$2:$Z$5,3,0)*(AI2499-Q2499),VLOOKUP(D2499,Dados!$X$7:$Z$33,3,0)*(AI2499-Q2499))) | AI2499: =IF(B2499="","",P2499+Q2499+O2499+M2499+L2499-N2499) | AJ2499: =IFERROR(IF(AND(AC2499="SIM",AG2499="-",Y2499="REVENDA"),(AB2499/1+1)*AI2499,IF(AND(AC2499="SIM",AG2499="Pneus",Y2499="REVENDA"),(AB2499/1+1)*(AI2499-AH2499),"")),"") | AK2499: =IF(AJ2499="","",AJ2499*17%) | AL2499: =IFERROR(IF(AC2499="NÃO","",IF(AK2499="","",IF(E2499="Simples Nacional",BF2499,IF(T2499=0.12,U2499*0.5833337002,IF(T2499=0,AI2499*0.07,U2499))))),"") | AM2499: =IFERROR(IF(AC2499="NÃO","",IF(OR(AG2499="-",AG2499="Pneus"),AK2499-AL2499,"")),"") | AN2499: =IF(AND(Y2499="REVENDA",AC2499="SIM",AG2499="BIT"),((AB2499/1+1)*AI2499)*0.4117,"") | AO2499: =IF(AN2499="","",AN2499*17%) | AP2499: =IF(AN2499="","",IF(T2499=0.12,(U2499*0.4117)*0.4117,IF(T2499=0,(AI2499*0.07)*0.4117,U2499*0.4117))) | AQ2499: =IF(AN2499="","",AO2499-AP2499) | AR2499: =IFERROR(IF(AND(AC2499="SIM",Y2499="REVENDA",LEFT(AG2499,5)="ANEXO")*OR(AE2499="ANEXO I",AF2499="ANEXO II"),VLOOKUP(H2499,Dados!G:I,2,0),""),"INSERIR MVA") | AS2499: =IF(LEFT(AG2499,5)="ANEXO",VLOOKUP(AG2499,Dados!$X$111:$Z$112,2,0)*(AI2499-Q2499),"") | AT2499: =IFERROR(IF(AR2499="","",(AI2499*AR2499)+AI2499),"INSERIR MVA") | AU2499: =IF(AT2499="","",IF(AY2499=0.04,U2499,AS2499*AY2499)) | AV2499: =IFERROR(IF(AU2499="","",(VLOOKUP(AG2499,Dados!$X$111:$Z$112,3,0)*AT2499*0.17)),"INSERIR MVA") | AW2499: =IFERROR(IF(AR2499="","",AV2499-AU2499),"") | AX2499: =IFERROR(IF(AC2499="NÃO","",IF(AM2499<>"",AM2499-W2499,IF(AQ2499<>"",AQ2499-W2499,IF(AW2499<>"",AW2499-W2499,"")))),"") | AY2499: =IFERROR(IF(ISNA(VLOOKUP(R2499,Dados!$X$2:$Y$5,2,0)),VLOOKUP(D2499,Dados!$X$7:$Y$33,2,0),VLOOKUP(R2499,Dados!$X$2:$Y$5,2,0)),"") | AZ2499: =IF(C2499="","",IF(AND(Y2499="CONSUMO",AC2499="NÃO")*OR(AG2499="-",AG2499="BIT"),IF(E2499<>"",(AI2499-(P2499+L2499-N2499+Q2499)*AY2499)/0.83),"")) | BA2499: =IF(AZ2499="","",AZ2499*0.17-((P2499+L2499-N2499+Q2499)*AY2499)) | BB2499: =IF(AND(Y2499="CONSUMO",AG2499="ANEXO I",AY2499>4%),(AI2499-(P2499+L2499-N2499+Q2499)*0.0514)/0.83*(0.5177)*(0.17)-AI2499*0.0514,IF(AND(Y2499="CONSUMO",AG2499="ANEXO II",AY2499>4%),(AI2499-(P2499+L2499-N2499+Q2499)*0.041)/0.83*(0.3295)*(0.17)-AI2499*0.041,IF(AND(Y2499="CONSUMO",AG2499="ANEXO I",AY2499=4%),(AI2499-(P2499+L2499-N2499+Q2499)*0.04)/0.83*(0.5177)*(0.17)-AI2499*0.04,IF(AND(Y2499="CONSUMO",AG2499="ANEXO II",AY2499=4%),(AI2499-(P2499+L2499-N2499+Q2499)*0.04)/0.83*(0.3295)*(0.17)-AI2499*0.04,"")))) | BC2499: =IF(C2499="","",IF(AND(Y2499="CONSUMO",AC2499="SIM")*OR(AG2499="-",AG2499="BIT"),IF(E2499<>"",(AI2499-(P2499+L2499-N2499+Q2499)*AY2499)/0.83),"")) | BD2499: =IF(BC2499="","",BC2499*0.17) | BE2499: =IF(I2499=6908,0,IF(BC2499="","",BD2499-((P2499+L2499-N2499+Q2499)*AY2499))) | BF2499: =IF(B2499="","",IF(OR(B2499="",E2499="Regime Normal"),0,(AI2499-Q2499)*VLOOKUP(R2499,Dados!$X$98:$Y$108,2,0))) | BG2499: =IFERROR(VLOOKUP(I2499,Dados!$AC$27:$AD$43,2,0),IF(B2499="","",IF(D2499<>"MT",IF(AND(AC2499="SIM",Y2499="Revenda"),"2403",IF(AND(AC2499="SIM",Y2499="Consumo"),"2407",IF(AND(AC2499="NÃO",Y2499="Revenda"),"2102",IF(AND(AC2499="NÃO",Y2499="Consumo"),"2556",)))),REPLACE(I2499,1,1,1))))

Sheet Relatorio
A1: Chave de Acesso | B1: NFE | C1: DT EMISSÃO | D1: ICMS ST DESTACADO | E1: Diferença de ICMS ST a Recolher (Cód 2817) | F1: Difal USO/CONS Imobilizado CG | G1: Difal USO/CONS Imobilizado CONVENIO | H1: Difal USO/CONS Imobilizado ST | I1: Soma DIFAL (1317) | J1: Data P/ Pagamento | K1: CM | L1: Juros | M1: Dias em Atraso
D2: =IF($B2="", "",SUMIF(LerXml!B:B,Relatorio!B2,LerXml!W:W)) | E2: =IF($B2="", "",SUMIF(LerXml!B:B,Relatorio!B2,LerXml!AX:AX)) | F2: =IF($B2="", "",SUMIF(LerXml!B:B,Relatorio!B2,LerXml!BA:BA)) | G2: =IF($B2="", "",SUMIF(LerXml!B:B,Relatorio!B2,LerXml!BB:BB)) | H2: =IF($B2="", "",SUMIF(LerXml!B:B,Relatorio!B2,LerXml!BE:BE)) | I2: =IF(AND($F2="",$G2="",$H2=""), "", SUM(F2:H2))
C3: 45867 | D3: =IF($B3="", "",SUMIF(LerXml!B:B,Relatorio!B3,LerXml!W:W)) | E3: =IF($B3="", "",SUMIF(LerXml!B:B,Relatorio!B3,LerXml!AX:AX)) | F3: =IF($B3="", "",SUMIF(LerXml!B:B,Relatorio!B3,LerXml!BA:BA)) | G3: =IF($B3="", "",SUMIF(LerXml!B:B,Relatorio!B3,LerXml!BB:BB)) | H3: =IF($B3="", "",SUMIF(LerXml!B:B,Relatorio!B3,LerXml!BE:BE)) | I3: =IF(AND($F3="",$G3="",$H3=""), "", IF(SUM(F3:H3)-D3 < 0,0,SUM(F3:H3)-D3))
D4: =IF($B4="", "",SUMIF(LerXml!B:B,Relatorio!B4,LerXml!W:W)) | E4: =IF($B4="", "",SUMIF(LerXml!B:B,Relatorio!B4,LerXml!AX:AX)) | F4: =IF($B4="", "",SUMIF(LerXml!B:B,Relatorio!B4,LerXml!BA:BA)) | G4: =IF($B4="", "",SUMIF(LerXml!B:B,Relatorio!B4,LerXml!BB:BB)) | H4: =IF($B4="", "",SUMIF(LerXml!B:B,Relatorio!B4,LerXml!BE:BE)) | I4: =IF(AND($F4="",$G4="",$H4=""), "", IF(SUM(F4:H4)-D4 < 0,0,SUM(F4:H4)-D4))
D5: =IF($B5="", "",SUMIF(LerXml!B:B,Relatorio!B5,LerXml!W:W)) | E5: =IF($B5="", "",SUMIF(LerXml!B:B,Relatorio!B5,LerXml!AX:AX)) | F5: =IF($B5="", "",SUMIF(LerXml!B:B,Relatorio!B5,LerXml!BA:BA)) | G5: =IF($B5="", "",SUMIF(LerXml!B:B,Relatorio!B5,LerXml!BB:BB)) | H5: =IF($B5="", "",SUMIF(LerXml!B:B,Relatorio!B5,LerXml!BE:BE)) | I5: =IF(AND($F5="",$G5="",$H5=""), "", IF(SUM(F5:H5)-D5 < 0,0,SUM(F5:H5)-D5))
D6: =IF($B6="", "",SUMIF(LerXml!B:B,Relatorio!B6,LerXml!W:W)) | E6: =IF($B6="", "",SUMIF(LerXml!B:B,Relatorio!B6,LerXml!AX:AX)) | F6: =IF($B6="", "",SUMIF(LerXml!B:B,Relatorio!B6,LerXml!BA:BA)) | G6: =IF($B6="", "",SUMIF(LerXml!B:B,Relatorio!B6,LerXml!BB:BB)) | H6: =IF($B6="", "",SUMIF(LerXml!B:B,Relatorio!B6,LerXml!BE:BE)) | I6: =IF(AND($F6="",$G6="",$H6=""), "", IF(SUM(F6:H6)-D6 < 0,0,SUM(F6:H6)-D6))
D7: =IF($B7="", "",SUMIF(LerXml!B:B,Relatorio!B7,LerXml!W:W)) | E7: =IF($B7="", "",SUMIF(LerXml!B:B,Relatorio!B7,LerXml!AX:AX)) | F7: =IF($B7="", "",SUMIF(LerXml!B:B,Relatorio!B7,LerXml!BA:BA)) | G7: =IF($B7="", "",SUMIF(LerXml!B:B,Relatorio!B7,LerXml!BB:BB)) | H7: =IF($B7="", "",SUMIF(LerXml!B:B,Relatorio!B7,LerXml!BE:BE)) | I7: =IF(AND($F7="",$G7="",$H7=""), "", IF(SUM(F7:H7)-D7 < 0,0,SUM(F7:H7)-D7))
D8: =IF($B8="", "",SUMIF(LerXml!B:B,Relatorio!B8,LerXml!W:W)) | E8: =IF($B8="", "",SUMIF(LerXml!B:B,Relatorio!B8,LerXml!AX:AX)) | F8: =IF($B8="", "",SUMIF(LerXml!B:B,Relatorio!B8,LerXml!BA:BA)) | G8: =IF($B8="", "",SUMIF(LerXml!B:B,Relatorio!B8,LerXml!BB:BB)) | H8: =IF($B8="", "",SUMIF(LerXml!B:B,Relatorio!B8,LerXml!BE:BE)) | I8: =IF(AND($F8="",$G8="",$H8=""), "", IF(SUM(F8:H8)-D8 < 0,0,SUM(F8:H8)-D8))
D9: =IF($B9="", "",SUMIF(LerXml!B:B,Relatorio!B9,LerXml!W:W)) | E9: =IF($B9="", "",SUMIF(LerXml!B:B,Relatorio!B9,LerXml!AX:AX)) | F9: =IF($B9="", "",SUMIF(LerXml!B:B,Relatorio!B9,LerXml!BA:BA)) | G9: =IF($B9="", "",SUMIF(LerXml!B:B,Relatorio!B9,LerXml!BB:BB)) | H9: =IF($B9="", "",SUMIF(LerXml!B:B,Relatorio!B9,LerXml!BE:BE)) | I9: =IF(AND($F9="",$G9="",$H9=""), "", IF(SUM(F9:H9)-D9 < 0,0,SUM(F9:H9)-D9))
D10: =IF($B10="", "",SUMIF(LerXml!B:B,Relatorio!B10,LerXml!W:W)) | E10: =IF($B10="", "",SUMIF(LerXml!B:B,Relatorio!B10,LerXml!AX:AX)) | F10: =IF($B10="", "",SUMIF(LerXml!B:B,Relatorio!B10,LerXml!BA:BA)) | G10: =IF($B10="", "",SUMIF(LerXml!B:B,Relatorio!B10,LerXml!BB:BB)) | H10: =IF($B10="", "",SUMIF(LerXml!B:B,Relatorio!B10,LerXml!BE:BE)) | I10: =IF(AND($F10="",$G10="",$H10=""), "", IF(SUM(F10:H10)-D10 < 0,0,SUM(F10:H10)-D10))
D11: =IF($B11="", "",SUMIF(LerXml!B:B,Relatorio!B11,LerXml!W:W)) | E11: =IF($B11="", "",SUMIF(LerXml!B:B,Relatorio!B11,LerXml!AX:AX)) | F11: =IF($B11="", "",SUMIF(LerXml!B:B,Relatorio!B11,LerXml!BA:BA)) | G11: =IF($B11="", "",SUMIF(LerXml!B:B,Relatorio!B11,LerXml!BB:BB)) | H11: =IF($B11="", "",SUMIF(LerXml!B:B,Relatorio!B11,LerXml!BE:BE)) | I11: =IF(AND($F11="",$G11="",$H11=""), "", IF(SUM(F11:H11)-D11 < 0,0,SUM(F11:H11)-D11))
D12: =IF($B12="", "",SUMIF(LerXml!B:B,Relatorio!B12,LerXml!W:W)) | E12: =IF($B12="", "",SUMIF(LerXml!B:B,Relatorio!B12,LerXml!AX:AX)) | F12: =IF($B12="", "",SUMIF(LerXml!B:B,Relatorio!B12,LerXml!BA:BA)) | G12: =IF($B12="", "",SUMIF(LerXml!B:B,Relatorio!B12,LerXml!BB:BB)) | H12: =IF($B12="", "",SUMIF(LerXml!B:B,Relatorio!B12,LerXml!BE:BE)) | I12: =IF(AND($F12="",$G12="",$H12=""), "", IF(SUM(F12:H12)-D12 < 0,0,SUM(F12:H12)-D12))
D13: =IF($B13="", "",SUMIF(LerXml!B:B,Relatorio!B13,LerXml!W:W)) | E13: =IF($B13="", "",SUMIF(LerXml!B:B,Relatorio!B13,LerXml!AX:AX)) | F13: =IF($B13="", "",SUMIF(LerXml!B:B,Relatorio!B13,LerXml!BA:BA)) | G13: =IF($B13="", "",SUMIF(LerXml!B:B,Relatorio!B13,LerXml!BB:BB)) | H13: =IF($B13="", "",SUMIF(LerXml!B:B,Relatorio!B13,LerXml!BE:BE)) | I13: =IF(AND($F13="",$G13="",$H13=""), "", IF(SUM(F13:H13)-D13 < 0,0,SUM(F13:H13)-D13))
D14: =IF($B14="", "",SUMIF(LerXml!B:B,Relatorio!B14,LerXml!W:W)) | E14: =IF($B14="", "",SUMIF(LerXml!B:B,Relatorio!B14,LerXml!AX:AX)) | F14: =IF($B14="", "",SUMIF(LerXml!B:B,Relatorio!B14,LerXml!BA:BA)) | G14: =IF($B14="", "",SUMIF(LerXml!B:B,Relatorio!B14,LerXml!BB:BB)) | H14: =IF($B14="", "",SUMIF(LerXml!B:B,Relatorio!B14,LerXml!BE:BE)) | I14: =IF(AND($F14="",$G14="",$H14=""), "", IF(SUM(F14:H14)-D14 < 0,0,SUM(F14:H14)-D14))
D15: =IF($B15="", "",SUMIF(LerXml!B:B,Relatorio!B15,LerXml!W:W)) | E15: =IF($B15="", "",SUMIF(LerXml!B:B,Relatorio!B15,LerXml!AX:AX)) | F15: =IF($B15="", "",SUMIF(LerXml!B:B,Relatorio!B15,LerXml!BA:BA)) | G15: =IF($B15="", "",SUMIF(LerXml!B:B,Relatorio!B15,LerXml!BB:BB)) | H15: =IF($B15="", "",SUMIF(LerXml!B:B,Relatorio!B15,LerXml!BE:BE)) | I15: =IF(AND($F15="",$G15="",$H15=""), "", IF(SUM(F15:H15)-D15 < 0,0,SUM(F15:H15)-D15))
... D2499: =IF($B2499="", "",SUMIF(LerXml!B:B,Relatorio!B2499,LerXml!W:W)) | E2499: =IF($B2499="", "",SUMIF(LerXml!B:B,Relatorio!B2499,LerXml!AX:AX)) | F2499: =IF($B2499="", "",SUMIF(LerXml!B:B,Relatorio!B2499,LerXml!BA:BA)) | G2499: =IF($B2499="", "",SUMIF(LerXml!B:B,Relatorio!B2499,LerXml!BB:BB)) | H2499: =IF($B2499="", "",SUMIF(LerXml!B:B,Relatorio!B2499,LerXml!BE:BE)) | I2499: =IF(AND($F2499="",$G2499="",$H2499=""), "", IF(SUM(F2499:H2499)-D2499 < 0,0,SUM(F2499:H2499)-D2499))

Sheet Portaria 195
A1: NCM SEM PONTOS | B1: NCM 8 DIG | C1: NCM 7 DIG | D1: NCM 6 DIG | E1: NCM 5 DIG | F1: NCM 4 | G1: DESCRIÇÃO CONFORME PORTARIA | H1: MVA | I1: SEGUIMENTO
A2: 38151210 | B2: 3815.12.10 | G2: Catalisadores em colmeia cerâmica ou metálica para conversão catalítica de gases de escape de veículos e outros catalisadores | H2: 0.5039 | I2: I - AUTOPEÇAS
A3: 38151290 | B3: 3815.12.90 | G3: Catalisadores em colmeia cerâmica ou metálica para conversão catalítica de gases de escape de veículos e outros catalisadores | H3: 0.5039 | I3: I - AUTOPEÇAS
A4: 3917 | F4: 3917 | G4: Tubos e seus acessórios (por exemplo, juntas, cotovelos, flanges, uniões), de plásticos | H4: 0.5039 | I4: I - AUTOPEÇAS
A5: 39181000 | B5: 3918.10.00 | G5: Protetores de caçamba | H5: 0.5039 | I5: I - AUTOPEÇAS
A6: 39233000 | B6: 3923.30.00 | G6: Reservatórios de óleo | H6: 0.5039 | I6: I - AUTOPEÇAS
A7: 39263000 | B7: 3926.30.00 | G7: Frisos, decalques, molduras e acabamentos | H7: 0.5039 | I7: I - AUTOPEÇAS
A8: 40103 | E8: 4010.3 | G8: Correias de transmissão de borracha vulcanizada, de matérias têxteis, mesmo impregnadas, revestidas ou recobertas, de plástico, ou estratificadas com plástico ou reforçadas com metal ou com outras matérias | H8: 0.5039 | I8: I - AUTOPEÇAS
A9: 59100000 | B9: 5910.00.00 | G9: Correias de transmissão de borracha vulcanizada, de matérias têxteis, mesmo impregnadas, revestidas ou recobertas, de plástico, ou estratificadas com plástico ou reforçadas com metal ou com outras matérias | H9: 0.5039 | I9: I - AUTOPEÇAS
A10: 40169300 | B10: 4016.93.00 | G10: Juntas, gaxetas e outros elementos com função semelhante de vedação | H10: 0.5039 | I10: I - AUTOPEÇAS
A11: 4823909 | C11: 4823.90.9 | G11: Juntas, gaxetas e outros elementos com função semelhante de vedação | H11: 0.5039 | I11: I - AUTOPEÇAS
A12: 40161010 | B12: 4016.10.10 | G12: Partes de veículos automóveis, tratores e máquinas autopropulsadas | H12: 0.5039 | I12: I - AUTOPEÇAS
A13: 40169990 | B13: 4016.99.90 | G13: Tapetes, revestimentos, mesmo confeccionados, batentes, buchas e coxins | H13: 0.5039 | I13: I - AUTOPEÇAS
A14: 57050000 | B14: 5705.00.00 | G14: Tapetes, revestimentos, mesmo confeccionados, batentes, buchas e coxins | H14: 0.5039 | I14: I - AUTOPEÇAS
A15: 59039000 | B15: 5903.90.00 | G15: Tecidos impregnados, revestidos, recobertos ou estratificados, com plástico | H15: 0.5039 | I15: I - AUTOPEÇAS
A16: 59090000 | B16: 5909.00.00 | G16: Mangueiras e tubos semelhantes, de matérias têxteis, mesmo com reforço ou acessórios de outras matérias | H16: 0.5039 | I16: I - AUTOPEÇAS
A17: 63061 | E17: 6306.1 | G17: Encerados e toldos | H17: 0.5039 | I17: I - AUTOPEÇAS
A18: 65061000 | B18: 6506.10.00 | G18: Capacetes e artefatos de uso semelhante, de proteção, para uso em motocicletas, incluídos ciclomotores | H18: 0.5039 | I18: I - AUTOPEÇAS
A19: 6813 | F19: 6813 | G19: Guarnições de fricção (por exemplo, placas, rolos, tiras, segmentos, discos, anéis, pastilhas), não montadas, para freios, embreagens ou qualquer outro mecanismo de fricção, à base de amianto, de outras substâncias minerais ou de celulose, mesmo combinadas com têxteis ou outras matérias | H19: 0.5039 | I19: I - AUTOPEÇAS
A20: 70071100 | B20: 7007.11.00 | G20: Vidros de dimensões e formatos que permitam aplicação automotiva | H20: 0.5039 | I20: I - AUTOPEÇAS
A21: 70072100 | B21: 7007.21.00 | G21: Vidros de dimensões e formatos que permitam aplicação automotiva | H21: 0.5039 | I21: I - AUTOPEÇAS
A22: 70091000 | B22: 7009.10.00 | G22: Espelhos retrovisores | H22: 0.5039 | I22: I - AUTOPEÇAS
A23: 70140000 | B23: 7014.00.00 | G23: Lentes de faróis, lanternas e outros utensílios | H23: 0.5039 | I23: I - AUTOPEÇAS
A24: 73110000 | B24: 7311.00.00 | G24: Cilindro de aço para GNV (gás natural veicular) | H24: 0.5039 | I24: I - AUTOPEÇAS
A25: 73110000 | B25: 7311.00.00 | G25: Recipientes para gases comprimidos ou liquefeitos, de ferro fundido, ferro ou aço, exceto o descrito no item 18.0 | H25: 0.5039 | I25: I - AUTOPEÇAS
A26: 7320 | F26: 7320 | G26: Molas e folhas de molas, de ferro ou aço | H26: 0.5039 | I26: I - AUTOPEÇAS
A27: 7325 | F27: 7325 | G27: Obras moldadas, de ferro fundido, ferro ou aço, exceto as do código 7325.91.00 | H27: 0.5039 | I27: I - AUTOPEÇAS
A28: 780600 | D28: 7806.00 | G28: Peso de chumbo para balanceamento de roda | H28: 0.5039 | I28: I - AUTOPEÇAS
A29: 80070090 | B29: 8007.00.90 | G29: Peso para balanceamento de roda e outros utensílios de estanho | H29: 0.5039 | I29: I - AUTOPEÇAS
A30: 830120 | D30: 8301.20 | G30: Fechaduras e partes de fechaduras | H30: 0.5039 | I30: I - AUTOPEÇAS
A31: 830160 | D31: 8301.60 | G31: Fechaduras e partes de fechaduras | H31: 0.5039 | I31: I - AUTOPEÇAS
A32: 830170 | D32: 8301.70 | G32: Chaves apresentadas isoladamente | H32: 0.5039 | I32: I - AUTOPEÇAS
A33: 83021000 | B33: 8302.10.00 | G33: Dobradiças, guarnições, ferragens e artigos semelhantes de metais comuns | H33: 0.5039 | I33: I - AUTOPEÇAS
A34: 83023000 | B34: 8302.30.00 | G34: Dobradiças, guarnições, ferragens e artigos semelhantes de metais comuns | H34: 0.5039 | I34: I - AUTOPEÇAS
A35: 831000 | D35: 8310.00 | G35: Triângulo de segurança | H35: 0.5039 | I35: I - AUTOPEÇAS
A36: 84073 | E36: 8407.3 | G36: Motores de pistão alternativo dos tipos utilizados para propulsão de veículos do Capítulo 87 | H36: 0.5039 | I36: I - AUTOPEÇAS
A37: 840820 | D37: 8408.20 | G37: Motores dos tipos utilizados para propulsão de veículos automotores | H37: 0.5039 | I37: I - AUTOPEÇAS
A38: 84099 | E38: 8409.9 | G38: Partes reconhecíveis como exclusiva ou principalmente destinadas aos motores das posições 8407 ou 8408 | H38: 0.5039 | I38: I - AUTOPEÇAS
A39: 84122 | E39: 8412.2 | G39: Motores hidráulicos | H39: 0.5039 | I39: I - AUTOPEÇAS
A40: 841330 | D40: 8413.30 | G40: Bombas para combustíveis, lubrificantes ou líquidos de arrefecimento, próprias para motores de ignição por centelha ou por compressão | H40: 0.5039 | I40: I - AUTOPEÇAS
A41: 84141000 | B41: 8414.10.00 | G41: Bombas de vácuo | H41: 0.5039 | I41: I - AUTOPEÇAS
A42: 8414801 | C42: 8414.80.1 | G42: Compressores e turbocompressores de ar | H42: 0.5039 | I42: I - AUTOPEÇAS
A43: 8414802 | C43: 8414.80.2 | G43: Compressores e turbocompressores de ar | H43: 0.5039 | I43: I - AUTOPEÇAS
A44: 84139190 | B44: 8413.91.90 | G44: Partes das bombas, compressores e turbocompressores dos CEST 01.032.00, 01.033.00 e 01.034.00 | H44: 0.5039 | I44: I - AUTOPEÇAS
A45: 84149010 | B45: 8414.90.10 | G45: Partes das bombas, compressores e turbocompressores dos CEST 01.032.00, 01.033.00 e 01.034.00 | H45: 0.5039 | I45: I - AUTOPEÇAS
A46: 8414903 | C46: 8414.90.3 | G46: Partes das bombas, compressores e turbocompressores dos CEST 01.032.00, 01.033.00 e 01.034.00 | H46: 0.5039 | I46: I - AUTOPEÇAS
A47: 84149039 | B47: 8414.90.39 | G47: Partes das bombas, compressores e turbocompressores dos CEST 01.032.00, 01.033.00 e 01.034.00 | H47: 0.5039 | I47: I - AUTOPEÇAS
A48: 841520 | D48: 8415.20 | G48: Máquinas e aparelhos de ar condicionado | H48: 0.5039 | I48: I - AUTOPEÇAS
A49: 84212300 | B49: 8421.23.00 | G49: Aparelhos para filtrar óleos minerais nos motores de ignição por centelha ou por compressão | H49: 0.5039 | I49: I - AUTOPEÇAS
A50: 84212990 | B50: 8421.29.90 | G50: Filtros a vácuo | H50: 0.5039 | I50: I - AUTOPEÇAS
A51: 84219 | E51: 8421.9 | G51: Partes dos aparelhos para filtrar ou depurar líquidos ou gases | H51: 0.5039 | I51: I - AUTOPEÇAS
A52: 84241000 | B52: 8424.10.00 | G52: Extintores, mesmo carregados | H52: 0.5039 | I52: I - AUTOPEÇAS
A53: 84213100 | B53: 8421.31.00 | G53: Filtros de entrada de ar para motores de ignição por centelha ou por compressão | H53: 0.5039 | I53: I - AUTOPEÇAS
A54: 84213920 | B54: 8421.39.20 | G54: Depuradores por conversão catalítica de gases de escape | H54: 0.5039 | I54: I - AUTOPEÇAS
A55: 84254200 | B55: 8425.42.00 | G55: Macacos | H55: 0.5039 | I55: I - AUTOPEÇAS
A56: 84311010 | B56: 8431.10.10 | G56: Partes para macacos do CEST 01.043.00 | H56: 0.5039 | I56: I - AUTOPEÇAS
A57: 84339090 | B57: 8433.90.90 | G57: Partes reconhecíveis como exclusiva ou principalmente destinadas às máquinas agrícolas ou rodoviárias | H57: 0.5039 | I57: I - AUTOPEÇAS
A58: 84811000 | B58: 8481.10.00 | G58: Válvulas redutoras de pressão | H58: 0.5039 | I58: I - AUTOPEÇAS
A59: 84812 | E59: 8481.2 | G59: Válvulas para transmissão óleo-hidráulicas ou pneumáticas | H59: 0.5039 | I59: I - AUTOPEÇAS
A60: 84818092 | B60: 8481.80.92 | G60: Válvulas solenoides | H60: 0.5039 | I60: I - AUTOPEÇAS
A61: 8482 | F61: 8482 | G61: Rolamentos | H61: 0.5039 | I61: I - AUTOPEÇAS
A62: 8483 | F62: 8483 | G62: Árvores de transmissão (incluídas as árvores de "cames" e virabrequins) e manivelas; mancais e "bronzes"; engrenagens e rodas de fricção; eixos de esferas ou de roletes; redutores, multiplicadores, caixas de transmissão e variadores de velocidade, incluídos os conversores de torque; volantes e polias, incluídas as polias para cadernais; embreagens e dispositivos de acoplamento, incluídas as juntas de articulação | H62: 0.5039 | I62: I - AUTOPEÇAS
A63: 8484 | F63: 8484 | G63: Juntas metaloplásticas; jogos ou sortidos de juntas de composições diferentes, apresentados em bolsas, envelopes ou embalagens semelhantes; juntas de vedação mecânicas (selos mecânicos) | H63: 0.5039 | I63: I - AUTOPEÇAS
A64: 850520 | D64: 8505.20 | G64: Acoplamentos, embreagens, variadores de velocidade e freios, eletromagnéticos | H64: 0.5039 | I64: I - AUTOPEÇAS
A65: 850710 | D65: 8507.10 | G65: Acumuladores elétricos de chumbo, do tipo utilizado para o arranque dos motores de pistão, exceto os classificados no CEST 01.053.01 | H65: 0.5039 | I65: I - AUTOPEÇAS
A66: 85071010 | B66: 8507.10.10 | G66: Acumuladores elétricos de chumbo, do tipo utilizado para o arranque dos motores de pistão e de capacidade inferior ou igual a 20 Ah e tensão inferior ou igual a 12 V | H66: 0.5039 | I66: I - AUTOPEÇAS
A67: 8511 | F67: 8511 | G67: Aparelhos e dispositivos elétricos de ignição ou de arranque para motores de ignição por centelha ou por compressão (por exemplo, magnetos, dínamos-magnetos, bobinas de ignição, velas de ignição ou de aquecimento, motores de arranque); geradores (dínamos e alternadores, por exemplo) e conjuntores-disjuntores utilizados com estes motores | H67: 0.5039 | I67: I - AUTOPEÇAS
A68: 851220 | D68: 8512.20 | G68: Aparelhos elétricos de iluminação ou de sinalização (exceto os da posição 8539), limpadores de para-brisas, degeladores e desembaçadores (desembaciadores) elétricos e suas partes | H68: 0.5039 | I68: I - AUTOPEÇAS
A69: 851240 | D69: 8512.40 | G69: Aparelhos elétricos de iluminação ou de sinalização (exceto os da posição 8539), limpadores de para-brisas, degeladores e desembaçadores (desembaciadores) elétricos e suas partes | H69: 0.5039 | I69: I - AUTOPEÇAS
A70: 85129000 | B70: 8512.90.00 | G70: Aparelhos elétricos de iluminação ou de sinalização (exceto os da posição 8539), limpadores de para-brisas, degeladores e desembaçadores (desembaciadores) elétricos e suas partes | H70: 0.5039 | I70: I - AUTOPEÇAS
A71: 85171213 | B71: 8517.12.13 | G71: Telefones móveis do tipo dos utilizados em veículos automóveis. | H71: 0.5039 | I71: I - AUTOPEÇAS
A72: 8518 | F72: 8518 | G72: Alto-falantes, amplificadores elétricos de audiofrequência e partes | H72: 0.5039 | I72: I - AUTOPEÇAS
A73: 85185000 | B73: 8518.50.00 | G73: Aparelhos elétricos de amplificação de som para veículos automotores | H73: 0.5039 | I73: I - AUTOPEÇAS
A74: 851981 | D74: 8519.81 | G74: Aparelhos de reprodução de som | H74: 0.5039 | I74: I - AUTOPEÇAS
A75: 8525501 | C75: 8525.50.1 | G75: Aparelhos transmissores (emissores) de radiotelefonia ou radiotelegrafia (rádio receptor/transmissor) | H75: 0.5039 | I75: I - AUTOPEÇAS
A76: 85256010 | B76: 8525.60.10 | G76: Aparelhos transmissores (emissores) de radiotelefonia ou radiotelegrafia (rádio receptor/transmissor) | H76: 0.5039 | I76: I - AUTOPEÇAS
A77: 85272100 | B77: 8527.21.00 | G77: Aparelhos receptores de radiodifusão que só funcionem com fonte externa de energia combinados com um aparelho de gravação ou de reprodução de som, do tipo utilizado em veículos automóveis | H77: 0.5039 | I77: I - AUTOPEÇAS
A78: 85272900 | B78: 8527.29.00 | G78: Outros aparelhos receptores de radiodifusão que só funcionem com fonte externa de energia, do tipo utilizado em veículos automóveis | H78: 0.5039 | I78: I - AUTOPEÇAS
A79: 85219090 | B79: 8521.90.90 | G79: Outros aparelhos videofônicos de gravação ou de reprodução, mesmo incorporando um receptor de sinais videofônicos, dos tipos utilizados exclusivamente em veículos automotores | H79: 0.5039 | I79: I - AUTOPEÇAS
A80: 85291090 | B80: 8529.10.90 | G80: Antenas | H80: 0.5039 | I80: I - AUTOPEÇAS
A81: 853400 | D81: 8534.00 | G81: Circuitos impressos | H81: 0.5039 | I81: I - AUTOPEÇAS
A82: 853530 | D82: 8535.30 | G82: Interruptores e seccionadores e comutadores | H82: 0.5039 | I82: I - AUTOPEÇAS
A83: 853650 | D83: 8536.50 | G83: Interruptores e seccionadores e comutadores | H83: 0.5039 | I83: I - AUTOPEÇAS
A84: 85361000 | B84: 8536.10.00 | G84: Fusíveis e corta-circuitos de fusíveis | H84: 0.5039 | I84: I - AUTOPEÇAS
A85: 85362000 | B85: 8536.20.00 | G85: Disjuntores | H85: 0.5039 | I85: I - AUTOPEÇAS
A86: 85364 | E86: 8536.4 | G86: Relés | H86: 0.5039 | I86: I - AUTOPEÇAS
A87: 8538 | F87: 8538 | G87: Partes reconhecíveis como exclusivas ou principalmente destinados aos aparelhos dos CEST 01.065.00, 01.066.00, 01.067.00 e 01.068.00 | H87: 0.5039 | I87: I - AUTOPEÇAS
A88: 853910 | D88: 8539.10 | G88: Faróis e projetores, em unidades seladas | H88: 0.5039 | I88: I - AUTOPEÇAS
A89: 85392 | E89: 8539.2 | G89: Lâmpadas e tubos de incandescência, exceto de raios ultravioleta ou infravermelhos | H89: 0.5039 | I89: I - AUTOPEÇAS
A90: 85442000 | B90: 8544.20.00 | G90: Cabos coaxiais e outros condutores elétricos coaxiais | H90: 0.5039 | I90: I - AUTOPEÇAS
A91: 85443000 | B91: 8544.30.00 | G91: Jogos de fios para velas de ignição e outros jogos de fios | H91: 0.5039 | I91: I - AUTOPEÇAS
A92: 8707 | F92: 8707 | G92: Carroçarias para os veículos automóveis das posições 8701 a 8705, incluídas as cabinas | H92: 0.5039 | I92: I - AUTOPEÇAS
A93: 8708 | F93: 8708 | G93: Partes e acessórios dos veículos automóveis das posições 8701 a 8705 | H93: 0.5039 | I93: I - AUTOPEÇAS
A94: 87141 | E94: 8714.1 | G94: Parte e acessórios de motocicletas (incluídos os ciclomotores) | H94: 0.5039 | I94: I - AUTOPEÇAS
A95: 87169090 | B95: 8716.90.90 | G95: Engates para reboques e semirreboques | H95: 0.5039 | I95: I - AUTOPEÇAS
A96: 902610 | D96: 9026.10 | G96: Medidores de nível; Medidores de vazão | H96: 0.5039 | I96: I - AUTOPEÇAS
A97: 902620 | D97: 9026.20 | G97: Aparelhos para medida ou controle da pressão | H97: 0.5039 | I97: I - AUTOPEÇAS
A98: 9029 | F98: 9029 | G98: Contadores, indicadores de velocidade e tacômetros, suas partes e acessórios | H98: 0.5039 | I98: I - AUTOPEÇAS
A99: 90303321 | B99: 9030.33.21 | G99: Amperímetros | H99: 0.5039 | I99: I - AUTOPEÇAS
A100: 90318040 | B100: 9031.80.40 | G100: Aparelhos digitais, de uso em veículos automóveis, para medida e indicação de múltiplas grandezas tais como: velocidade média, consumos instantâneo e médio e autonomia (computador de bordo) | H100: 0.5039 | I100: I - AUTOPEÇAS
...

Sheet Convenio 52-91
A1: Brasil
A2: Acesso à informação
A4: Participe
A5: Serviços
A6: Legislação
A7: Canais
A9: Ir para o conteúdo 1
A10: Ir para o menu 2
A11: Ir para a busca 3
A12: Ir para o rodapé 4
A14: Acessibilidade
A15: Alto Contraste
... A46: Convênios ICMS
A47: 2019
A48: 2020
A49: 2021
A50: 1991
A51: CONVÊNIO ICMS 1/91
A52: CONVÊNIO ICMS 2/91
A53: CONVÊNIO ICMS 3/91
A54: CONVÊNIO ICMS 4/91
A55: CONVÊNIO ICMS 5/91
A56: CONVÊNIO ICMS 6/91
A57: CONVÊNIO ICMS 7/91
A58: CONVÊNIO ICMS 8/91
A59: CONVÊNIO ICMS 9/91
A60: CONVÊNIO ICMS 10/91
A61: CONVÊNIO ICMS 11/91
A62: CONVÊNIO ICMS 12/91
... A292: Nova redação dada ao Anexo I pelo Conv. ICMS 89/09, efeitos a partir de 15.10.09.
A293: ANEXO I | E293: ANEXO II
A294: CLÁUSULA PRIMEIRA DO CONVÊNIO ICMS 52/91 | E294: (CLÁUSULA SEGUNDA DO CONVÊNIO ICMS 52/91)
A295: MÁQUINAS, APARELHOS E EQUIPAMENTOS INDUSTRIAIS | E295: MÁQUINAS E IMPLEMENTOS AGRÍCOLAS
A296: ITEM | B296: DESCRIÇÃO | C296: NCM/SH | E296: ITEM | F296: DESCRIÇÃO | G296: NCM/SH
A297: 1 | B297: Cabeça de poço para perfuração de poços de petróleo | C297: 7307.19.20 | E297: 1 | F297: RESERVATÓRIOS, TAMBORES, LATAS E RECIPIENTES SEMELHANTES
A298: 2 | B298: Ferramentas de embutir, de estampar ou de puncionar | C298: 8207.30.00 | E298: 1.1 | F298: Reservatórios, tambores, latas e recipientes semelhantes, de plástico, de capacidade não superior a 300 litros, para transporte de leite | G298: 3923.90.00
A299: 3 | B299: Brocas | C299: 8207.19.00 | E299: 1.2 | F299: Reservatórios, tambores, latas e recipientes semelhantes, de liga de alumínio, de capacidade não superior a 300 litros, para transporte de leite | G299: 7612.90.90
A300: 4 | B300: CALDEIRAS DE VAPOR, SEUS APARELHOS AUXILIARES E GERADORES DE GÁS | E300: Nova redação dada ao item 1.3 do Anexo II pelo Conv. ICMS 182/10, efeitos a partir de 01.03.11.
A301: 4.1 | B301: Caldeiras aquatubulares com produção de vapor superior a 45 toneladas por hora | C301: 8402.11.00 | E301: 1.3 | F301: Reservatórios, tambores, latas e recipientes semelhantes, de ferro fundido, ferro ou aço, de capacidade não superior a 300 litros, para transporte de leite | G301: 7310.10.90,
A302: 4.2 | B302: Caldeiras aquatubulares com produção de vapor não superior a 45 toneladas por hora | C302: 8402.12.00 | G302: 7310.29.10 e
A303: 4.3 | B303: Outras caldeiras para produção de vapor, incluídas as caldeiras mistas | C303: 8402.19.00 | G303: 7310.29.90
A304: 4.4 | B304: Caldeiras denominadas 'de água superaquecida' | C304: 8402.20.00 | E304: Redação anterior dada ao item 1.3 do Anexo II pelo Conv. ICMS 89/09, efeitos de 15.10.09 a 28.02.11.
A305: 5 | B305: APARELHOS AUXILIARES PARA CALDEIRAS DAS POSIÇÕES 84.02 | E305: 1.3 | F305: Reservatórios, tambores, latas e recipientes semelhantes, de ferro fundido, ferro ou aço, de capacidade não superior a 300 litros, para transporte de leite | G305: 7310.10.90 e 7310.29.10
A306: 5.1 | B306: Aparelhos auxiliares para caldeiras das posições 84.02 | C306: 8404.10.10 | E306: 1.4 | F306: Reservatórios, tambores, latas e recipientes semelhantes, de latão (liga de cobre e zinco), de capacidade não superior a 300 litros, para transporte de leite | G306: 7419.99.90
A307: 5.2 | B307: Condensadores para máquinas a vapor | C307: 8404.20.00 | E307: 2 | F307: SILOS SEM DISPOSITIVOS DE VENTILAÇÃO OU AQUECIMENTO INCORPORADOS, MESMO QUE POSSUAM TUBULAÇÕES QUE PERMITAM A INJEÇÃO DE AR PARA VENTILAÇÃO OU AQUECIMENTO
A308: 6 | B308: Geradores de gás de ar (gás pobre) ou de gás de água, com ou sem depuradores; geradores de acetileno e geradores semelhantes de gás, operados a água, com ou sem depuradores | C308: 8405.10.00 | E308: Nova redação dada ao item 2.1 do Anexo II pelo Conv. ICMS 30/20, efeitos a partir de 01.06.2020.
A309: 7 | B309: TURBINAS A VAPOR | E309: 2.1 | F309: Silos de matéria plástica artificial ou de lona plastificada, com capacidade superior a 300 litros | G309: 3917.32.90
A310: 7.1 | B310: Turbinas para propulsão de embarcações | C310: 8406.10.00
A311: 7.2 | B311: Outras de potência superior a 40MW | C311: 8406.81.00 | G311: 3925.10.00
A312: 7.3 | B312: Outras de potência não superior a 40MW | C312: 8406.82.00 | E312: Redação original, efeitos até 31.05.2020.
A313: 8 | B313: TURBINAS HIDRÁULICAS, RODAS HIDRÁULICAS E SEUS REGULADORES | E313: 2.1 | F313: Silos de matéria plástica artificial ou de lona plastificada, com capacidade superior a 300 litros | G313: 3925.10.00
A314: 8.1 | B314: Turbinas e rodas hidráulicas de potência não superior a 1.000kW | C314: 8410.11.00 | E314: 2.2 | F314: Silos de ferro ou aço para armazenamento de grãos e outras matérias sólidas | G314: 7309.00.10
A315: 8.2 | B315: Turbinas e rodas hidráulicas de potência superior a 1.000kW, mas não superior a 10.000kW | C315: 8410.12.00 | E315: 2.3 | F315: Silos com dispositivos de ventilação ou aquecimento (ventiladores ou aquecedores) incorporados, de qualquer matéria | G315: 8419.89.99
A316: 8.3 | B316: Turbinas e rodas hidráulicas de potência superior a 10.000kW | C316: 8410.13.00 | E316: 2.4 | F316: Silos metálicos para cereais, fixos (não transportáveis), incluídas as baterias, com mecanismos elevadores ou extratores incorporados | G316: 8479.89.40
A317: 8.4 | B317: Reguladores | C317: 8410.90.00 | E317: 2.5 | F317: Silos pré-fabricados com estrutura de madeira e paredes exteriores constituídas essencialmente dessa matéria | G317: 9406.00.91
A318: 9 | B318: Máquinas a vapor, de êmbolos, separadas das respectivas caldeiras | C318: 8412.80.00 | E318: 2.6 | F318: Silos pré-fabricados com estrutura de ferro ou aço e paredes exteriores constituídas essencialmente dessa matéria | G318: 9406.00.92
A319: 10 | B319: OUTRAS BOMBAS CENTRÍFUGAS | E319: 3 | F319: Troncos (bretes) de contenção bovina | G319: 4421.90.00
A320: 10.1 | B320: Eletrobombas submersíveis | C320: 8413.70.10 | E320: 4 | F320: OBRAS MOLDADAS, DE FERRO FUNDIDO, FERRO OU AÇO
A321: 10.2 | B321: Bombas centrífugas, de vazão inferior ou igual a 300 litros por minuto | C321: 8413.70.80 | E321: 4.1 | F321: Comedouros para animais | G321: 7326.90.90
A322: 10.3 | B322: Outras bombas centrífugas | C322: 8413.70.90 | E322: 4.2 | F322: Ninhos metálicos para aves | G322: 7326.90.90
A323: 11 | B323: COMPRESSORES DE AR OU DE OUTROS GASES | E323: 4.3 | F323: Esteiras ou lagartas especiais para proteção de pneus de tratores | G323: 8708.70.90
A324: 11.1 | B324: Compressores de ar de parafuso | C324: 8414.80.12 | E324: 5 | F324: PÁS, ALVIÕES, PICARETAS, ENXADAS, SACHOS, FORCADOS, FORQUILHAS, ANCINHOS E RASPADEIRAS; MACHADOS, PODÕES E FERRAMENTAS SEMELHANTES COM GUME; TESOURAS DE PODAR DE TODOS OS TIPOS; FOICES E FOICINHAS, FACAS PARA FENO OU PARA PALHA, TESOURAS PARA SEBES, CUNHAS E OUTRAS FERRAMENTAS MANUAIS PARA AGRICULTURA, HORTICULTURA OU SILVICULTURA
A325: 11.2 | B325: Compressores de ar de lóbulos paralelos (tipo 'Roots') | C325: 8414.80.13 | E325: 5.1 | F325: Pás | G325: 8201.10.00
A326: 11.3 | B326: Outros compressores inclusive de anel líquido | C326: 8414.80.19 | E326: 5.2 | F326: Forcados e forquilhas | G326: 8201.20.00
A327: 11.4 | B327: Compressores de gases, exceto ar, de pistão | C327: 8414.80.31 | E327: 5.3 | F327: Alviões, picaretas, enxadas, sachos, ancinhos e raspadeiras | G327: 8201.30.00
A328: 11.5 | B328: Compressores de gases exceto ar, de parafuso | C328: 8414.80.32 | E328: 5.4 | F328: Machados, podões e ferramentas semelhantes com gume | G328: 8201.40.00
A329: 11.6 | B329: Compressores de gases exceto ar, centrífugos, de vazão máxima inferior a 22.000m3/h | C329: 8414.80.33 | E329: 5.5 | F329: Tesouras de podar (incluídas as tesouras para aves) manipuladas com uma das mãos | G329: 8201.50.00
A330: 11.7 | B330: Outros compressores centrífugos radiais | C330: 8414.80.38 | E330: 5.6 | F330: Tesouras para sebes, tesouras de podar e ferramentas semelhantes, manipuladas com as duas mãos | G330: 8201.60.00
A331: 11.8 | B331: Outros compressores de gases, exceto ar, inclusive axiais | C331: 8414.80.39 | E331: 5.7 | F331: Outras ferramentas manuais, para agricultura, horticultura e silvicultura | G331: 8201.90.00
A332: 12 | B332: QUEIMADORES PARA ALIMENTAÇÃO DE FORNALHAS DE COMBUSTÍVEIS LÍQUIDOS, COMBUSTÍVEIS SÓLIDOS PULVERIZADOS OU DE GÁS; FORNALHAS AUTOMÁTICAS, INCLUÍDOS AS ANTEFORNALHAS, GRELHAS MECÂNICAS, DESCARREGADORES MECÂNICOS DE CINZAS E DISPOSITIVOS SEMELHANTES | E332: 6 | F332: Moinhos de vento (cata-vento) destinados a bombear água | G332: 8412.80.00
A333: 12.1 | B333: Queimadores de combustíveis líquidos | C333: 8416.10.00 | E333: 7 | F333: DISPOSITIVOS DESTINADOS À SUSTENTAÇÃO DE SILOS (ARMAZÉNS) INFLÁVEIS, DESDE QUE AS SAÍDAS, DO MESMO ESTABELECIMENTO INDUSTRIAL, OCORRAM SIMULTANEAMENTE COM AS COBERTURAS DE LONA PLASTIFICADA OU DE MATÉRIA PLÁSTICA ARTIFICIAL, COM AS QUAIS FORMEM UM CONJUNTO COMPLETO
A334: 12.2 | B334: Outros queimadores, incluídos os mistos, de gases | C334: 8416.20.10 | E334: 7.1 | F334: Ventiladores | G334: 8414.59.90
A335: 12.3 | B335: Outros queimadores, inclusive de carvão pulverizado | C335: 8416.20.90 | E335: 7.2 | F335: Compressores de ar estacionários, de pistão | G335: 8414.80.11
A336: 12.4 | B336: Fornalhas automáticas, incluídas as antefornalhas, grelhas mecânicas, descarregadores mecânicos de cinzas e dispositivos semelhantes | C336: 8416.30.00 | E336: 7.3 | F336: Outros compressores de ar | G336: 8414.80.19
A337: 12.5 | B337: Ventaneiras | C337: 8416.90.00 | E337: 7.4 | F337: Coifas (exaustores) | G337: 8414.80.90
A338: 13 | B338: FORNOS INDUSTRIAIS, NÃO ELÉTRICOS | E338: 8 | F338: Secadores para produtos agrícolas | G338: 8419.31.00
A339: 13.1 | B339: Fornos industriais para fusão de metais | C339: 8417.10.10 | E339: 9 | F339: Balanças bovinas mecânicas ou eletrônicas | G339: 8423.82.00
A340: 13.2 | B340: Fornos industriais para tratamento térmico de metais | C340: 8417.10.20 | E340: 10 | F340: APARELHOS MECÂNICOS (MESMO MANUAIS) PARA PROJETAR, DISPERSAR OU PULVERIZAR LÍQUIDOS OU PÓS
A341: 13.3 | B341: Outros fornos para tratamento térmico de minérios ou de metais | C341: 8417.10.90 | E341: Nova redação dada ao subitem 10.1 do Anexo II pelo Conv. ICMS 146/20, efeitos a partir de 29.12.20.
A342: 13.4 | B342: Fornos de padaria, pastelaria ou para a indústria de bolachas e biscoito | C342: 8417.20.00 | E342: 10.1 | F342: Aparelho para projetar, dispersar ou pulverizar fungicidas, inseticidas e outros produtos para combate a pragas, de uso agrícola, manuais | G342: 8424.41.00
A343: 13.5 | B343: Fornos industriais para cerâmica | C343: 8417.80.10 | E343: Redação original do subitem 10.1 do Anexo II, efeitos até 28.12.20.
A344: 13.6 | B344: Fornos industriais para fusão de vidro | C344: 84178020 | E344: 10.1 | F344: Aparelho para projetar, dispersar ou pulverizar fungicidas, inseticidas e outros produtos para combate a pragas, de uso agrícola, manuais | G344: 8424.81.11
A345: Nova redação dada ao subitem 13.7 do Anexo I pelo Conv. ICMS 27/12, efeitos a partir de 01.06.12. | E345: Nova redação dada ao subitem 10.2 do Anexo II pelo Conv. ICMS 146/20, efeitos a partir de 29.12.20.
A346: 13.7 | B346: Outros fornos industriais. | C346: 8417.80.90 | E346: 10.2 | F346: Outros aparelhos para projetar, dispersar ou pulverizar fungicidas, inseticidas e outros produtos para combate a pragas, de uso agrícola | G346: 8424.49.00
A347: Redação anterior dada ao subitem 13.7 do Anexo I pelo Conv. ICMS 89/09, efeitos de 15.10.09 a 31.05.12. | E347: Redação original do subitem 10.2 do Anexo II, efeitos até 28.12.20.
A348: 13.7 | B348: Fornos industriais para carbonização de .7madeira | C348: 84178090 | E348: 10.2 | F348: Outros aparelhos para projetar, dispersar ou pulverizar fungicidas, inseticidas e outros produtos para combate a pragas, de uso agrícola | G348: 8424.81.19
A349: 14 | B349: MÁQUINAS PARA PRODUÇÃO DE FRIO | E349: Nova redação dada ao subitem 10.3 do Anexo II pelo Conv. ICMS 129/19, efeitos a partir de 29.07.19.
A350: 14.1 | B350: Sorveteiras industriais | C350: 8418.69.10 | E350: 10.3 | F350: Irrigadores e sistemas de irrigação para uso na lavoura, por aspersão, inclusive os elementos integrantes desses sistemas, como máquinas, aparelhos, equipamentos, dispositivos e instrumentos. | G350: 8424.82.21
A351: 14.2 | B351: Máquinas de fabricar gelo em cubos ou escamas; instalações frigoríficas industriais formadas por elementos não reunidos em corpo único, nem montadas sobre base comum | C351: 8418.69.99 | E351: Redação anterior dada ao subitem 10.3 do Anexo II pelo Conv. ICMS 140/10, efeitos de 01.12.10 a 28.07.19
A352: Acrescido o subitem 14.3 ao Anexo I pelo Conv. ICMS 55/10, efeitos a partir de 23.04.10. | E352: 10.3 | F352: Irrigadores e sistemas de irrigação para uso na lavoura, por aspersão, inclusive os elementos integrantes desses sistemas, como máquinas, aparelhos, equipamentos, dispositivos e instrumentos. | G352: 8424.81.21
A353: 14.3 | B353: Resfriadores de leite | C353: 8418.69.20 | E353: Redação anterior dada ao subitem 10.3 do Anexo II pelo Conv. ICMS 89/09, efeitos de 15.10.09 a 30.11.10.
A354: 15 | B354: APARELHOS E DISPOSITIVOS, MESMO AQUECIDOS ELETRICAMENTE (EXCETO OS FORNOS E OUTROS APARELHOS DA POSIÇÃO 85.14), PARA TRATAMENTO DE MATÉRIAS POR MEIO DE OPERAÇÕES QUE IMPLIQUEM MUDANÇA DE TEMPERATURA, TAIS COMO AQUECIMENTO, COZIMENTO, TORREFAÇÃO, DESTILAÇÃO, RETIFICAÇÃO, ESTERILIZAÇÃO, PASTEURIZAÇÃO, ESTUFAGEM, SECAGEM, EVAPORAÇÃO, VAPORIZAÇÃO, CONDENSAÇÃO OU ARREFECIMENTO, EXCETO OS DE USO DOMÉSTICO; AQUECEDORES DE ÁGUA NÃO ELÉTRICOS, DE AQUECIMENTO INSTANTÂNEO OU DE ACUMULAÇÃO | E354: 10.3 | F354: Irrigadores e sistemas de irrigação para uso na lavoura, por aspersão | G354: 8424.81.21
A355: 15.1 | B355: Secadores para madeiras, pastas de papel, papéis ou cartões | C355: 8419.32.00 | E355: Nova redação dada ao subitem 10.4 do Anexo II pelo Conv. ICMS 113/17, efeitos a partir de 26.10.17.
A356: 15.2 | B356: Outros secadores exceto para produtos agrícolas | C356: 8419.39.00 | E356: 10.4 | F356: Outros irrigadores e sistemas de irrigação, inclusive os elementos integrantes desses sistemas, como máquinas, aparelhos, equipamentos, dispositivos e instrumentos. | G356: 8424.82.29
A357: 15.3 | B357: Aparelhos de destilação de água | C357: 8419.40.10 | E357: Redação anterior dada ao subitem 10.4 do Anexo II pelo Conv. ICMS 140/10, efeitos de 01.12.10 a 25.10.17.
A358: 15.4 | B358: Aparelhos de destilação ou retificação de álcoois e outros fluídos voláteis ou de hidrocarbonetos | C358: 8419.40.20 | E358: 10.4 | F358: Outros irrigadores e sistemas de irrigação, inclusive os elementos integrantes desses sistemas, como máquinas, aparelhos, equipamentos, dispositivos e instrumentos. | G358: 8424.81.29
A359: 15.5 | B359: Outros aparelhos de destilação ou de retificação | C359: 8419.40.90 | E359: Redação anterior dada ao subitem 10.4 do Anexo II pelo Conv. ICMS 89/09, efeitos de 15.10.09 a 30.11.10.
A360: 15.6 | B360: Trocadores de calor de placas | C360: 8419.50.10 | E360: 10.4 | F360: Outros irrigadores e sistemas de irrigação | G360: 8424.81.29
A361: 15.7 | B361: Trocadores de calor tubulares metálicos | C361: 8419.50.21 | E361: 11 | F361: EMPILHADEIRAS; OUTROS VEÍCULOS PARA MOVIMENTAÇÃO DE CARGA E SEMELHANTES, EQUIPADOS COM DISPOSITIVOS DE ELEVAÇÃO
A362: 15.8 | B362: Trocadores de calor tubulares de grafite | C362: 8419.50.22 | E362: 11.1 | F362: Máquina apanhadora e carregadora de cana, autopropulsada | G362: 8427.20.90
...

Sheet BIT
A1: NCM | B1: DESCRIÇÃO (ÚLTIMA ATUALIZAÇÃO EM 01/07/2022) | C1: BIT
A2: 3705.00.10 | B2: Fotomáscaras sobre vidro plano, positivas, próprias para gravação em pastilhas de silício (chips) para fabricação de microestruturas eletrônicas | C2: 0BIT
A3: 6909.12.20 | B3: Guias de agulhas para cabeças de impressão | C3: 0BIT
A4: 6909.19.20 | B4: Guias de agulhas para cabeças de impressão | C4: 0BIT
A5: 7116.20.20 | B5: Guias de agulhas, de rubi, para cabeças de impressão | C5: 0BIT
A6: 7410.11.12 | B6: De espessura inferior ou igual a 0,04 mm e uma resistividade elétrica inferior ou igual a 0,017241 ohm.mm2/m | C6: 0BIT
A7: 7410.11.13 | B7: Outras, de espessura inferior ou igual a 0,04 mm | C7: 12BIT
A8: 7410.11.19 | B8: Outras | C8: 12BIT
A9: 7410.21.10 | B9: Com suporte isolante de resina epóxida e fibra de vidro, do tipo utilizado para circuitos impressos | C9: 4BIT
A10: 7410.21.20 | B10: Com espessura superior a 0,012 mm, sobre suporte de poliéster ou poliimida e com espessura total, incluindo o suporte, inferior ou igual a 0,195 mm | C10: 0BIT
A11: 7410.21.30 | B11: Com suporte isolante de resina fenólica e papel, do tipo utilizado para circuitos impressos | C11: 4BIT
A12: 8409.91.40 | B12: Sistema de injeção eletrônica | C12: 16BIT
... A66: 8471.49.00 | B66: -- Outras, apresentadas sob a forma de sistemas | C66: 16BIT
A67: 8471.50.10 | C67: 16BIT
A68: 8471.50.20 | C68: 12BIT
A69: 8471.50.30 | C69: 8BIT
A70: 8471.50.40 | C70: 4BIT
A71: 8471.50.90 | B71: Outras | C71: 16BIT
A72: 8471.60.52 | B72: Teclados | C72: 12BIT
A73: 8471.60.53 | B73: Indicadores ou apontadores (mouse e track-ball, por exemplo) | C73: 12BIT
A74: 8471.60.54 | B74: Mesas digitalizadoras | C74: 12BIT
A75: 8471.60.59 | B75: Outras | C75: 12BIT
A76: 8471.60.61 | B76: Com unidade de saída por vídeo monocromático | C76: 16BIT
A77: 8471.60.62 | B77: Com unidade de saída por vídeo policromático | C77: 16BIT
A78: 8471.60.80 | B78: Terminais de auto-atendimento bancário | C78: 16BIT
A79: 8471.60.90 | B79: Outras | C79: 16BIT
A80: 8471.70.10 | B80: De discos magnéticos | C80: 8BIT
A81: 8471.70.20 | B81: De discos para leitura ou gravação de dados por meios ópticos (unidade de disco óptico) | C81: 2BIT
A82: 8471.70.30 | B82: De fitas magnéticas | C82: 2BIT
... A361: 9032.90.99 | B361: Outros | C361: 8BIT

Sheet Dados
A1: LISTA DE TODOS OS NCM COM MVA DE ST DA PORTARIA 195/2019 | G1: LISTA ST PORTARIA 195/2019 ART 2B | K1: LISTA CONVENIO 52/91 E ANEXOS | P1: LISTA BIT | T1: Beneficios | U1: É ST? | V1: Tipo do Produto | X1: ORIGEM | AB1: 0.6529 | AC1: AUTO PEÇAS
A2: CEST | B2: MVA CEST | C2: NCM | D2: DESCRIÇÃO | E2: MVA NCM | G2: CEST | H2: MVA CONV | I2: SEGMENTO | K2: NCM ANEXO I | L2: ANEXO I | M2: NCM ANEXO II | N2: ANEXO II | P2: NCM BIT | Q2: DESCRIÇÃO | R2: BIT | T2: BIT | U2: SIM | V2: CONSUMO | X2: 1 | Y2: 0.04 | Z2: 0.085 | AB2: 0.6749 | AC2: BEBIDAS ALCOÓLICAS, EXCETO CERVEJA E CHOPE
A3: 1708400 | B3: 0.4552 | C3: 0101.21.00 | D3: Não Encontrado | E3: Não Encontrado | G3: 100100 | H3: 0.6529 | I3: AUTO PEÇAS | K3: 7307.19.20 | L3: ANEXO I | M3: 3923.90.00 | N3: ANEXO II | P3: 3705.00.10 | Q3: Fotomáscaras sobre vidro plano, positivas, próprias para gravação em pastilhas de silício (chips) para fabricação de microestruturas eletrônicas | R3: BIT | T3: Anexo I | U3: NÃO | V3: REVENDA | X3: 2 | Y3: 0.04 | Z3: 0.085 | AB3: 0.7363 | AC3: cervejas, chopes, refrigerantes, águas e outras bebidas
A4: 1708400 | B4: 0.4552 | C4: 0101.29.00 | D4: Não Encontrado | E4: Não Encontrado | G4: 100100 | H4: 0.6529 | I4: AUTO PEÇAS | K4: 8207.30.00 | L4: ANEXO I | M4: 7612.90.90 | N4: ANEXO II | P4: 6909.12.20 | Q4: Guias de agulhas para cabeças de impressão | R4: BIT | T4: Anexo II | X4: 3 | Y4: 0.04 | Z4: 0.085 | AB4: 0.2994 | AC4: cimento
A5: 1708701 | B5: 0.4552 | C5: 0101.30.00 | D5: Não Encontrado | E5: Não Encontrado | G5: 100200 | H5: 0.6529 | I5: AUTO PEÇAS | K5: 8207.19.00 | L5: ANEXO I | M5: 7310.10.90 | N5: ANEXO II | P5: 6909.19.20 | Q5: Guias de agulhas para cabeças de impressão | R5: BIT | T5: - | X5: 8 | Y5: 0.04 | Z5: 0.085 | AB5: 0.5561 | AC5: ferramentas
A6: 1708400 | B6: 0.4552 | C6: 0101.90.00 | D6: Não Encontrado | E6: Não Encontrado | G6: 100300 | H6: 0.6529 | I6: AUTO PEÇAS | K6: 8402.11.00 | L6: ANEXO I | M6: 7310.29.10 | N6: ANEXO II | P6: 7116.20.20 | Q6: Guias de agulhas, de rubi, para cabeças de impressão | R6: BIT | X6: ESTADO | Y6: ALIQUOTA | AB6: 0.6529 | AC6: ferramentas
A7: 1708500 | B7: 0.4552 | C7: 0102.21.10 | D7: Não Encontrado | E7: Não Encontrado | G7: 109000 | H7: 0.6529 | I7: AUTO PEÇAS | K7: 8402.12.00 | L7: ANEXO I | M7: 7310.29.90 | N7: ANEXO II | P7: 7410.11.12 | Q7: De espessura inferior ou igual a 0,04 mm e uma resistividade elétrica inferior ou igual a 0,017241 ohm.mm2/m | R7: BIT | X7: MG | Y7: 0.07 | Z7: 0.0878 | AB7: 0.8324 | AC7: lâmpadas, reatores e "starter"
A8: 1708400 | B8: 0.4552 | C8: 0102.21.90 | D8: Não Encontrado | E8: Não Encontrado | G8: 109000 | H8: 0.6529 | I8: AUTO PEÇAS | K8: 8402.19.00 | L8: ANEXO I | M8: 7419.99.90 | N8: ANEXO II | P8: 7410.11.13 | Q8: Outras, de espessura inferior ou igual a 0,04 mm | R8: BIT | X8: PR | Y8: 0.07 | Z8: 0.0878 | AB8: 1.0884 | AC8: lâmpadas, reatores e "starter"
A9: 1708701 | B9: 0.4552 | C9: 0102.29.11 | D9: Não Encontrado | E9: Não Encontrado | G9: 100400 | H9: 0.6529 | I9: AUTO PEÇAS | K9: 8402.20.00 | L9: ANEXO I | M9: 3917.32.90 | N9: ANEXO II | P9: 7410.11.19 | Q9: Outras | R9: BIT | T9: 4011.10.00 | U9: Pneus | X9: RS | Y9: 0.07 | Z9: 0.0878 | AB9: 0.6406 | AC9: lâmpadas, reatores e "starter"
A10: 1708700 | B10: 0.4552 | C10: 0102.29.19 | D10: Não Encontrado | E10: Não Encontrado | G10: 100500 | H10: 0.6529 | I10: AUTO PEÇAS | K10: 8404.10.10 | L10: ANEXO I | M10: 3925.10.00 | N10: ANEXO II | P10: 7410.21.10 | Q10: Com suporte isolante de resina epóxida e fibra de vidro, do tipo utilizado para circuitos impressos | R10: BIT | T10: 4011.20.10 | U10: Pneus | X10: RJ | Y10: 0.07 | Z10: 0.0878 | AB10: 0.7475 | AC10: materiais de construção e congêneres
A11: 1708702 | B11: 0.4552 | C11: 0102.29.90 | D11: Não Encontrado | E11: Não Encontrado | G11: 110300 | H11: 0.6529 | I11: AUTO PEÇAS | K11: 8404.20.00 | L11: ANEXO I | M11: 7309.00.10 | N11: ANEXO II | P11: 7410.21.20 | Q11: Com espessura superior a 0,012 mm, sobre suporte de poliéster ou poliimida e com espessura total, incluindo o suporte, inferior ou igual a 0,195 mm | R11: BIT | T11: 4011.20.90 | U11: Pneus | X11: SC | Y11: 0.07 | Z11: 0.0878 | AB11: 0.758 | AC11: materiais de limpeza
A12: 1708702 | B12: 0.4552 | C12: 0102.31.10 | D12: Não Encontrado | E12: Não Encontrado | G12: 108700 | H12: 0.6529 | I12: AUTO PEÇAS | K12: 8405.10.00 | L12: ANEXO I | M12: 8419.89.99 | N12: ANEXO II | P12: 7410.21.30 | Q12: Com suporte isolante de resina fenólica e papel, do tipo utilizado para circuitos impressos | R12: BIT | T12: 4011.30.00 | U12: Pneus | X12: SP | Y12: 0.07 | Z12: 0.0878 | AB12: 0.6328 | AC12: materiais elétricos
A13: 1708700 | B13: 0.4552 | C13: 0102.31.90 | D13: Não Encontrado | E13: Não Encontrado | G13: 100600 | H13: 0.6529 | I13: AUTO PEÇAS | K13: 8406.10.00 | L13: ANEXO I | M13: 8479.89.40 | N13: ANEXO II | P13: 8409.91.40 | Q13: Sistema de injeção eletrônica | R13: BIT | T13: 4011.40.00 | U13: Pneus | X13: AC | Y13: 0.12 | Z13: 0.093 | AB13: 0.6035 | AC13: medicamentos de uso humano e outros produtos farmacêuticos para uso humano ou veterinário
A14: 1708701 | B14: 0.4552 | C14: 0102.39.11 | D14: Não Encontrado | E14: Não Encontrado | G14: 100800 | H14: 0.6529 | I14: AUTO PEÇAS | K14: 8406.81.00 | L14: ANEXO I | M14: 9406.00.91 | N14: ANEXO II | P14: 8443.31.11 | Q14: De jato de tinta líquida, com largura de impressão inferior ou igual a 420 mm | R14: BIT | T14: 4011.50.00 | U14: Pneus | X14: AL | Y14: 0.12 | Z14: 0.093 | AB14: 0.6652 | AC14: papéis, plásticos, produtos cerâmicos e vidros
A15: 1708701 | B15: 0.4552 | C15: 0102.39.19 | D15: Não Encontrado | E15: Não Encontrado | G15: 100700 | H15: 0.6529 | I15: AUTO PEÇAS | K15: 8406.82.00 | L15: ANEXO I | M15: 9406.00.92 | N15: ANEXO II | P15: 8443.31.12 | Q15: De transferência térmica de cera sólida (por exemplo, solid ink e dye sublimation) | R15: BIT | T15: 4011.70.10 | U15: Pneus | X15: AM | Y15: 0.12 | Z15: 0.093 | AB15: 0.7879 | AC15: pneumáticos, câmaras de ar e protetores de borracha
A16: 1708300 | B16: 0.4552 | C16: 0102.39.90 | D16: Não Encontrado | E16: Não Encontrado | G16: 100900 | H16: 0.6529 | I16: AUTO PEÇAS | K16: 8410.11.00 | L16: ANEXO I | M16: 4421.90.00 | N16: ANEXO II | P16: 8443.31.13 | Q16: A laser, LED (Diodos Emissores de Luz) ou LCS (Sistema de Cristal Líquido), monocromáticas, com largura de impressão inferior ou igual a 280 mm | R16: BIT | T16: 4011.70.90 | U16: Pneus | X16: AP | Y16: 0.12 | Z16: 0.093 | AB16: 0.5975 | AC16: produtos alimentícios
A17: 1708301 | B17: 0.4552 | C17: 0102.90.00 | D17: Não Encontrado | E17: Não Encontrado | G17: 108800 | H17: 0.6529 | I17: AUTO PEÇAS | K17: 8410.12.00 | L17: ANEXO I | M17: 7326.90.90 | N17: ANEXO II | P17: 8443.31.14 | Q17: A laser, LED (Diodos Emissores de Luz) ou LCS (Sistema de Cristal Líquido), monocromáticas, com largura de impressão superior a 280 mm, mas não superior a 420 mm | R17: BIT | T17: 4011.80.10 | U17: Pneus | X17: BA | Y17: 0.12 | Z17: 0.093 | AB17: 0.739 | AC17: produtos de papelaria
A18: 1708300 | B18: 0.4552 | C18: 0103.10.00 | D18: Não Encontrado | E18: Não Encontrado | G18: 108900 | H18: 0.6529 | I18: AUTO PEÇAS | K18: 8410.13.00 | L18: ANEXO I | M18: 7326.90.90 | N18: ANEXO II | P18: 8443.31.15 | Q18: A laser, LED (Diodos Emissores de Luz) ou LCS (Sistema de Cristal Líquido), policromáticas | R18: BIT | T18: 4011.80.20 | U18: Pneus | X18: CE | Y18: 0.12 | Z18: 0.093 | AB18: 0.758 | AC18: produtos de perfumaria e de higiene pessoal e cosméticos
A19: 1708600 | B19: 0.4552 | C19: 0103.91.00 | D19: Não Encontrado | E19: Não Encontrado | G19: 100700 | H19: 0.6529 | I19: AUTO PEÇAS | K19: 8410.90.00 | L19: ANEXO I | M19: 8708.70.90 | N19: ANEXO II | P19: 8443.31.16 | Q19: Outras, com largura de impressão superior a 420 mm | R19: BIT | T19: 4011.80.90 | U19: Pneus | X19: DF | Y19: 0.12 | Z19: 0.093 | AB19: 0.5386 | AC19: produtos eletrônicos, eletroeletrônicos e eletrodomésticos
A20: 1708700 | B20: 0.4552 | C20: 0103.92.00 | D20: Não Encontrado | E20: Não Encontrado | G20: 110400 | H20: 0.6529 | I20: AUTO PEÇAS | K20: 8412.80.00 | L20: ANEXO I | M20: 8201.10.00 | N20: ANEXO II | P20: 8443.31.19 | Q20: Outras | R20: BIT | T20: 4011.90.10 | U20: Pneus | X20: ES | Y20: 0.12 | Z20: 0.093 | AB20: 0.6857 | AC20: rações para animais domésticos
... A23: 1701600 | B23: 0.4552 | C23: 0104.10.90 | D23: Não Encontrado | E23: Não Encontrado | G23: 100900 | H23: 0.6529 | I23: AUTO PEÇAS | K23: 8413.70.90 | L23: ANEXO I | M23: 8201.40.00 | N23: ANEXO II | P23: 8443.32.21 | Q23: De linha | R23: BIT | T23: 4013.10.90 | U23: Pneus | X23: MS | Y23: 0.12 | Z23: 0.093 | AB23: 0.947 | AC23: cigarros e outros produtos derivados do fumo
A24: 1701601 | B24: 0.4552 | C24: 0104.20.10 | D24: Não Encontrado | E24: Não Encontrado | G24: 101000 | H24: 0.6529 | I24: AUTO PEÇAS | K24: 8414.80.12 | L24: ANEXO I | M24: 8201.50.00 | N24: ANEXO II | P24: 8443.32.22 | Q24: De caracteres Braille | R24: BIT | T24: 4013.20.00 | U24: Pneus | X24: PA | Y24: 0.12 | Z24: 0.093
A25: 1701800 | B25: 0.4552 | C25: 0104.20.90 | D25: Não Encontrado | E25: Não Encontrado | G25: 101100 | H25: 0.6529 | I25: AUTO PEÇAS | K25: 8414.80.13 | L25: ANEXO I | M25: 8201.60.00 | N25: ANEXO II | P25: 8443.32.23 | Q25: Outras matriciais (por pontos) | R25: BIT | T25: 4013.90.00 | U25: Pneus | X25: PB | Y25: 0.12 | Z25: 0.093
A26: 1701801 | B26: 0.4552 | C26: 0105.11.10 | D26: Não Encontrado | E26: Não Encontrado | G26: 100600 | H26: 0.6529 | I26: AUTO PEÇAS | K26: 8414.80.19 | L26: ANEXO I | M26: 8201.90.00 | N26: ANEXO II | P26: 8443.32.29 | Q26: Outras | R26: BIT | X26: PE | Y26: 0.12 | Z26: 0.093
A27: 1701902 | B27: 0.4552 | C27: 0105.11.90 | D27: Não Encontrado | E27: Não Encontrado | G27: 110700 | H27: 0.6529 | I27: AUTO PEÇAS | K27: 8414.80.31 | L27: ANEXO I | M27: 8412.80.00 | N27: ANEXO II | P27: 8443.32.31 | Q27: De jato de tinta líquida, com largura de impressão inferior ou igual a 420 mm | R27: BIT | X27: PI | Y27: 0.12 | Z27: 0.093 | AC27: 6922 | AD27: 2922
A28: 1701600 | B28: 0.4552 | C28: 0105.12.00 | D28: Não Encontrado | E28: Não Encontrado | G28: 101200 | H28: 0.6529 | I28: AUTO PEÇAS | K28: 8414.80.32 | L28: ANEXO I | M28: 8414.59.90 | N28: ANEXO II | P28: 8443.32.32 | Q28: De transferência térmica de cera sólida (por exemplo, solid ink e dye sublimation) | R28: BIT | X28: RN | Y28: 0.12 | Z28: 0.093 | AC28: 6915 | AD28: 2915
A29: 1701601 | B29: 0.4552 | C29: 0105.13.00 | D29: Não Encontrado | E29: Não Encontrado | G29: 101300 | H29: 0.6529 | I29: AUTO PEÇAS | K29: 8414.80.33 | L29: ANEXO I | M29: 8414.80.11 | N29: ANEXO II | P29: 8443.32.33 | Q29: A laser, LED (Diodos Emissores de Luz) ou LCS (Sistema de Cristal Líquido), monocromáticas, com largura de impressão inferior ou igual a 280 mm | R29: BIT | X29: RO | Y29: 0.12 | Z29: 0.093 | AC29: 6916 | AD29: 2916
A30: 1701800 | B30: 0.4552 | C30: 0105.14.00 | D30: Não Encontrado | E30: Não Encontrado | G30: 108800 | H30: 0.6529 | I30: AUTO PEÇAS | K30: 8414.80.38 | L30: ANEXO I | M30: 8414.80.19 | N30: ANEXO II | P30: 8443.32.34 | Q30: A laser, LED (Diodos Emissores de Luz) ou LCS (Sistema de Cristal Líquido), monocromáticas, com largura de impressão superior a 280 mm, mas não superior a 420 mm | R30: BIT | X30: RR | Y30: 0.12 | Z30: 0.093 | AC30: 6949 | AD30: 2949
A31: 1701801 | B31: 0.4552 | C31: 0105.15.00 | D31: Não Encontrado | E31: Não Encontrado | G31: 101400 | H31: 0.6529 | I31: AUTO PEÇAS | K31: 8414.80.39 | L31: ANEXO I | M31: 8414.80.90 | N31: ANEXO II | P31: 8443.32.35 | Q31: A laser, LED (Diodos Emissores de Luz) ou LCS (Sistema de Cristal Líquido), policromáticas, com velocidade de impressão inferior ou igual a 20 páginas por minuto (ppm) | R31: BIT | X31: SE | Y31: 0.12 | Z31: 0.093 | AC31: 6910 | AD31: 2910
A32: 1701700 | B32: 0.4552 | C32: 0105.94.00 | D32: Não Encontrado | E32: Não Encontrado | G32: 110800 | H32: 0.6529 | I32: AUTO PEÇAS | K32: 8416.10.00 | L32: ANEXO I | M32: 8419.31.00 | N32: ANEXO II | P32: 8443.32.36 | Q32: A laser, LED (Diodos Emissores de Luz) ou LCS (Sistema de Cristal Líquido), policromáticas, com velocidade de impressão superior a 20 páginas por minuto (ppm) | R32: BIT | X32: TO | Y32: 0.12 | Z32: 0.093 | AC32: 6911 | AD32: 2911
A33: 1701701 | B33: 0.4552 | C33: 0105.99.00 | D33: Não Encontrado | E33: Não Encontrado | G33: 101500 | H33: 0.6529 | I33: AUTO PEÇAS | K33: 8416.20.10 | L33: ANEXO I | M33: 8423.82.00 | N33: ANEXO II | P33: 8443.32.37 | Q33: Térmicas, do tipo utilizado em impressão de imagens para diagnóstico médico em folhas revestidas com camada termossensível | R33: BIT | X33: MT | Y33: 0.12 | Z33: 0.093 | AC33: 6920 | AD33: 2920
A34: 1701900 | B34: 0.4552 | C34: 0106.11.00 | D34: Não Encontrado | E34: Não Encontrado | G34: 101500 | H34: 0.6529 | I34: AUTO PEÇAS | K34: 8416.20.90 | L34: ANEXO I | M34: 8424.41.00 | N34: ANEXO II | P34: 8443.32.38 | Q34: Outras, com largura de impressão superior a 420 mm | R34: BIT | AC34: 6921 | AD34: 2921
A35: 1701901 | B35: 0.4552 | C35: 0106.12.00 | D35: Não Encontrado | E35: Não Encontrado | G35: 110900 | H35: 0.6529 | I35: AUTO PEÇAS | K35: 8416.30.00 | L35: ANEXO I | M35: 8424.49.00 | N35: ANEXO II | P35: 8443.32.39 | Q35: Outras | R35: BIT | AC35: 2201 | AD35: Dev Terceiro
A36: 1701902 | B36: 0.4552 | C36: 0106.13.00 | D36: Não Encontrado | E36: Não Encontrado | G36: 101600 | H36: 0.6529 | I36: AUTO PEÇAS | K36: 8416.90.00 | L36: ANEXO I | M36: 8424.82.21 | N36: ANEXO II | P36: 8443.32.40 | Q36: Outras impressoras alimentadas por folhas | R36: BIT | X36: LISTA DIFAL CONVENIO 52/91 ANEXO I | AC36: 2202 | AD36: Dev Terceiro
A37: 1701700 | B37: 0.4552 | C37: 0106.14.00 | D37: Não Encontrado | E37: Não Encontrado | G37: 101700 | H37: 0.6529 | I37: AUTO PEÇAS | K37: 8417.10.10 | L37: ANEXO I | M37: 8424.82.29 | N37: ANEXO II | P37: 8443.32.51 | Q37: Por meio de penas | R37: BIT | X37: ESTADO | Y37: ALIQUOTA | AC37: 2203 | AD37: Dev Terceiro
A38: 1701701 | B38: 0.4552 | C38: 0106.19.00 | D38: Não Encontrado | E38: Não Encontrado | G38: 101800 | H38: 0.6529 | I38: AUTO PEÇAS | K38: 8417.10.20 | L38: ANEXO I | M38: 8427.20.90 | N38: ANEXO II | P38: 8443.32.52 | Q38: Outros, com largura de impressão superior a 580 mm | R38: BIT | X38: MG | Y38: 0.0366 | AC38: 2204 | AD38: Dev Terceiro
A39: 1701200 | B39: 0.4552 | C39: 0106.20.00 | D39: Não Encontrado | E39: Não Encontrado | G39: 101900 | H39: 0.6529 | I39: AUTO PEÇAS | K39: 8417.10.90 | L39: ANEXO I | M39: 8427.90.00 | N39: ANEXO II | P39: 8443.32.59 | Q39: Outros | R39: BIT | X39: PR | Y39: 0.0366 | AC39: 2205 | AD39: Dev Terceiro
A40: 1701902 | B40: 0.4552 | C40: 0106.31.00 | D40: Não Encontrado | E40: Não Encontrado | G40: 111100 | H40: 0.6529 | I40: AUTO PEÇAS | K40: 8417.20.00 | L40: ANEXO I | M40: 8430.69.90 | N40: ANEXO II | P40: 8443.32.91 | Q40: Impressoras de código de barras postais, tipo 3 em 5, a jato de tinta fluorescente, com velocidade de até 4,5 m/s e passo de 1,4 mm | R40: BIT | X40: RS | Y40: 0.0366 | AC40: 2206 | AD40: Dev Terceiro
A41: 1701200 | B41: 0.4552 | C41: 0106.32.00 | D41: Não Encontrado | E41: Não Encontrado | G41: 111200 | H41: 0.6529 | I41: AUTO PEÇAS | K41: 8417.80.10 | L41: ANEXO I | M41: 8432.10.00 | N41: ANEXO II | P41: 8443.32.99 | Q41: Outras | R41: BIT | X41: RJ | Y41: 0.0366 | AC41: 2207 | AD41: Dev Terceiro
A42: 1701900 | B42: 0.4552 | C42: 0106.33.10 | D42: Não Encontrado | E42: Não Encontrado | G42: 102000 | H42: 0.6529 | I42: AUTO PEÇAS | K42: 84178020 | L42: ANEXO I | M42: 8432.29.00 | N42: ANEXO II | P42: 8443.99.11 | Q42: Mecanismos de impressão, mesmo sem cabeça de impressão incorporada | R42: BIT | X42: SC | Y42: 0.0366 | AC42: 2208 | AD42: Dev Terceiro
A43: 1701901 | B43: 0.4552 | C43: 0106.33.90 | D43: Não Encontrado | E43: Não Encontrado | G43: 112800 | H43: 0.6529 | I43: AUTO PEÇAS | K43: 8417.80.90 | L43: ANEXO I | M43: 8432.31.10 | N43: ANEXO II | P43: 8443.99.12 | Q43: Cabeças de impressão | R43: BIT | X43: SP | Y43: 0.0366 | AC43: 2209 | AD43: Dev Terceiro
A44: 1701902 | B44: 0.4552 | C44: 0106.39.00 | D44: Não Encontrado | E44: Não Encontrado | G44: 102100 | H44: 0.6529 | I44: AUTO PEÇAS | K44: 8418.69.10 | L44: ANEXO I | M44: 8432.39.10 | N44: ANEXO II | P44: 8443.99.19 | Q44: Outros | R44: BIT | X44: AC | Y44: 0
A45: 1701900 | B45: 0.4552 | C45: 0106.41.00 | D45: Não Encontrado | E45: Não Encontrado | G45: 102200 | H45: 0.6529 | I45: AUTO PEÇAS | K45: 8418.69.99 | L45: ANEXO I | M45: 8432.31.90 | N45: ANEXO II | P45: 8443.99.21 | Q45: Mecanismos de impressão, mesmo sem cabeça de impressão incorporada | R45: BIT | X45: AL | Y45: 0
A46: 1701901 | B46: 0.4552 | C46: 0106.49.00 | D46: Não Encontrado | E46: Não Encontrado | G46: 102300 | H46: 0.6529 | I46: AUTO PEÇAS | K46: 8418.69.20 | L46: ANEXO I | M46: 8432.41.00 | N46: ANEXO II | P46: 8443.99.22 | Q46: Cabeças de impressão | R46: BIT | X46: AM | Y46: 0
A47: 1701200 | B47: 0.4552 | C47: 0106.90.00 | D47: Não Encontrado | E47: Não Encontrado | G47: 102400 | H47: 0.6529 | I47: AUTO PEÇAS | K47: 8419.32.00 | L47: ANEXO I | M47: 8432.42.00 | N47: ANEXO II | P47: 8443.99.23 | Q47: Cartuchos de tinta | R47: BIT | X47: AP | Y47: 0
A48: 1701900 | B48: 0.4552 | C48: 0201.10.00 | D48: Não Encontrado | E48: Não Encontrado | G48: 102400 | H48: 0.6529 | I48: AUTO PEÇAS | K48: 8419.39.00 | L48: ANEXO I | M48: 8432.80.00 | N48: ANEXO II | P48: 8443.99.29 | Q48: Outros | R48: BIT | X48: BA | Y48: 0
A49: 1701901 | B49: 0.4552 | C49: 0201.20.10 | D49: Não Encontrado | E49: Não Encontrado | G49: 102500 | H49: 0.6529 | I49: AUTO PEÇAS | K49: 8419.40.10 | L49: ANEXO I | M49: 8432.90.00 | N49: ANEXO II | P49: 8443.99.31 | Q49: Mecanismos de impressão, mesmo sem cilindro fotossensível incorporado | R49: BIT | X49: CE | Y49: 0
A50: 1702000 | B50: 0.4552 | C50: 0201.20.20 | D50: Não Encontrado | E50: Não Encontrado | G50: 102600 | H50: 0.6529 | I50: AUTO PEÇAS | K50: 8419.40.20 | L50: ANEXO I | M50: 8432.21.00 | N50: ANEXO II | P50: 8443.99.32 | Q50: Cilindros recobertos de matéria semicondutora fotoelétrica | R50: BIT | X50: DF | Y50: 0
A51: 1702001 | B51: 0.4552 | C51: 0201.20.90 | D51: Não Encontrado | E51: Não Encontrado | G51: 102600 | H51: 0.6529 | I51: AUTO PEÇAS | K51: 8419.40.90 | L51: ANEXO I | M51: 8433.11.00 | N51: ANEXO II | P51: 8443.99.33 | Q51: Cartuchos de revelador (toners) | R51: BIT | X51: ES | Y51: 0
A52: 1702100 | B52: 0.4552 | C52: 0201.30.00 | D52: Não Encontrado | E52: Não Encontrado | G52: 102700 | H52: 0.6529 | I52: AUTO PEÇAS | K52: 8419.50.10 | L52: ANEXO I | M52: 8433.19.00 | N52: ANEXO II | P52: 8443.99.39 | Q52: Outros | R52: BIT | X52: GO | Y52: 0
A53: 1702101 | B53: 0.4552 | C53: 0202.10.00 | D53: Não Encontrado | E53: Não Encontrado | G53: 102800 | H53: 0.6529 | I53: AUTO PEÇAS | K53: 8419.50.21 | L53: ANEXO I | M53: 8433.20.10 | N53: ANEXO II | P53: 8443.99.41 | Q53: Mecanismos de impressão, mesmo sem cabeça de impressão incorporada | R53: BIT | X53: MA | Y53: 0
A54: 1702200 | B54: 0.4552 | C54: 0202.20.10 | D54: Não Encontrado | E54: Não Encontrado | G54: 102900 | H54: 0.6529 | I54: AUTO PEÇAS | K54: 8419.50.22 | L54: ANEXO I | M54: 8433.20.90 | N54: ANEXO II | P54: 8443.99.42 | Q54: Cabeças de impressão | R54: BIT | X54: MS | Y54: 0
A55: 1702500 | B55: 0.4552 | C55: 0202.20.20 | D55: Não Encontrado | E55: Não Encontrado | G55: 103000 | H55: 0.6529 | I55: AUTO PEÇAS | K55: 8419.50.29 | L55: ANEXO I | M55: 8433.30.00 | N55: ANEXO II | P55: 8443.99.49 | Q55: Outros | R55: BIT | X55: PA | Y55: 0
... A64: 1702404 | B64: 0.4552 | C64: 0204.10.00 | D64: Não Encontrado | E64: Não Encontrado | G64: 103500 | H64: 0.6529 | I64: AUTO PEÇAS | K64: 8419.89.40 | L64: ANEXO I | M64: 8433.60.21 | N64: ANEXO II | P64: 8471.30.19 | Q64: Outras | R64: BIT | X64: MT | Y64: 0
A65: 1708800 | B65: 0.4552 | C65: 0204.21.00 | D65: Não Encontrado | E65: Não Encontrado | G65: 103300 | H65: 0.6529 | I65: AUTO PEÇAS | K65: 8419.89.99 | L65: ANEXO I | M65: 8433.60.29 | N65: ANEXO II | P65: 8471.30.90 | Q65: Outras | R65: BIT
A66: 1708801 | B66: 0.4552 | C66: 0204.22.00 | D66: Não Encontrado | E66: Não Encontrado | G66: 109400 | H66: 0.6529 | I66: AUTO PEÇAS | K66: 8420.10.10 | L66: ANEXO I | M66: 8433.60.90 | N66: ANEXO II | P66: 8471.41.00 | Q66: -- Que contenham, no mesmo corpo, pelo menos uma unidade central de processamento e, mesmo combinadas, uma unidade de entrada e uma unidade de saída | R66: BIT | X66: LISTA DIFAL CONVENIO 52/91 ANEXO II
A67: 1708900 | B67: 0.4552 | C67: 0204.23.00 | D67: Não Encontrado | E67: Não Encontrado | G67: 109400 | H67: 0.6529 | I67: AUTO PEÇAS | K67: 8420.10.90 | L67: ANEXO I | M67: 8433.90.90 | N67: ANEXO II | P67: 8471.49.00 | Q67: -- Outras, apresentadas sob a forma de sistemas | R67: BIT | X67: ESTADO | Y67: ALIQUOTA
A68: 1708901 | B68: 0.4552 | C68: 0204.30.00 | D68: Não Encontrado | E68: Não Encontrado | G68: 103400 | H68: 0.6529 | I68: AUTO PEÇAS | K68: 8420.91.00 | L68: ANEXO I | M68: 8467.89.00 | N68: ANEXO II | P68: 8471.50.10 | R68: BIT | X68: MG | Y68: 0.015
A69: 1709600 | B69: 0.4552 | C69: 0204.41.00 | D69: Não Encontrado | E69: Não Encontrado | G69: 103400 | H69: 0.6529 | I69: AUTO PEÇAS | K69: 8421.11.10 | L69: ANEXO I | M69: 8467.89.00 | N69: ANEXO II | P69: 8471.50.20 | R69: BIT | X69: PR | Y69: 0.015
A70: 1709601 | B70: 0.4552 | C70: 0204.42.00 | D70: Não Encontrado | E70: Não Encontrado | G70: 103500 | H70: 0.6529 | I70: AUTO PEÇAS | K70: 8421.11.90 | L70: ANEXO I | M70: 8434.10.00 | N70: ANEXO II | P70: 8471.50.30 | R70: BIT | X70: RS | Y70: 0.015
A71: 1709602 | B71: 0.4552 | C71: 0204.43.00 | D71: Não Encontrado | E71: Não Encontrado | G71: 103500 | H71: 0.6529 | I71: AUTO PEÇAS | K71: 8421.12.90 | L71: ANEXO I | M71: 8436.10.00 | N71: ANEXO II | P71: 8471.50.40 | R71: BIT | X71: RJ | Y71: 0.015
A72: 1709603 | B72: 0.4552 | C72: 0204.50.00 | D72: Não Encontrado | E72: Não Encontrado | G72: 103500 | H72: 0.6529 | I72: AUTO PEÇAS | K72: 8421.19.10 | L72: ANEXO I | M72: 8436.21.00 | N72: ANEXO II | P72: 8471.50.90 | Q72: Outras | R72: BIT | X72: SC | Y72: 0.015
A73: 1709604 | B73: 0.4552 | C73: 0205.00.00 | D73: Não Encontrado | E73: Não Encontrado | G73: 103600 | H73: 0.6529 | I73: AUTO PEÇAS | K73: 8421.19.90 | L73: ANEXO I | M73: 8436.29.00 | N73: ANEXO II | P73: 8471.60.52 | Q73: Teclados | R73: BIT | X73: SP | Y73: 0.015
A74: 1709605 | B74: 0.4552 | C74: 0206.10.00 | D74: Não Encontrado | E74: Não Encontrado | G74: 111300 | H74: 0.6529 | I74: AUTO PEÇAS | K74: 8421.39.90 | L74: ANEXO I | M74: 8436.80.00 | N74: ANEXO II | P74: 8471.60.53 | Q74: Indicadores ou apontadores (mouse e track-ball, por exemplo) | R74: BIT | X74: AC | Y74: 0
A75: 1709700 | B75: 0.4552 | C75: 0206.21.00 | D75: Não Encontrado | E75: Não Encontrado | G75: 111400 | H75: 0.6529 | I75: AUTO PEÇAS | K75: 8422.20.00 | L75: ANEXO I | M75: 8436.91.00 | N75: ANEXO II | P75: 8471.60.54 | Q75: Mesas digitalizadoras | R75: BIT | X75: AL | Y75: 0
A76: 1709800 | B76: 0.4552 | C76: 0206.22.00 | D76: Não Encontrado | E76: Não Encontrado | G76: 103700 | H76: 0.6529 | I76: AUTO PEÇAS | K76: 8422.30.10 | L76: ANEXO I | M76: 8436.99.00 | N76: ANEXO II | P76: 8471.60.59 | Q76: Outras | R76: BIT | X76: AM | Y76: 0
A77: 1704400 | B77: 0.4552 | C77: 0206.29.10 | D77: Não Encontrado | E77: Não Encontrado | G77: 103800 | H77: 0.6529 | I77: AUTO PEÇAS | K77: 8422.30.21 | L77: ANEXO I | M77: 8467.81.00 | N77: ANEXO II | P77: 8471.60.61 | Q77: Com unidade de saída por vídeo monocromático | R77: BIT | X77: AP | Y77: 0
A78: 1704401 | B78: 0.4552 | C78: 0206.29.90 | D78: Não Encontrado | E78: Não Encontrado | G78: 104100 | H78: 0.6529 | I78: AUTO PEÇAS | K78: 8422.30.22 | L78: ANEXO I | M78: 8526.91.00 | N78: ANEXO II | P78: 8471.60.62 | Q78: Com unidade de saída por vídeo policromático | R78: BIT | X78: BA | Y78: 0
A79: 1704402 | B79: 0.4552 | C79: 0206.30.00 | D79: Não Encontrado | E79: Não Encontrado | G79: 104200 | H79: 0.6529 | I79: AUTO PEÇAS | K79: 8422.30.23 | L79: ANEXO I | M79: 8701.10.00 | N79: ANEXO II | P79: 8471.60.80 | Q79: Terminais de auto-atendimento bancário | R79: BIT | X79: CE | Y79: 0
A80: 1704403 | B80: 0.4552 | C80: 0206.41.00 | D80: Não Encontrado | E80: Não Encontrado | G80: 109500 | H80: 0.6529 | I80: AUTO PEÇAS | K80: 8422.30.29 | L80: ANEXO I | M80: 8701.91.00 | N80: ANEXO II | P80: 8471.60.90 | Q80: Outras | R80: BIT | X80: DF | Y80: 0
A81: 1704404 | B81: 0.4552 | C81: 0206.49.00 | D81: Não Encontrado | E81: Não Encontrado | G81: 103900 | H81: 0.6529 | I81: AUTO PEÇAS | K81: 8422.40.10 | L81: ANEXO I | M81: 8701.92.00 | N81: ANEXO II | P81: 8471.70.10 | Q81: De discos magnéticos | R81: BIT | X81: ES | Y81: 0
A82: 1704405 | B82: 0.4552 | C82: 0206.80.00 | D82: Não Encontrado | E82: Não Encontrado | G82: 104000 | H82: 0.6529 | I82: AUTO PEÇAS | K82: 8422.40.20 | L82: ANEXO I | M82: 8701.93.00 | N82: ANEXO II | P82: 8471.70.20 | Q82: De discos para leitura ou gravação de dados por meios ópticos (unidade de disco óptico) | R82: BIT | X82: GO | Y82: 0
A83: 1704406 | B83: 0.4552 | C83: 0206.90.00 | D83: Não Encontrado | E83: Não Encontrado | G83: 111500 | H83: 0.6529 | I83: AUTO PEÇAS | K83: 8422.40.30 | L83: ANEXO I | M83: 8701.94.90 | N83: ANEXO II | P83: 8471.70.30 | Q83: De fitas magnéticas | R83: BIT | X83: MA | Y83: 0
A84: 1704407 | B84: 0.4552 | C84: 0207.11.00 | D84: Não Encontrado | E84: 0.4552 | G84: 104300 | H84: 0.6529 | I84: AUTO PEÇAS | K84: 8422.40.90 | L84: ANEXO I | M84: 8701.95.90 | N84: ANEXO II | P84: 8471.70.40 | Q84: De estado sólido (SSD - Solid-State Drive) | R84: BIT | X84: MS | Y84: 0
A85: 1704408 | B85: 0.4552 | C85: 0207.12.00 | D85: Não Encontrado | E85: 0.4552 | G85: 111600 | H85: 0.6529 | I85: AUTO PEÇAS | K85: 8423.20.00 | L85: ANEXO I | M85: 8413.81.00 | N85: ANEXO II | P85: 8471.70.90 | Q85: Outras, incluídas as combinações de unidades de, pelo menos, dois dos itens precedentes | R85: BIT | X85: PA | Y85: 0
A86: 1704409 | B86: 0.4552 | C86: 0207.12.10 | D86: Não Encontrado | E86: 0.4552 | G86: 104400 | H86: 0.6529 | I86: AUTO PEÇAS | K86: 8423.30.11 | L86: ANEXO I | M86: 8716.20.00 | N86: ANEXO II | P86: 8471.80.00 | Q86: - Outras unidades de máquinas automáticas para processamento de dados | R86: BIT | X86: PB | Y86: 0
A87: 1704410 | B87: 0.4552 | C87: 0207.12.20 | D87: Não Encontrado | E87: 0.4552 | G87: 111700 | H87: 0.6529 | I87: AUTO PEÇAS | K87: 8423.30.19 | L87: ANEXO I | M87: 8716.80.00 | N87: ANEXO II | P87: 8471.90.11 | Q87: De cartões magnéticos | R87: BIT | X87: PE | Y87: 0
A88: 1704411 | B88: 0.4552 | C88: 0207.13.00 | D88: Não Encontrado | E88: 0.4552 | G88: 104500 | H88: 0.6529 | I88: AUTO PEÇAS | K88: 8423.30.90 | L88: ANEXO I | M88: 8802.20.10 | N88: ANEXO II | P88: 8471.90.12 | Q88: Leitores de códigos de barras | R88: BIT | X88: PI | Y88: 0
A89: 1704412 | B89: 0.4552 | C89: 0207.14.00 | D89: Não Encontrado | E89: 0.4552 | G89: 104501 | H89: 0.6529 | I89: AUTO PEÇAS | K89: 8423.81.10 | L89: ANEXO I | M89: 8802.30.10 | N89: ANEXO II | P89: 8471.90.13 | Q89: Leitores de caracteres magnetizáveis | R89: BIT | X89: RN | Y89: 0
A90: 1704413 | B90: 0.4552 | C90: 0207.24.00 | D90: Não Encontrado | E90: 0.4552 | G90: 104600 | H90: 0.6529 | I90: AUTO PEÇAS | K90: 8423.81.90 | L90: ANEXO I | M90: 8803.10.00 | N90: ANEXO II | P90: 8471.90.14 | Q90: Digitalizadores de imagens (scanners) | R90: BIT | X90: RO | Y90: 0
A91: 1704414 | B91: 0.4552 | C91: 0207.25.00 | D91: Não Encontrado | E91: 0.4552 | G91: 104700 | H91: 0.6529 | I91: AUTO PEÇAS | K91: 8423.81.90 | L91: ANEXO I | M91: 8803.20.00 | N91: ANEXO II | P91: 8471.90.19 | Q91: Outros | R91: BIT | X91: RR | Y91: 0
A92: 1704415 | B92: 0.4552 | C92: 0207.26.00 | D92: Não Encontrado | E92: 0.4552 | G92: 104800 | H92: 0.6529 | I92: AUTO PEÇAS | K92: 8423.82.00 | L92: ANEXO I | M92: 8803.30.00 | N92: ANEXO II | P92: 8471.90.90 | Q92: Outros | R92: BIT | X92: SE | Y92: 0
A93: 1704416 | B93: 0.4552 | C93: 0207.27.00 | D93: Não Encontrado | E93: 0.4552 | G93: 104900 | H93: 0.6529 | I93: AUTO PEÇAS | K93: 8423.89.00 | L93: ANEXO I | M93: 8803.90.00 | N93: ANEXO II | P93: 8472.30.10 | Q93: Máquinas automáticas para obliterar selos postais | R93: BIT | X93: TO | Y93: 0
A94: 1704417 | B94: 0.4552 | C94: 0207.41.00 | D94: Não Encontrado | E94: Não Encontrado | G94: 105000 | H94: 0.6529 | I94: AUTO PEÇAS | K94: 8423.82.00 | L94: ANEXO I | M94: 9027.80.14 | N94: ANEXO II | P94: 8472.30.20 | Q94: Máquinas automáticas para seleção de correspondência por formato e classificação e distribuição da mesma por leitura óptica do código postal | R94: BIT | X94: MT | Y94: 0
A95: 1704418 | B95: 0.4552 | C95: 0207.42.00 | D95: Não Encontrado | E95: Não Encontrado | G95: 105100 | H95: 0.6529 | I95: AUTO PEÇAS | K95: 8424.20.00 | L95: ANEXO I | M95: 9406.00.10 | N95: ANEXO II | P95: 8472.30.30 | Q95: Máquinas automáticas para seleção e distribuição de encomendas, por leitura óptica do código postal | R95: BIT
A96: 1704419 | B96: 0.4552 | C96: 0207.43.00 | D96: Não Encontrado | E96: Não Encontrado | G96: 109600 | H96: 0.6529 | I96: AUTO PEÇAS | K96: 8424.30.10 | L96: ANEXO I | P96: 8472.90.10 | Q96: Distribuidores (dispensadores) automáticos de notas (papéis-moeda), incluindo os que efetuam outras operações bancárias | R96: BIT
A97: 1704420 | B97: 0.4552 | C97: 0207.44.00 | D97: Não Encontrado | E97: Não Encontrado | G97: 109700 | H97: 0.6529 | I97: AUTO PEÇAS | K97: 8424.30.20 | L97: ANEXO I | P97: 8472.90.20 | Q97: Máquinas do tipo utilizado em caixas de banco, com dispositivo para autenticar | R97: BIT | X97: Simples Nacional
A98: 1704421 | B98: 0.4552 | C98: 0207.45.00 | D98: Não Encontrado | E98: Não Encontrado | G98: 111800 | H98: 0.6529 | I98: AUTO PEÇAS | K98: 8424.30.30 | L98: ANEXO I | P98: 8472.90.51 | Q98: Com capacidade de classificação superior a 400 documentos por minuto | R98: BIT | X98: 1 | Y98: 0.04
A99: 1704422 | B99: 0.4552 | C99: 0207.51.00 | D99: Não Encontrado | E99: Não Encontrado | G99: 109800 | H99: 0.6529 | I99: AUTO PEÇAS | K99: 8424.30.90 | L99: ANEXO I | P99: 8472.90.59 | Q99: Outras | R99: BIT | X99: 2 | Y99: 0.04
A100: 1704423 | B100: 0.4552 | C100: 0207.52.00 | D100: Não Encontrado | E100: Não Encontrado | G100: 105200 | H100: 0.6529 | I100: AUTO PEÇAS | K100: 8424.89.90 | L100: ANEXO I | P100: 8473.29.10 | Q100: Circuitos impressos com componentes elétricos ou eletrônicos, montados, para caixas registradoras | R100: BIT | X100: 3 | Y100: 0.04
A101: 1704424 | B101: 0.4552 | C101: 0207.53.00 | D101: Não Encontrado | E101: Não Encontrado | G101: 105300 | H101: 0.6529 | I101: AUTO PEÇAS | K101: 8425.11.00 | L101: ANEXO I | P101: 8473.29.90 | Q101: Outros | R101: BIT | X101: 8 | Y101: 0.04
A102: 1704425 | B102: 0.4552 | C102: 0207.54.00 | D102: Não Encontrado | E102: Não Encontrado | G102: 105301 | H102: 0.6529 | I102: AUTO PEÇAS | K102: 8425.19.10 | L102: ANEXO I | P102: 8473.30.11 | Q102: Com fonte de alimentação, mesmo com módulo display numérico | R102: BIT | X102: 4 | Y102: 0.07
A103: 1704426 | B103: 0.4552 | C103: 0207.55.00 | D103: Não Encontrado | E103: Não Encontrado | G103: 109900 | H103: 0.6529 | I103: AUTO PEÇAS | K103: 8425.19.90 | L103: ANEXO I | P103: 8473.30.19 | Q103: Outros | R103: BIT | X103: 5 | Y103: 0.07
A104: 1704427 | B104: 0.4552 | C104: 0207.60.00 | D104: Não Encontrado | E104: Não Encontrado | G104: 109900 | H104: 0.6529 | I104: AUTO PEÇAS | K104: 8425.31.10 | L104: ANEXO I | P104: 8473.30.31 | Q104: Conjuntos cabeça-disco (HDA - Head Disk Assembly) de unidades de discos rígidos, montados | R104: BIT | X104: 6 | Y104: 0.07
A105: 1704500 | B105: 0.4552 | C105: 0208.10.00 | D105: Não Encontrado | E105: Não Encontrado | G105: 105400 | H105: 0.6529 | I105: AUTO PEÇAS | K105: 84253190 | L105: ANEXO I | P105: 8473.30.32 | Q105: Braços posicionadores de cabeças magnéticas | R105: BIT | X105: 7 | Y105: 0.07
A106: 1709700 | B106: 0.4552 | C106: 0208.30.00 | D106: Não Encontrado | E106: Não Encontrado | G106: 105500 | H106: 0.6529 | I106: AUTO PEÇAS | K106: 8425.39.10 | L106: ANEXO I | P106: 8473.30.33 | Q106: Cabeças magnéticas | R106: BIT | X106: 9 | Y106: 0.07
A107: 2000100 | B107: 0.5964 | C107: 0208.40.00 | D107: Não Encontrado | E107: Não Encontrado | G107: 110000 | H107: 0.6529 | I107: AUTO PEÇAS | K107: 8425.39.90 | L107: ANEXO I | P107: 8473.30.34 | Q107: Mecanismos bobinadores para unidades de fitas magnéticas (magnetic tape transporter) | R107: BIT | X107: 10 | Y107: 0.07
A108: 2000101 | B108: 0.5964 | C108: 0208.50.00 | D108: Não Encontrado | E108: Não Encontrado | G108: 105500 | H108: 0.6529 | I108: AUTO PEÇAS | K108: 8426.11.00 | L108: ANEXO I | P108: 8473.30.39 | Q108: Outras | R108: BIT | X108: 0 | Y108: 0.07
A109: 1708700 | B109: 0.4552 | C109: 0208.60.00 | D109: Não Encontrado | E109: Não Encontrado | G109: 105500 | H109: 0.6529 | I109: AUTO PEÇAS | K109: 8426.20.00 | L109: ANEXO I | P109: 8473.30.41 | Q109: Placas-mãe (mother boards) | R109: BIT
A110: 1708701 | B110: 0.4552 | C110: 0208.90.00 | D110: Não Encontrado | E110: Não Encontrado | G110: 105600 | H110: 0.6529 | I110: AUTO PEÇAS | K110: 8426.30.00 | L110: ANEXO I | P110: 8473.30.42 | Q110: Placas (módulos) de memória com uma superfície inferior ou igual a 50 cm2 | R110: BIT | Y110: INTERESTADUAL | Z110: INTERNO
...

Sheet CFOP Totais
A1: CFOP | B1: TOTAL
A2: 2403 | B2: =SUMIF(LerXml!$BG:$BG,'CFOP Totais'!$A2,LerXml!AI:AI)+SUMIF(LerXml!$BG:$BG,'CFOP Totais'!$A2,LerXml!W:W) -> 0
A3: 2102 | B3: =SUMIF(LerXml!$BG:$BG,'CFOP Totais'!$A3,LerXml!AI:AI)+SUMIF(LerXml!$BG:$BG,'CFOP Totais'!$A3,LerXml!W:W) -> 0
A4: 2407 | B4: =SUMIF(LerXml!$BG:$BG,'CFOP Totais'!$A4,LerXml!AI:AI)+SUMIF(LerXml!$BG:$BG,'CFOP Totais'!$A4,LerXml!W:W) -> 0
A5: 2556 | B5: =SUMIF(LerXml!$BG:$BG,'CFOP Totais'!$A5,LerXml!AI:AI)+SUMIF(LerXml!$BG:$BG,'CFOP Totais'!$A5,LerXml!W:W) -> 0
A6: 2910 | B6: =SUMIF(LerXml!$BG:$BG,'CFOP Totais'!$A6,LerXml!AI:AI)+SUMIF(LerXml!$BG:$BG,'CFOP Totais'!$A6,LerXml!W:W) -> 0
A7: 2949 | B7: =SUMIF(LerXml!$BG:$BG,'CFOP Totais'!$A7,LerXml!AI:AI)+SUMIF(LerXml!$BG:$BG,'CFOP Totais'!$A7,LerXml!W:W) -> 0
A8: 1403 | B8: =SUMIF(LerXml!$BG:$BG,'CFOP Totais'!$A8,LerXml!AI:AI)+SUMIF(LerXml!$BG:$BG,'CFOP Totais'!$A8,LerXml!W:W) -> 0
A9: 1102 | B9: =SUMIF(LerXml!$BG:$BG,'CFOP Totais'!$A9,LerXml!AI:AI)+SUMIF(LerXml!$BG:$BG,'CFOP Totais'!$A9,LerXml!W:W) -> 0
A10: 1910 | B10: =SUMIF(LerXml!$BG:$BG,'CFOP Totais'!$A10,LerXml!AI:AI)+SUMIF(LerXml!$BG:$BG,'CFOP Totais'!$A10,LerXml!W:W) -> 0
A11: 1949 | B11: =SUMIF(LerXml!$BG:$BG,'CFOP Totais'!$A11,LerXml!AI:AI)+SUMIF(LerXml!$BG:$BG,'CFOP Totais'!$A11,LerXml!W:W) -> 0
A12: Novo CFOP 1 | B12: =SUMIF(LerXml!$BG:$BG,'CFOP Totais'!$A12,LerXml!AI:AI)+SUMIF(LerXml!$BG:$BG,'CFOP Totais'!$A12,LerXml!W:W) -> 0
A13: Novo CFOP 2 | B13: =SUMIF(LerXml!$BG:$BG,'CFOP Totais'!$A13,LerXml!AI:AI)+SUMIF(LerXml!$BG:$BG,'CFOP Totais'!$A13,LerXml!W:W) -> 0
A14: Novo CFOP 3 | B14: =SUMIF(LerXml!$BG:$BG,'CFOP Totais'!$A14,LerXml!AI:AI)+SUMIF(LerXml!$BG:$BG,'CFOP Totais'!$A14,LerXml!W:W) -> 0
A15: Novo CFOP 4 | B15: =SUMIF(LerXml!$BG:$BG,'CFOP Totais'!$A15,LerXml!AI:AI)+SUMIF(LerXml!$BG:$BG,'CFOP Totais'!$A15,LerXml!W:W) -> 0
A16: Novo CFOP 5 | B16: =SUMIF(LerXml!$BG:$BG,'CFOP Totais'!$A16,LerXml!AI:AI)+SUMIF(LerXml!$BG:$BG,'CFOP Totais'!$A16,LerXml!W:W) -> 0
A17: Novo CFOP 6 | B17: =SUMIF(LerXml!$BG:$BG,'CFOP Totais'!$A17,LerXml!AI:AI)+SUMIF(LerXml!$BG:$BG,'CFOP Totais'!$A17,LerXml!W:W) -> 0
A18: Novo CFOP 7 | B18: =SUMIF(LerXml!$BG:$BG,'CFOP Totais'!$A18,LerXml!AI:AI)+SUMIF(LerXml!$BG:$BG,'CFOP Totais'!$A18,LerXml!W:W) -> 0

Sheet CFOP
A1: NFE | B1: TOTAL NFE | C1: 2403 | D1: 2102 | E1: 2407 | F1: 2556 | G1: 2910 | H1: 2949 | I1: 1403 | J1: 1102 | K1: 1910 | L1: 1949 | M1: NOVO CFOP 1 | N1: NOVO CFOP 2 | O1: NOVO CFOP 3
B2: =SUM(C2:L2) -> 0 | C2: =SUMIFS(LerXml!$AI:$AI,LerXml!$BG:$BG,C$1,LerXml!$B:$B,$A2)+SUMIFS(LerXml!$W:$W,LerXml!$BG:$BG,C$1,LerXml!$B:$B,$A2) -> 0 | D2: =SUMIFS(LerXml!$AI:$AI,LerXml!$BG:$BG,D$1,LerXml!$B:$B,$A2)+SUMIFS(LerXml!$W:$W,LerXml!$BG:$BG,D$1,LerXml!$B:$B,$A2) -> 0 | E2: =SUMIFS(LerXml!$AI:$AI,LerXml!$BG:$BG,E$1,LerXml!$B:$B,$A2)+SUMIFS(LerXml!$W:$W,LerXml!$BG:$BG,E$1,LerXml!$B:$B,$A2) -> 0 | F2: =SUMIFS(LerXml!$AI:$AI,LerXml!$BG:$BG,F$1,LerXml!$B:$B,$A2)+SUMIFS(LerXml!$W:$W,LerXml!$BG:$BG,F$1,LerXml!$B:$B,$A2) -> 0 | G2: =SUMIFS(LerXml!$AI:$AI,LerXml!$BG:$BG,G$1,LerXml!$B:$B,$A2)+SUMIFS(LerXml!$W:$W,LerXml!$BG:$BG,G$1,LerXml!$B:$B,$A2) -> 0 | H2: =SUMIFS(LerXml!$AI:$AI,LerXml!$BG:$BG,H$1,LerXml!$B:$B,$A2)+SUMIFS(LerXml!$W:$W,LerXml!$BG:$BG,H$1,LerXml!$B:$B,$A2) -> 0 | I2: =SUMIFS(LerXml!$AI:$AI,LerXml!$BG:$BG,I$1,LerXml!$B:$B,$A2)+SUMIFS(LerXml!$W:$W,LerXml!$BG:$BG,I$1,LerXml!$B:$B,$A2) -> 0 | J2: =SUMIFS(LerXml!$AI:$AI,LerXml!$BG:$BG,J$1,LerXml!$B:$B,$A2)+SUMIFS(LerXml!$W:$W,LerXml!$BG:$BG,J$1,LerXml!$B:$B,$A2) -> 0 | ... O2: =SUMIFS(LerXml!$AI:$AI,LerXml!$BG:$BG,O$1,LerXml!$B:$B,$A2)+SUMIFS(LerXml!$W:$W,LerXml!$BG:$BG,O$1,LerXml!$B:$B,$A2) -> 0
A3: 427530 | B3: =SUM(C3:L3) -> 0 | C3: =SUMIFS(LerXml!$AI:$AI,LerXml!$BG:$BG,C$1,LerXml!$B:$B,$A3)+SUMIFS(LerXml!$W:$W,LerXml!$BG:$BG,C$1,LerXml!$B:$B,$A3) -> 0 | D3: =SUMIFS(LerXml!$AI:$AI,LerXml!$BG:$BG,D$1,LerXml!$B:$B,$A3)+SUMIFS(LerXml!$W:$W,LerXml!$BG:$BG,D$1,LerXml!$B:$B,$A3) -> 0 | E3: =SUMIFS(LerXml!$AI:$AI,LerXml!$BG:$BG,E$1,LerXml!$B:$B,$A3)+SUMIFS(LerXml!$W:$W,LerXml!$BG:$BG,E$1,LerXml!$B:$B,$A3) -> 0 | F3: =SUMIFS(LerXml!$AI:$AI,LerXml!$BG:$BG,F$1,LerXml!$B:$B,$A3)+SUMIFS(LerXml!$W:$W,LerXml!$BG:$BG,F$1,LerXml!$B:$B,$A3) -> 0 | G3: =SUMIFS(LerXml!$AI:$AI,LerXml!$BG:$BG,G$1,LerXml!$B:$B,$A3)+SUMIFS(LerXml!$W:$W,LerXml!$BG:$BG,G$1,LerXml!$B:$B,$A3) -> 0 | H3: =SUMIFS(LerXml!$AI:$AI,LerXml!$BG:$BG,H$1,LerXml!$B:$B,$A3)+SUMIFS(LerXml!$W:$W,LerXml!$BG:$BG,H$1,LerXml!$B:$B,$A3) -> 0 | I3: =SUMIFS(LerXml!$AI:$AI,LerXml!$BG:$BG,I$1,LerXml!$B:$B,$A3)+SUMIFS(LerXml!$W:$W,LerXml!$BG:$BG,I$1,LerXml!$B:$B,$A3) -> 0 | J3: =SUMIFS(LerXml!$AI:$AI,LerXml!$BG:$BG,J$1,LerXml!$B:$B,$A3)+SUMIFS(LerXml!$W:$W,LerXml!$BG:$BG,J$1,LerXml!$B:$B,$A3) -> 0 | ... L3: =SUMIFS(LerXml!$AI:$AI,LerXml!$BG:$BG,L$1,LerXml!$B:$B,$A3)+SUMIFS(LerXml!$W:$W,LerXml!$BG:$BG,L$1,LerXml!$B:$B,$A3) -> 0
